Workbook

Sheet Cover Sheet 
B9: Clearinghouse: ESB Funding and Financing Opportunities
B11: Author: World Resources Institute
B12: Date of Data Extract: 01/11/2024
B15: Purpose: Support school districts in their search for ESB funding and financing
B16: Navigation: The public version of the Clearinghouse Excel Workbook contains the following spreadsheet tabs
B17: Cover Sheet provides introduction and context for the work (this tab)
B18: Clearinghouse contains the program information that has been collected as of the date specified on the Cover Sheet
B19: Definitions & Lists defines each variable collected and details data type (either a list of options or open-ended)
B20: Data Sources: Several resources were referenced to identify funding opportunities, but all information included here was drawn directly from publicly-available sources. Reference files included:
B21: Alternative Fuels Data Center (AFDC)
B22: Atlas EV Hub
B23: U.S. Department of Transportation EV Federal Funding and Financing Programs
... B29: This is a dynamic document and WRI welcomes any feedback or updates from users. Please send any notes to Michelle Levinson (michelle.levinson@wri.org).

Sheet Definitions & Lists
A1: Column Header | B1: Priority | C1: Name | D1: Category | E1: Type | F1: Funder Type | G1: Geography | H1: Maximum Allowance | I1: Unit of Max Allowance | J1: Match | K1: Eligible Sectors/Types | L1: EJ Approach | M1: EJ Criteria | N1: Scrappage | O1: Applicable Technologies | P1: Application Status | Q1: Notes | R1: Application Website | S1: Source/Reference | T1: Source/Reference (2) | U1: Source/Reference (3)
A2: Definition | B2: Order in which schools should conduct their funding search, where A - Programs that are a best fit for ESBs B - Programs not specific to ESBs, such as those focused on technologies, economic development & clean energy C - Programs that are dormant, where status is unknown, or information on how to access is unknown | C2: Name of the program | D2: Nature of assistance provided | E2: Specific form of assistance provided | F2: Type of organization or institution providing assistance | G2: Geographic area to which program applies. Note that users should be expansive in selecting the broadest set of geographies that are pertinent | H2: Maximum amount applicants can access through program | I2: Unit by which potential maximum amount awarded is measured | J2: Minimum cost-sharing percentage. Unless "N/A" is selected, applicants will need to cover some of the expenses but these may not be specified | K2: Project purpose or applicant type eligible for assistance | L2: Characterization of environmental justice approach in the application process, describing potential benefits/advantages for applicants who meet the EJ Criteria. Some programs may apply a combination of approaches, or a highly tailored approach not captured here. | M2: Criteria through which environmental justice approach is applied. Where no approach is employed, "n/a" is selected | N2: If program requires scrappage of an older polluting bus, and if so the nature of this requirement | O2: Types of expenses that assistance can be applied towards | P2: Nature of open period for program applications | Q2: Any other program details noted by data collection team | R2: Link where general information on program can be found | S2: Other source or reference materials, as available | T2: Other source or reference materials, as available | U2: Other source or reference materials, as available
B3: A | C3: (open ended) | D3: Funding | E3: Grant | F3: Federal | G3: Federal - competitive | H3: ($ per unit) | I3: per bus | J3: N/A | K3: School Buses only | L3: none | M3: Pollution burden | N3: Required | O3: Bus (&/or Battery) | P3: Rolling | Q3: (open ended) | R3: (open ended) | S3: (open ended) | T3: (open ended) | U3: (open ended)
B4: B | D4: Financing | E4: Rebate | F4: Utility | G4: Tribal Government or Indigenous Communities | H4: (% up to max) | I4: incremental cost | J4: (if yes) % or other amount (open-ended) | K4: MDHV vehicles only | L4: exclusive to | M4: Race/Ethinicity/Tribe | N4: Not required | O4: Charger | P4: Annual Window
B5: C | D5: Other | E5: Discount/point of sale coupon or voucher | F5: State | G5: AL | H5: Varies | I5: per charger | J5: (if yes, unspecified) some amount | K5: Any public fleet vehicle | L5: prioritization | M5: Income | O5: Charger & infrastructure | P5: Unknown
E6: Incentive | F6: VW Settlement | G6: AK | H6: N/A | I6: per port | K6: Any fleet vehicles | L6: extra funds | M6: All | O6: Bus & Charger
E7: Tax Credit | F7: City | G7: AZ | I7: per charging session | K7: EVs | M7: Pollution + Race/Ethinicity/Tribe | O7: Infrastructure
E8: Technical Assistance | F8: County | G8: AR | I8: per applicant | K8: Other | M8: Income + Race/Ethinicity/Tribe | O8: Workforce Training
E9: Equipment | F9: Regional jurisdiction | G9: CA | I9: per district | K9: Resilience investments or Infrastructure | M9: Pollution + Income | O9: Maintenance Cost
E10: Sales/use tax exemption | F10: Philanthropic | G10: CO | I10: per site | K10: Economic development investments | M10: n/a | O10: Anything
E11: Loan | F11: Commercial bank | G11: CT | I11: per project | K11: Disaster recovery investments | O11: Other
E12: Rate | F12: Venture investors | G12: DE | I12: per kwh | K12: Energy | O12: New Bus or Repower Bus
E13: Bill Credit | F13: Green/clean energy bank | G13: FL | I13: per gallon | K13: Technology innovation | O13: Repower Bus & Charger
E14: Law | G14: GA | I14: per month
E15: Penalty/disincentive | G15: HI | I15: per year
E16: Cost allowance | G16: ID | I16: per event
G17: IL | I17: N/A
G18: IN
G19: IA
G20: KS
G21: KY
G22: LA
G23: ME
G24: MD
G25: MA
G26: MI
G27: MN
G28: MS
G29: MO
... G63: Federal

Sheet Clearinghouse Official
A1: Priority | B1: Name | C1: Category | D1: Type | E1: Funder Type | F1: Geography | G1: Maximum Allowance | H1: Unit of Max Allowance | I1: Minimum Match Requirement | J1: Eligible Sectors/Types | K1: EJ Approach | L1: EJ Criteria | M1: Scrappage | N1: Applicable Technologies | O1: Application Status | P1: Notes | Q1: Program Website | R1: Source/Reference | S1: Source/Reference (2) | T1: Source/Reference (3)
A2: C | B2: Electric Vehicle Supply Equipment (EVSE) Funding Authorization | C2: Other | D2: Law | E2: State | F2: CO | G2: N/A | H2: N/A | I2: N/A | J2: EVs | K2: prioritization | L2: All | M2: Not required | N2: Bus & Charger | O2: Rolling | P2: Law provides new funding available for sustainable transportation. It creates three new transportation electrification enterprises: the Clean Transit Enterprise housed in the Colorado Department of Transportation (CDOT), the Clean Fleet Enterprise housed in the Colorado Department of Public Health and Environment (CDPHE), and the Community Access Enterprise housed in the Colorado Energy Office (CEO). | Q2: https://energyoffice.colorado.gov/about-us/boards-commissions/community-access-enterprise | R2: https://leg.colorado.gov/bills/sb21-260 | S2: Alternative Fuels Data Center: Electric Vehicle (EV) Charging Stations Funding Authorization (energy.gov)
A3: C | B3: Small-Scale Local Energy Loan Program | C3: Financing | D3: Loan | E3: State | F3: OR | G3: N/A | H3: N/A | I3: N/A | J3: Energy | K3: none | L3: n/a | M3: Not required | N3: Anything | O3: Unknown | P3: SELP is not currently accepting new loan applications. | Q3: https://www.oregon.gov/energy/incentives/pages/energy-loan-program.aspx
A4: B | B4: Community Project Funding | C4: Funding | D4: Grant | E4: Federal | F4: Federal | G4: N/A | H4: N/A | I4: N/A | J4: Other | K4: none | L4: n/a | M4: Not required | N4: Anything | O4: Annual Window | Q4: https://appropriations.house.gov/fiscal-year-2024-member-request-guidance | R4: Fact Sheet on Reforms 2023.pdf (house.gov) | S4: https://appropriations.house.gov/sites/democrats.appropriations.house.gov/files/Ag%20Request%20Guidance.pdf
A5: B | B5: Indian Energy Program | C5: Funding | D5: Grant | E5: Federal | F5: Tribal Government or Indigenous Communities | G5: N/A | H5: N/A | I5: N/A | J5: Other | K5: exclusive to | L5: Race/Ethinicity/Tribe | M5: Not required | N5: Anything | O5: Rolling | P5: No specific funding provided. Information of current funding opportunities from federal agencies and other entities for tribal energy projects development and deployment. | Q5: https://www.energy.gov/indianenergy/office-indian-energy-policy-and-programs | R5: Current Funding Opportunities | Department of Energy
A6: B | B6: Congestion Mitigation and Air Quality Improvement Program | C6: Funding | D6: Rebate | E6: Federal | F6: Federal - state admin | G6: N/A | H6: N/A | I6: N/A | J6: Any public fleet vehicle | K6: prioritization | L6: Pollution burden | M6: Not required | N6: Anything | O6: Annual Window | P6: CMAQ provides flexible funding to state and local governments for transportation projects. Schools should reach out to local and state government for funding. | Q6: https://www.law.cornell.edu/uscode/text/23/149 | R6: https://www.fhwa.dot.gov/bipartisan-infrastructure-law/cmaq.cfm | S6: CMAQ-Workbook-2022.pdf (ewgateway.org)
A7: C | B7: Alternative Fuel Vehicle Research and Development Funding | C7: Funding | D7: Incentive | E7: State | F7: NY | G7: N/A | H7: N/A | I7: N/A | J7: Any fleet vehicles | K7: prioritization | L7: Pollution + Income | M7: Not required | N7: Anything | O7: Unknown | P7: Broad category of funding for R&D; individual RFPs/funding opps are updated on the website under this umbrella with more specifics | Q7: https://www.nyserda.ny.gov/All-Programs/Clean-Transportation-Program
A8: A | B8: Alternative Fuels Incentive Grant Program | C8: Funding | D8: Rebate | E8: State | F8: PA | G8: 300000 | H8: incremental cost | I8: 0.5 | J8: Any fleet vehicles | K8: prioritization | L8: Income + Race/Ethinicity/Tribe | M8: Not required | N8: New Bus or Repower Bus | O8: Annual Window | P8: Program will reopen Spring 2024. It cannot be stacked with any VW funding. | Q8: https://www.dep.pa.gov/Citizens/GrantsLoansRebates/Alternative-Fuels-Incentive-Grant/Pages/default.aspx | R8: AFIG_Webinar_08162022.pptx (live.com)
A9: B | B9: SC Energy Efficiency Revolving Loan Program | C9: Financing | D9: Loan | E9: State | F9: SC | G9: 1000000 | H9: per applicant | I9: Yes, unspecified | J9: Energy | K9: none | L9: n/a | M9: Not required | N9: Anything | O9: Rolling | Q9: https://www.businessdevelopment.org/eerl.html | R9: https://www.businessdevelopment.org/eerl.html | S9: https://afdc.energy.gov/laws/11518
A10: A | B10: Government Alternative Fuel Vehicle (AFV) Incentive | C10: Funding | D10: Rebate | E10: Federal | F10: VA | G10: 10000 | H10: incremental cost | I10: Yes, unspecified | J10: Any public fleet vehicle | K10: prioritization | L10: Pollution burden | M10: Not required | N10: Bus (&/or Battery) | O10: Rolling | P10: Funding is currently available through September 30, 2024. Fleets that are interested in utilizing this Program for the purchase or conversion to new alternative fuel vehicles should first contact Alleyn Harned (540-568-8896) or Matt Wade (540-568-4051) with Virginia Clean Cities. | Q10: https://vacleancities.org/reports-2/cmaq-incentive-program/ | R10: https://vacleancities.org/wp-content/uploads/2023/12/CMAQ-Application-Package-Final-12_11_23.pdf | S10: https://afdc.energy.gov/laws/all?state=VA
A11: A | B11: Environmental Justice Small Grant Program | C11: Funding | D11: Grant | E11: Federal | F11: Federal - competitive | G11: 100000 | H11: per applicant | I11: Yes, unspecified | J11: Economic development investments | K11: exclusive to | L11: Income + Race/Ethinicity/Tribe | M11: Not required | N11: Anything | O11: Annual Window | P11: Restricted to federally recognized tribal goverments | Q11: https://www.epa.gov/environmentaljustice/environmental-justice-small-grants-program#Eligibility
A12: B | B12: Energy/Mineral Impact Assistance Fund Grant | C12: Funding | D12: Grant | E12: State | F12: CO | G12: 1000000 | H12: per applicant | I12: 0.5 | J12: Economic development investments | K12: prioritization | L12: Pollution + Income | M12: Not required | N12: Anything | O12: Annual Window | P12: The Energy/Mineral Impact Assistance Fund Grant (EIAF) program assists political subdivisions that are socially and/or economically impacted by the development, processing, or energy conversion of minerals and mineral fuels. | Q12: https://cdola.colorado.gov/funding-programs/energy/mineral-impact-assistance-fund-grant-eiaf | R12: https://cdola.colorado.gov/funding-programs/energy/mineral-impact-assistance-fund-grant-eiaf | S12: https://drive.google.com/file/d/16LBF9sUL6nx3cv1K0B73lTMgH1teAT9w/view
A13: A | B13: South Carolina Mini-Grants | C13: Funding | D13: Grant | E13: Federal | F13: SC | G13: 10000 | H13: per applicant | I13: Yes, unspecified | J13: Energy | K13: none | L13: n/a | M13: Not required | N13: Anything | O13: Annual Window | P13: No mentioned of EJ approach. | Q13: https://energy.sc.gov/programs/funding/mini-grant-program | S13: http://energy.sc.gov/files/view/Mini%20Grant%20Overview_2021_LM.pdf | T13: Alternative Fuels Data Center: Alternative Fuel Project Grants (energy.gov)
A14: C | B14: Indigenous Communities Program (American Rescue Plan) | C14: Funding | D14: Grant | E14: Federal | F14: Tribal Government or Indigenous Communities | G14: 5000000 | H14: per applicant | I14: Yes, unspecified | J14: Economic development investments | K14: exclusive to | L14: Race/Ethinicity/Tribe | M14: Not required | N14: Anything | O14: Unknown | P14: Last round closed April 2022. Funds have to be awarded by September 30, 2022. | Q14: https://eda.gov/arpa/indigenous/ | R14: Indigenous-Communities-webinar-slides.pdf (eda.gov) | S14: American Rescue Plan Indigenous Communities – Frequently Asked Questions - American Rescue Plan | U.S. Economic Development Administration (eda.gov)
A15: B | B15: State Economic & Infrastructure Development Investment Program | C15: Funding | D15: Grant | E15: Federal | F15: Regional - state admin | G15: 100000000 | H15: per applicant | I15: Yes, unspecified | J15: Economic development investments | K15: extra funds | L15: Income | M15: Not required | N15: Anything | O15: Annual Window | P15: Letters of interest by April 2023 | Q15: https://www.nbrc.gov/content/Catalyst | R15: NBRC Catalyst Program Overview.pdf
A16: B | B16: Inflation Reduction Act Community Change Grants Program | C16: Funding | D16: Grant | E16: Federal | F16: Federal - competitive | G16: 20000000 | H16: per applicant | I16: Yes, unspecified | J16: Resilience investments or Infrastructure | K16: exclusive to | L16: All | M16: Not required | N16: Anything | O16: Rolling | P16: Deadline November 2024 | Q16: https://www.epa.gov/inflation-reduction-act/inflation-reduction-act-community-change-grants-program | R16: https://www.epa.gov/system/files/documents/2023-12/epa-ira-oejecr-ccg-nofo-final-2023-12-20.pdf
A17: B | B17: State Energy Program | C17: Funding | D17: Grant | E17: Federal | F17: Federal - state admin | G17: Varies | H17: per applicant | I17: Yes, unspecified | J17: Energy | K17: prioritization | L17: All | M17: Not required | N17: Anything | O17: Annual Window | P17: Grant awarded only to states. | Q17: https://www.energy.gov/eere/wipo/state-energy-program-guidance | R17: SEP Program Notice 23-01 Program Year 2023 State Energy Program Formula Grant Application Instructions.pdf
A18: A | B18: Clean Air Grant | C18: Funding | D18: Grant | E18: VW Settlement | F18: NV | G18: 1 | H18: incremental cost | I18: Yes, unspecified | J18: MDHV vehicles only | K18: prioritization | L18: All | M18: Required | N18: New Bus or Repower Bus | O18: Annual Window | P18: Most recent round 2022. Upcoming funding expected | Q18: NV Clean Air Grant | R18: 2021 Application Form | S18: DEMF 2021 Competitive Application Webinar (nv.gov)
A19: C | B19: Clean Fuel Advanced Technology Project Grant Funding | C19: Funding | D19: Grant | E19: Federal | F19: NC | G19: 300000 | H19: per applicant | I19: 0.24 | J19: Other | K19: none | L19: n/a | M19: Not required | N19: Anything | O19: Unknown | P19: Last Round closed Sept. 2022. While there's no mentioned of EJ approach, the grant has to be implemented in pre-selected counties. | Q19: https://nccleantech.ncsu.edu/our-work/center-projects/cfat-project-request-for-proposals-information/ | R19: https://drive.google.com/file/d/1wnRhVO4Xd8ZsOnnVeZ0r2B9TAD7jdsHo/view | S19: https://afdc.energy.gov/fuels/laws/NG?state=NC
A20: B | B20: Community Facilities Direct Loan and Grant Program | C20: Financing | D20: Loan | E20: Federal | F20: Federal - competitive | G20: N/A | H20: N/A | I20: N/A | J20: Other | K20: extra funds | L20: Income | M20: Not required | N20: Anything | O20: Rolling | P20: Focused on rural communities. Applicants must show proof they cannot get a commercial loan. | Q20: https://www.rd.usda.gov/programs-services/community-facilities/community-facilities-direct-loan-grant-program#overview | R20: Community Facilities Direct Loan Program (usda.gov)
A21: B | B21: Congressionally Directed Spending | C21: Funding | D21: Grant | E21: Federal | F21: Federal | G21: N/A | H21: N/A | I21: N/A | J21: Other | K21: none | L21: n/a | M21: Not required | N21: Anything | O21: Annual Window | P21: Schools are encourage to contact their senate representative. | Q21: https://www.appropriations.senate.gov/congressionally-directed-spending-requests
A22: C | B22: Alternative Fuel Vehicles and Infrastructure Grant Program (ALT Fuels Colorado) | C22: Funding | D22: Rebate | E22: VW Settlement | F22: CO | G22: 1.17 | H22: incremental cost | I22: Yes, unspecified | J22: MDHV vehicles only | K22: none | L22: n/a | M22: Required | N22: Bus (&/or Battery) | O22: Unknown | P22: Most recent round was 2021. As of January 2022, all funding allocated has been distributed. Future funding opportunities will be offered & managed by the Colorado Department of Public Health & Environment (CDPHE) Clean Fleet Enterprise. No information on future programs. | Q22: https://raqc.org/program/alt-fuels-colorado/#:~:text=The%20Program%20ALT%20Fuels%20Colorado%20removes%20barriers%20to,AFVs%20by%20providing%20incentives%20to%20offset%20incremental%20costs. | R22: AFC Program Guide.pdf (egnyte.com) | S22: https://afdc.energy.gov/laws/11489
A23: A | B23: ConserFund | C23: Financing | D23: Loan | E23: State | F23: SC | G23: 500000 | H23: per district | I23: Yes, unspecified | J23: Energy | K23: none | L23: n/a | M23: Not required | N23: Anything | O23: Rolling | P23: 1.5% interest rate | Q23: https://energy.sc.gov/programs/funding/loans/conserfund | R23: http://www.energy.sc.gov/incentives/conserfund | S23: http://www.energy.sc.gov/files/CF%20FAQ%27s%20-%20Basics%20-10.07.2020_0.pdf | T23: https://afdc.energy.gov/laws/11517
A24: C | B24: Clean Fuels Incentive Program | C24: Funding | D24: Grant | E24: State | F24: MD | G24: 150000 | H24: incremental cost | I24: Yes, unspecified | J24: Any fleet vehicles | K24: prioritization | L24: All | M24: Not required | N24: Bus (&/or Battery) | O24: Unknown | P24: Vehicles associated with the replacement or retirement of existing gas/diesel vehicles will be viewed more favorably during the application process. Applications closed 2022. | Q24: https://energy.maryland.gov/transportation/Pages/Clean-Fuels-Incentive-Program.aspx | R24: FY23 CFIP FOA Final.docx (maryland.gov)
A25: A | B25: AFV Mechanic Training Program | C25: Funding | D25: Grant | E25: State | F25: CA | G25: 15000 | H25: per applicant | I25: Yes, unspecified | J25: Any fleet vehicles | K25: none | L25: n/a | M25: Not required | N25: Workforce Training | O25: Rolling | P25: This is strictly a training program. | Q25: http://valleyair.org/grants/mechanictraining.htm | R25: Alt Fuel Mech Trng Guidelines Document Revised.PDF (valleyair.org)
A26: C | B26: Transportation Electrification Infrastructure Projects | C26: Other | D26: Law | E26: State | F26: IL | G26: N/A | H26: N/A | I26: N/A | J26: Any fleet vehicles | K26: prioritization | L26: Pollution burden | M26: Not required | N26: Bus (&/or Battery) | O26: Rolling | P26: Law that provides funding to the Environmental Protection Agency for grants for transportation electrification infrastructure projects; including, but not limited to grants for the purpose of encouraging electric vehicle charging infrastructure, prioritizing investments in medium and heavy-duty charging, and electrifying public transit, fleets, and school buses. | Q26: https://www.ilga.gov/legislation/publicacts/101/PDF/101-0029.pdf | R26: Alternative Fuels Data Center: Transportation Electrification Infrastructure Projects (energy.gov)
A27: A | B27: Literary Funds Loans | C27: Financing | D27: Loan | E27: State | F27: VA | G27: 25000000 | H27: per applicant | I27: Yes, unspecified | J27: School Buses only | K27: none | L27: n/a | M27: Not required | N27: Anything | O27: Annual Window | P27: Most recent round closed Nov 16, 2023 (opened Sept 21, 2023 - small window). Pursuant to the appropriation act, the Department of Education shall conduct an annual open enrollment process for loan applications. | Q27: https://www.doe.virginia.gov/programs-services/school-operations-support-services/facility-construction-maintenance/literary-fund-loans | R27: https://lis.virginia.gov/cgi-bin/legp604.exe?071+ful+CHAP0121&071+ful+CHAP0121 | S27: https://law.lis.virginia.gov/vacode/title22.1/chapter10/section22.1-146/ | T27: Superintendent’s Memo #273-22 (virginia.gov)
A28: C | B28: New York State’s Beneficiary Mitigation Plan | C28: Funding | D28: Incentive | E28: VW Settlement | F28: NY | G28: N/A | H28: N/A | I28: N/A | J28: MDHV vehicles only | K28: prioritization | L28: Pollution burden | M28: Not required | N28: New Bus or Repower Bus | O28: Unknown | P28: It seems all VW funds were awarded: At this time, there are no plans to reopen the application process. | Q28: https://www.dec.ny.gov/chemical/109784.html
A29: C | B29: Funds for School District Alternative Fuel Use | C29: Other | D29: Law | E29: State | F29: NV | G29: N/A | H29: N/A | I29: N/A | J29: School Buses only | K29: none | L29: n/a | M29: Not required | N29: Bus & Charger | O29: Rolling | P29: Violations of air pollution control laws will lead to fines that school districts receive, local air pollution control board approves what $ can be spent on; repowers specifically named | Q29: https://www.leg.state.nv.us/NRS/NRS-445B.html#NRS445BSec500 | R29: https://afdc.energy.gov/fuels/laws/NG?state=NV#:~:text=%28Reference%20Nevada%20Revised%20Statutes484A.463%29%20Funds%20for%20School%20District,county%20school%20district%20fund%20where%20the%20violation%20occurred.
A30: A | B30: Clean Diesel Grant Program | C30: Funding | D30: Rebate | E30: VW Settlement | F30: SD | G30: 0.45 | H30: per applicant | I30: 0.55 | J30: MDHV vehicles only | K30: none | L30: n/a | M30: Required | N30: Bus & Charger | O30: Annual Window | P30: Closed Dec 8 2023. Clean Diesel Grant Program utilizes funding from VW and DERA to replace diesel buses. | Q30: https://danr.sd.gov/Environment/AirQuality/CleanDieselProgram/default.aspx | R30: https://danr.sd.gov/Environment/AirQuality/CleanDieselProgram/docs/R14App.pdf | S30: https://afdc.energy.gov/laws/12401
A31: A | B31: Diesel Emission Reduction Project Funding (DERA) | C31: Funding | D31: Grant | E31: Federal | F31: IA | G31: 0.45 | H31: per applicant | I31: 0.55 | J31: MDHV vehicles only | K31: prioritization | L31: Pollution burden | M31: Required | N31: Bus (&/or Battery) | O31: Annual Window | P31: Closed Oct 2023. The replaced bus must be scrapped or permanently disabled within ninety (90) days of being replaced. | Q31: https://iowadot.gov/dera/Application-Process | R31: https://iowadot.gov/dera/pdfs/DERA-Grant-Program-Information-Guide-2023.pdf | S31: https://afdc.energy.gov/laws/12125
A32: A | B32: North Carolina Mobile Source Emissions Reduction Grant | C32: Funding | D32: Grant | E32: State | F32: NC | G32: 0.45 | H32: per applicant | I32: 0.65 | J32: Any fleet vehicles | K32: prioritization | L32: Pollution + Income | M32: Required | N32: New Bus or Repower Bus | O32: Annual Window | P32: Application open November 2023 and close Feb 2024. EJ Criteria varies. Also includes minority-owned, etc. depending on which part of DERA funding applicant is applying for | Q32: https://deq.nc.gov/about/divisions/air-quality/motor-vehicles-and-air-quality/mobile-sources-emissions-reductions-grant | R32: open (nc.gov)
A33: A | B33: Vermont Diesel Emissions Reduction Financial Assistance (DERA) | C33: Funding | D33: Grant | E33: Federal | F33: VT | G33: 0.45 | H33: per applicant | I33: 0.55 | J33: MDHV vehicles only | K33: prioritization | L33: Pollution + Income | M33: Required | N33: New Bus or Repower Bus | O33: Annual Window | P33: Most recent round closed Dec. 2023. Application done through Vermont Business Assistance Network | Q33: https://dec.vermont.gov/air-quality/mobile-sources/diesel-emissions/vt-diesel-grant | R33: 2021-2022 Diesel Emissions Reduction Act (DERA) State Grants Program Guide (EPA-420-B-22-023, April 2022) (vermont.gov) | S33: https://afdc.energy.gov/laws/12003
A34: C | B34: Alternative Fuel and Alternative Fuel Vehicle (AFV) Fund | C34: Other | D34: Law | E34: State | F34: NC | G34: N/A | H34: N/A | I34: N/A | J34: Any public fleet vehicle | K34: none | L34: n/a | M34: Not required | N34: Bus (&/or Battery) | O34: Rolling | P34: The North Carolina State Energy Office administers the Energy Policy Act (EPAct) Credit Banking and Selling Program, which enables the state to generate funds from the sale of EPAct 1992 credits. The funds that EPAct credit sales generate are deposited into the Alternative Fuel Revolving Fund (Fund) for state agencies to offset the incremental costs of purchasing biofuel or electric vehicles. | Q34: https://law.justia.com/codes/north-carolina/2012/chapter-143/article-3/section-143-58.5/ | R34: https://afdc.energy.gov/fuels/laws/NG?state=NC
A35: C | B35: Vehicle Emissions Reduction and Electric Vehicle Supply Equipment (EVSE) Project Funding | C35: Funding | D35: Grant | E35: VW Settlement | F35: LA | G35: N/A | H35: N/A | I35: N/A | J35: Any fleet vehicles | K35: prioritization | L35: Pollution burden | M35: Required | N35: Bus (&/or Battery) | O35: Unknown | P35: It seems all VW funds were awarded (2022): At this time, there are no plans to reopen the application process. | Q35: https://deq.louisiana.gov/page/louisiana-volkswagen-environmental-mitigation-trust
A36: C | B36: Diesel Emissions Reduction Act Tribal and Insular Areas Grants (DERA) | C36: Funding | D36: Grant | E36: Federal | F36: Tribal Government or Indigenous Communities | G36: 800000 | H36: per applicant | I36: Yes, unspecified | J36: Any fleet vehicles | K36: prioritization | L36: Pollution + Income | M36: Required | N36: New Bus or Repower Bus | O36: Unknown | P36: Most recent round closed Oct. 2022 | Q36: https://www.epa.gov/dera/tribal-insulararea
A37: A | B37: Plug-In Electric Vehicle (PEV) Time-Of-Use (TOU) - NV Energy | C37: Other | D37: Rate | E37: Utility | F37: NV | G37: Varies | H37: per applicant | I37: N/A | J37: EVs | K37: none | L37: n/a | M37: Not required | N37: Maintenance Cost | O37: Rolling | P37: Must participate for 1 year, can switch to regular cost if not satisfied after 1 year; TOU for off-peak charging | Q37: https://www.nvenergy.com/account-services/energy-pricing-plans/time-of-use/sign-up-residential | R37: https://www.nvenergy.com/account-services/energy-pricing-plans/electric-vehicle
A38: C | B38: Medium- and Heavy-Duty Grant Program | C38: Funding | D38: Grant | E38: VW Settlement | F38: IN | G38: 0.75 | H38: per applicant | I38: Yes, unspecified | J38: Any public fleet vehicle | K38: prioritization | L38: Pollution burden | M38: Required | N38: Bus (&/or Battery) | O38: Unknown | P38: Most recent round was 2022 | Q38: https://www.in.gov/idem/airquality/volkswagen-mitigation-trust/ | R38: https://afdc.energy.gov/laws/12180 | S38: https://www.in.gov/idem/airquality/files/vw_trust_decree_apndx_d2.pdf
A39: A | B39: Diesel Emissions Reduction Act National Grants (DERA) | C39: Funding | D39: Grant | E39: Federal | F39: Federal - competitive | G39: Varies | H39: per applicant | I39: Yes, unspecified | J39: Any fleet vehicles | K39: prioritization | L39: Pollution + Income | M39: Required | N39: Bus (&/or Battery) | O39: Annual Window | P39: Application opened Aug 2023, closed Dec 1, 2023 | Q39: https://www.epa.gov/grants/2022-2023-diesel-emissions-reduction-act-dera-national-grants | R39: https://www.epa.gov/system/files/documents/2023-08/dera-national-program-nofo-fY22-fY23-final-8-1-23-v4.pdf
A40: A | B40: Georgia Converted Vehicle and EV Charger Tax Credits | C40: Funding | D40: Tax Credit | E40: State | F40: GA | G40: 2500 | H40: per bus | I40: 0.9 | J40: Any fleet vehicles | K40: none | L40: n/a | M40: Not required | N40: Repowered Bus & Charger | O40: Rolling | P40: Tax credit is still available for vehicles converted to alternative fuels. The LEV/ZEV and MDV/HDV tax credits were discontinued effective July 1, 2015. | Q40: https://epd.georgia.gov/forms-permits/air-protection-branch-forms-permits/clean-vehicle-tax-credits | R40: https://afdc.energy.gov/laws/13209
A41: B | B41: Alternative Fuel Vehicle (AFV) and Fueling Infrastructure Loans | C41: Financing | D41: Loan | E41: State | F41: NE | G41: 500000 | H41: per applicant | I41: Yes, unspecified | J41: Energy | K41: none | L41: n/a | M41: Not required | N41: Bus (&/or Battery) | O41: Rolling | P41: Schools qualify for 1% interest rate | Q41: https://neo.ne.gov/programs/loans/loans.html#item-02 | R41: schooldistricts.pdf (ne.gov) | S41: https://afdc.energy.gov/fuels/laws/HY?state=ne
A42: A | B42: Alternative Fuel Schoool Bus Program | C42: Funding | D42: Rebate | E42: VW Settlement | F42: OK | G42: 0.75 | H42: per applicant | I42: 0.25 | J42: MDHV vehicles only | K42: prioritization | L42: Pollution burden | M42: Required | N42: Bus & Charger | O42: Annual Window | P42: Applications closed Jan. 2023. | Q42: https://www.deq.ok.gov/wp-content/uploads/air-division/VW_AFSB_FY20_Grant_Solicitation.pdf | R42: Alternative Fuel School Bus Program - Oklahoma Department of Environmental Quality | S42: https://afdc.energy.gov/laws/12081
A43: A | B43: Reduce Emissions from Diesels (DERA) | C43: Funding | D43: Grant | E43: Federal | F43: AR | G43: 400000 | H43: per applicant | I43: 0.55 | J43: MDHV vehicles only | K43: prioritization | L43: Pollution burden | M43: Required | N43: Bus (&/or Battery) | O43: Annual Window | P43: Opened Fall 2022, monthly rolling deadline for proposal submissions (4:30 p.m. CST on the last day of each following month) until all funds are awarded or October 31, 2023. Closed | Q43: https://www.adeq.state.ar.us/air/planning/gored/ | R43: https://www.adeq.state.ar.us/air/planning/gored/pdfs/Go_RED_Applicant_Guide_2021.pdf | S43: https://www.adeq.state.ar.us/poa/pi/emaillist_subscribe.aspx?ml=CleanDieselFunding_emaillist&t=s&Submit=Subscribe
A44: A | B44: Pennsylvania Onroad Rebate Program | C44: Funding | D44: Rebate | E44: VW Settlement | F44: PA | G44: 156000 | H44: per applicant | I44: 0.4 | J44: MDHV vehicles only | K44: prioritization | L44: Income | M44: Required | N44: New Bus or Repower Bus | O44: Annual Window | P44: Applications for FYs 23-24 opened November 2023 and awarded on a rolling basis. | Q44: https://www.dep.pa.gov/Business/Air/Volkswagen/Pages/Driving-PA-Forward-Grant-and-Rebate-Awards.aspx | R44: OnroadRebateProgramGuidelines.pdf (state.pa.us)
A45: A | B45: Diesel Emission Reduction Grant | C45: Funding | D45: Rebate | E45: Federal | F45: OH | G45: 2000000 | H45: per applicant | I45: 0.2 | J45: MDHV vehicles only | K45: exclusive to | L45: Pollution burden | M45: Required | N45: Bus (&/or Battery) | O45: Annual Window | P45: The 2023 application cycle opened October 6, with a deadline on Friday November 17 at 5:00 p.m. | Q45: https://epa.ohio.gov/divisions-and-offices/environmental-education/grant-programs/diesel-emission-reduction-grants | R45: DERG-RFPandApplication.pdf (ohio.gov)
A46: C | B46: Smart Grid Infrastructure Development and Support | C46: Other | D46: Law | E46: State | F46: IL | G46: N/A | H46: N/A | I46: N/A | J46: Technology innovation | K46: none | L46: n/a | M46: Not required | N46: Bus (&/or Battery) | O46: Rolling | P46: The Illinois Science and Energy Innovation Trust (Trust) will provide financial and technical support to public and private entities within the state for programs and projects that support, encourage, or utilize innovative technologies and methods to modernize the state’s electric grid. Technologies may include advanced electricity storage and peak-shaving technologies, such as electric vehicles (EV) or devices that allow EVs to engage in smart grid functions. No information on application process or funding eligibility | Q46: https://www.ilga.gov/legislation/ilcs/fulltext.asp?DocName=022000050K16-108.5 | R46: Alternative Fuels Data Center: Illinois Laws and Incentives (energy.gov)
A47: C | B47: Pennsylvania Truck and Bus Fleet Grant Program | C47: Funding | D47: Grant | E47: VW Settlement | F47: PA | G47: 150000 | H47: per bus | I47: 0.4 | J47: MDHV vehicles only | K47: prioritization | L47: Pollution + Income | M47: Required | N47: New Bus or Repower Bus | O47: Unknown | P47: No funds remaining for this program. | Q47: Homepage - Driving PA Forward | R47: TruckBusFleetGrantProgramGuidelines.pdf (state.pa.us) | S47: Webinar - Overview and Application Process - Oct 2020
A48: C | B48: Diesel Vehicle Retrofit and Improvement Grants | C48: Funding | D48: Grant | E48: State | F48: IN | G48: 1000000 | H48: per applicant | I48: 0.25 | J48: MDHV vehicles only | K48: prioritization | L48: Pollution + Income | M48: Required | N48: Bus (&/or Battery) | O48: Unknown | P48: Applications closed in Dec. 2022 | Q48: https://www.in.gov/idem/airquality/dieselwise/ | R48: AGENCY: (in.gov)
A49: C | B49: Medium- and Heavy-Duty Diesel Vehicle Replacement Rebates | C49: Funding | D49: Grant | E49: VW Settlement | F49: ID | G49: N/A | H49: N/A | I49: N/A | J49: Any fleet vehicles | K49: none | L49: n/a | M49: Not required | N49: Bus + Charger | O49: Unknown | P49: Last round was 2022 | Q49: https://www.deq.idaho.gov/air-quality/improving-air-quality/volkswagen-and-diesel-funding/
A50: A | B50: Ohio VW Mitigation Grant - Request for Application | C50: Funding | D50: Grant | E50: VW Settlement | F50: OH | G50: 2000000 | H50: per applicant | I50: 0.25 | J50: MDHV vehicles only | K50: prioritization | L50: Income | M50: Required | N50: Bus (&/or Battery) | O50: Annual Window | P50: For 2023 application cycle, there is funding available for purchase of electric school bus and infrastructure. Public school district owners of eligible buses are able to be reimbursed for up to 75% of the electric school bus (not to exceed $375,000 per vehicle) | Q50: https://epa.ohio.gov/divisions-and-offices/environmental-education/grant-programs/vw-mitigation-grants#2021Offerings | R50: https://epa.ohio.gov/static/Portals/42/documents/VW/DMTF-RFA-June2023.pdf
A51: A | B51: Electric Vehicle (EV) Charging Station Rebates - Iowa Association of Electric Cooperatives (IAEC) | C51: Funding | D51: Rebate | E51: Utility | F51: IA | G51: Varies | H51: per applicant | I51: Yes, unspecified | J51: EVs | K51: none | L51: n/a | M51: Not required | N51: Charger | O51: Rolling | P51: Offerings vary depending on member cooperative. Please check with your local cooperative for any rebates they offer. | Q51: https://www.iowarec.org/iowa-co-ops/our-members | R51: Alternative Fuels Data Center: Electric Vehicle (EV) Charging Station Rebates - Iowa Association of Electric Cooperatives (IAEC) (energy.gov)
A52: C | B52: Utility Electric Vehicle Supply Equipment (EVSE) Programs Authorization | C52: Other | D52: Law | E52: State | F52: NY | G52: N/A | H52: N/A | I52: N/A | J52: MDHV vehicles only | K52: extra funds | L52: Income + Race/Ethinicity/Tribe | M52: Not required | N52: Charger & infrastructure | O52: Rolling | P52: General law that allows for the other funding opportunities. This program has many programs within it; recommend downloading the link listed on the source to read the law text. | Q52: https://afdc.energy.gov/laws/12481
A53: C | B53: Central Coast Incentive Project | C53: Funding | D53: Rebate | E53: State | F53: CA | G53: 5000 | H53: per charger | I53: Yes, unspecified | J53: EVs | K53: extra funds | L53: Pollution + Income | M53: Not required | N53: Charger & infrastructure | O53: Unknown | P53: The Central Coast Incentive Project is no longer accepting applications, but more rebates might be available through CALeVIP. | Q53: https://calevip.org/incentive-project/central-coast | R53: What is the Central Coast Incentive Project? | CALeVIP
A54: A | B54: Electric Vehicle (EV) and Infrastructure Coaching Service | C54: Other | D54: Technical Assistance | E54: State | F54: CO | G54: N/A | H54: N/A | I54: N/A | J54: EVs | K54: none | L54: n/a | M54: Not required | N54: Workforce Training | O54: Rolling | P54: ReCharge provides coaching services to consumers, local governments, workplaces, and multi-unit dwellings to help them identify monetary savings, grant opportunities, and other EV benefits. | Q54: https://energyoffice.colorado.gov/zero-emission-vehicles/recharge-colorado | R54: recharge_flyer_3.31.22_final.pdf - Google Drive
A55: A | B55: Entergy fleet electrification incentives | C55: Other | D55: Technical Assistance | E55: Utility | F55: AR | G55: N/A | H55: N/A | I55: N/A | J55: Any fleet vehicles | K55: none | L55: n/a | M55: Not required | N55: Charger + infrastructure | O55: Rolling | P55: Contact company for a consulation before applying. MULTIPLE STATES - not just TX. Mentions school districts in "transit" on fleet electrification page. | Q55: https://entergyetech.com/truck-stop-fleet-electrification/ | R55: EV Charging Service Guide.pdf (entergy.com)
A56: A | B56: Electric Equipment and Electric Vehicle Supply Equipment (EVSE) Incentive - Entergy | C56: Other | D56: Equipment | E56: Utility | F56: LA | G56: N/A | H56: N/A | I56: N/A | J56: Any fleet vehicles | K56: none | L56: n/a | M56: Not required | N56: Charger + infrastructure | O56: Rolling | P56: Contact company for a consulation before applying. MULTIPLE STATES - not just TX. Mentions school districts in "transit" on fleet electrification page. | Q56: https://entergyetech.com/truck-stop-fleet-electrification/
A57: A | B57: Fleet Electrification Assessment Central Hudson | C57: Other | D57: Technical Assistance | E57: Utility | F57: NY | G57: N/A | H57: N/A | I57: N/A | J57: MDHV vehicles only | K57: prioritization | L57: Pollution + Income | M57: Not required | N57: Infrastructure | O57: Rolling | P57: You must be an operator of a light, medium, or heavy-duty vehicle fleet operator within the territory of Central Hudson. Services include: Total cost of ownership comparisons per vehicle, Forecast of fleet-wide cost of operation and savings, Evaluation of multi-year procurement plans specific to your fleet, Emission reduction potential associated with converting your fleet | Q57: https://www.cenhud.com/en/my-energy/electric-vehicles/green-your-fleet/fleet-assessment-services/
A58: C | B58: Public Plug-In Electric Vehicle Charging Rate Pilot Program | C58: Other | D58: Rate | E58: Utility | F58: CT | G58: N/A | H58: N/A | I58: N/A | J58: EVs | K58: none | L58: n/a | M58: Not required | N58: Maintenance Cost | O58: Unknown | P58: This voluntary rate program is available to any level 2 or level 3 charging station whose load is separately metered and available for use by the public. Eligibility for this rate is subject to the review and approval of Eversource. | Q58: https://www.eversource.com/content/residential/account-billing/manage-bill/about-your-bill/rates-tariffs/electric-vehicle-rate-program#:~:text=Connecticut%20Electric%20Vehicle%20Rate%20Program%20The%20Electric%20Vehicle,metered%20and%20available%20for%20use%20by%20the%20public. | R58: https://www.eversource.com/content/ct-c/business/my-account/billing-payments/about-your-bill/rates-tariffs/electric-vehicle-rate-program | S58: https://afdc.energy.gov/laws/12417
A59: A | B59: Clean Transportation Program | C59: Funding | D59: Incentive | E59: State | F59: CA | G59: N/A | H59: N/A | I59: N/A | J59: MDHV vehicles only | K59: prioritization | L59: All | M59: Not required | N59: Bus & Charger | O59: Annual Window | P59: The Clean Transportation Program invests up to $100 million annually in a broad portfolio of transportation and fuel transportation projects throughout the state. The Energy Commission leverages public and private investments to support adoption of cleaner transportation powered by alternative and renewable fuels. | Q59: https://www.energy.ca.gov/programs-and-topics/programs/clean-transportation-program | R59: Clean Transportation Program Overview (ca.gov) | S59: 2022-2023 Investment Plan Update (ca.gov) | T59: Clean Transportation Program (arcgis.com)
A60: A | B60: National Grid - Fleet Electrification Assessment | C60: Other | D60: Technical Assistance | E60: Utility | F60: NY | G60: N/A | H60: N/A | I60: N/A | J60: Any fleet vehicles | K60: prioritization | L60: Pollution + Income | M60: Not required | N60: Infrastructure | O60: Rolling | P60: National Grid offers fleet assessment and make ready funding. Participation in NYTVIP required for make ready funding. | Q60: https://www.nationalgridus.com/ev-fleet-hub/Get-Started/Fleet-Advisory-Services-Program
A61: A | B61: Electric Vehicle (EV) Leasing Program - Orlando Utilities Commission (OUC) | C61: Funding | D61: Incentive | E61: Utility | F61: FL | G61: 1 | H61: per applicant | I61: Yes, unspecified | J61: EVs | K61: none | L61: n/a | M61: Not required | N61: Charger | O61: Rolling | P61: Infrastructure incentives from 50% to 100%, depending on eligibility. | Q61: https://www.ouc.com/business/commercial-ev-charging-service | R61: commercial_ev_brochure.pdf (ouc.com)
A62: A | B62: Non-Residential Electric Vehicle (EV) Make-Ready Grant - Rocky Mountain Power | C62: Other | D62: Technical Assistance | E62: Utility | F62: UT | G62: N/A | H62: N/A | I62: N/A | J62: EVs | K62: none | L62: n/a | M62: Not required | N62: Infrastructure | O62: Rolling | P62: Single port: $1,000 per charger up to 75% of total charger cost Multi-port: $1,500 per charger up to 75% of total charger cost | Q62: https://www.rockymountainpower.net/savings-energy-choices/electric-vehicles/utah-commercial-incentives.html | R62: https://www.rockymountainpower.net/content/dam/pcorp/documents/en/rockymountainpower/savings-energy-choices/electric-vehicles/AC_Level_2_Application.docx | S62: Alternative Fuels Data Center: Non-Residential Electric Vehicle (EV) Make-Ready Grant – Rocky Mountain Power (energy.gov)
A63: A | B63: Fleet Electrification Assessment National Grid | C63: Other | D63: Technical Assistance | E63: Utility | F63: MA | G63: N/A | H63: N/A | I63: N/A | J63: Any public fleet vehicle | K63: none | L63: n/a | M63: Not required | N63: Infrastructure | O63: Rolling | P63: Eligible applicants must be National Grid customers and include municipal, school bus, public transit, and state and federal government fleets. | Q63: https://fleetadvisoryma.nationalgrid.com/about-program | R63: Moving Your Fleet Forward with Electric Vehicles (EVs) (nationalgrid.com)
A64: A | B64: RI Diesel Emissions Reduction Act (DERA) | C64: Funding | D64: Grant | E64: Federal | F64: RI | G64: 0.45 | H64: per bus | I64: 0.55 | J64: MDHV vehicles only | K64: prioritization | L64: Income + Race/Ethinicity/Tribe | M64: Required | N64: New Bus or Repower Bus | O64: Annual Window | P64: September 06, 2023 – Request for Proposals and application is released, Closed October 06, 2023. For ESBs, "We will only accept applications for school bus replacement projects if they are zero-emission (ZEV) replacements, including all-electric and fuel cell vehicles. We will also accept applications for school bus engine swaps from a diesel engine to a ZEV engine and chassis." Repowers were eligible! | Q64: https://dem.ri.gov/environmental-protection-bureau/air-resources/mobile-sources/diesel-emissions-reduction-act-dera | R64: https://dem.ri.gov/sites/g/files/xkgbur861/files/2022-10/FY2022%20State%20DERA%20RFP%20FINAL.pdf
A65: C | B65: Diesel Emissions Mitigation Program - EVSE | C65: Funding | D65: Rebate | E65: VW Settlement | F65: CT | G65: 0.65 | H65: per applicant | I65: 0.35 | J65: Any fleet vehicles | K65: prioritization | L65: Income | M65: Not required | N65: Charger | O65: Unknown | P65: Closed Aug. 2022 | Q65: https://portal.ct.gov/DEEP/Air/Mobile-Sources/VW/VW-Settlement---Grants | R65: PowerPoint Presentation (ct.gov) | S65: https://afdc.energy.gov/laws/11973 | T65: https://portal.ct.gov/DEEP/Air/Mobile-Sources/VW/VW-Settlement---FAQ
A66: A | B66: Fleet Electrification Assessment Consumers Energy | C66: Other | D66: Technical Assistance | E66: Utility | F66: MI | G66: N/A | H66: N/A | I66: N/A | J66: Any fleet vehicles | K66: none | L66: n/a | M66: Not required | N66: Infrastructure | O66: Rolling | P66: Eligible applicants must be Consumers. Energy customers and include any organization with light, medium, or heavy-duty fleet vehicles. | Q66: https://www.consumersenergy.com/business/products-and-services/powermifleet#eligibility-requirements-section
A67: A | B67: Fleet Electrification Assessment Duquesne Light Company (DLC) | C67: Other | D67: Technical Assistance | E67: Utility | F67: PA | G67: N/A | H67: N/A | I67: N/A | J67: Any fleet vehicles | K67: prioritization | L67: All | M67: Not required | N67: Infrastructure | O67: Rolling | P67: This program will roadmap towards fleet electrification and help you determine if you qualify for incentives. | Q67: https://www.duquesnelight.com/energy-money-savings/electric-vehicles/electricfleet#undefined
A68: B | B68: Disaster Relief Fund (American Rescue Plan) | C68: Funding | D68: Grant | E68: Federal | F68: Federal - competitive | G68: Varies | H68: per applicant | I68: Yes, unspecified | J68: Disaster recovery investments | K68: none | L68: n/a | M68: Not required | N68: Infrastructure | O68: Rolling | P68: The Disaster Relief Fund (DRF) is an appropriation against which FEMA can direct, coordinate, manage, and fund eligible response and recovery efforts associated with domestic major disasters and emergencies. Given the grant is given in response to natural disasters, there's no EJ approach. | Q68: https://www.fema.gov/about/reports-and-data/disaster-relief-fund-monthly-reports | R68: Disaster Relief Fund FY 2024 Funding Requirements (fema.gov)
A69: C | B69: Workplace Electric Vehicle Charging Funding Assistance Program - Electric Vehicle Supply Equipment (EVSE) Rebate | C69: Funding | D69: Grant | E69: State | F69: UT | G69: 0.5 | H69: per applicant | I69: 0.5 | J69: EVs | K69: none | L69: n/a | M69: Not required | N69: Charger | O69: Unknown | P69: As of Dec 2023, $0 funding remains. "Funds will be updated if additional money becomes available in the future." Must be completed and fully operational on/before 2 years from approval date of preliminary application. No information regarding EJ approach. | Q69: https://documents.deq.utah.gov/air-quality/planning/air-quality-policy/DAQ-2019-014602.pdf | R69: https://deq.utah.gov/air-quality/workplace-electric-vehicle-charging-funding-assistance-program | S69: https://afdc.energy.gov/laws/12320
A70: C | B70: Level 2 EVSE Rebate Program | C70: Funding | D70: Rebate | E70: VW Settlement | F70: AR | G70: 9300 | H70: per applicant | I70: 0.1 | J70: EVs | K70: none | L70: n/a | M70: Not required | N70: Charger | O70: Unknown | P70: No information regarding EJ approach. By August 2023, there was no more funding available. | Q70: https://www.adeq.state.ar.us/energy/opportunities/evse/ | R70: https://www.adeq.state.ar.us/air/planning/vw/pdfs/evse-rebate-program-structure-final-1-11-21.pdf
A71: B | B71: Charge Up Michigan Placement Project | C71: Funding | D71: Rebate | E71: VW Settlement | F71: MI | G71: 70000 | H71: per applicant | I71: 0.666 | J71: EVs | K71: prioritization | L71: Pollution burden | M71: Not required | N71: Charger & infrastructure | O71: Rolling | P71: Charging stations must be installed on pre-determined areas. Any public or private organization located in Michigan, or those outside of Michigan that have demonstrated significant experience installing and maintaining electric vehicle charging stations and have a significant presence in Michigan. No information regarding EJ approach. | Q71: https://www.michigan.gov/climateandenergy/0,4580,7-364--487842--,00.html | R71: https://www.michigan.gov/documents/energy/ChargeUPMichiganRFP_673311_7.pdf | S71: https://www.surveymonkey.com/r/2019ChargeUpMichigan
A72: A | B72: Electric School Bus Grants | C72: Funding | D72: Grant | E72: VW Settlement | F72: MN | G72: 0.85 | H72: per bus | I72: 0.15 | J72: School Buses only | K72: prioritization | L72: Income | M72: Required | N72: Bus & Charger | O72: Annual Window | P72: Applications opened Spring 2023 | Q72: https://www.pca.state.mn.us/air-water-land-climate/volkswagen-settlement-grants | R72: Electric and cleaner school buses | Minnesota Pollution Control Agency (state.mn.us) | S72: https://afdc.energy.gov/laws/12476
A73: A | B73: Diesel Emissions Reductions Grants (DERA) | C73: Funding | D73: Grant | E73: Federal | F73: MA | G73: 0.45 | H73: per bus | I73: 0.55 | J73: MDHV vehicles only | K73: prioritization | L73: Income + Race/Ethinicity/Tribe | M73: Required | N73: Bus (&/or Battery) | O73: Annual Window | P73: Closed Aug 2022, no mention of reopening. The vehicle, equipment, and/or engine being replaced must be scrapped or rendered permanently disabled within ninety (90) days of being replaced. | Q73: https://www.mass.gov/how-to/apply-for-a-diesel-emissions-reduction-act-dera-electric-solicitation-grant | R73: https://www.mass.gov/doc/dera-open-solicitation-grant-guidance-requirements/download
A74: C | B74: Oregon School Bus Replacement Program | C74: Funding | D74: Grant | E74: VW Settlement | F74: OR | G74: 50000 | H74: per bus | I74: 0.7 | J74: School Buses only | K74: none | L74: n/a | M74: Required | N74: New Bus or Repower Bus | O74: Unknown | P74: Grant recipient will have 90 days after the new equipment is put into operation to complete the scrappage of the replaced equipment or be required to return all grant funds. No information regarding EJ approach. | Q74: Homepage - OR School Bus Replacement Program | R74: Application Form - OR School Bus Replacement Program
A75: A | B75: Fleet Electrification Assessment NYSEG | C75: Other | D75: Technical Assistance | E75: Utility | F75: NY | G75: N/A | H75: N/A | I75: N/A | J75: MDHV vehicles only | K75: prioritization | L75: Pollution + Income | M75: Not required | N75: Infrastructure | O75: Rolling | P75: Eligible applicants must be NYSEG customers and include any commercial, private, or public fleet with light-, medium-, or heavy-duty vehicles. Offers a fleet assesment as well as a Medium and Heavy Duty Fleet Make-Ready Pilot Program | Q75: https://www.nyseg.com/en/smartenergy/electricvehicles/ev-fleet-assessment-program
A76: A | B76: Fleet Electrification Assessment Orange & Rockland (O&R) | C76: Other | D76: Technical Assistance | E76: Utility | F76: NY | G76: N/A | H76: N/A | I76: N/A | J76: MDHV vehicles only | K76: prioritization | L76: Pollution + Income | M76: Not required | N76: Infrastructure | O76: Rolling | P76: Orange and Rockland offers fleet assessment and make ready funding. Participation in NYTVIP required for make ready funding. | Q76: https://www.oru.com/en/our-energy-future/technology-innovation/electric-vehicles/new-york/commercial-ev-drivers/fleet-owners-and-operators | R76: Microsoft Word - NY EV Infrastructure Medium- and Heavy-Duty Make-Ready Pilot Program Implementation Plan FINAL FINAL2.docx (azureedge.net)
A77: C | B77: Texas Clean Fleet Program - Texas Emissions Reduction Plan (TERP) | C77: Funding | D77: Grant | E77: State | F77: TX | G77: 0.8 | H77: per bus | I77: 0.2 | J77: MDHV vehicles only | K77: prioritization | L77: Pollution burden | M77: Required | N77: Bus (&/or Battery) | O77: Unknown | P77: Last round was 2022 | Q77: https://wayback.archive-it.org/414/20210527094043 | R77: https://www.tceq.texas.gov/airquality/terp/tcf.html | S77: https://afdc.energy.gov/laws/6583
A78: C | B78: New Mexico Volkswagen Environmental Mitigation Trust Program | C78: Funding | D78: Rebate | E78: VW Settlement | F78: NM | G78: 1 | H78: per bus | I78: 0.25 | J78: MDHV vehicles only | K78: prioritization | L78: Income | M78: Required | N78: New Bus or Repower Bus | O78: Unknown | P78: Most recent round closed Mar. 2022. Even though projects must begin after awards are granted and approved, funds will be reimbursed after project has been completed. Maximum allowances: https://www.vwcourtsettlement.com/en/docs/DOJ/Approved%20Appendix%20D-2.pdf | Q78: 2022 Guidelines & Application | R78: NMED VW Settlement Homepage
A79: A | B79: Fleet Electrification Assessment - Duke Energy | C79: Other | D79: Technical Assistance | E79: Utility | F79: IN | G79: N/A | H79: N/A | I79: N/A | J79: Any fleet vehicles | K79: none | L79: n/a | M79: Not required | N79: Charger + infrastructure | O79: Rolling | P79: Can provide EV solutions, including configuration, engineering & installation, procure hardware/software. new electric service, maintenance, as well as funding. | Q79: https://www.duke-energy.com/energy-education/energy-savings-and-efficiency/fleet-electrification | R79: https://www.duke-energy.com/energy-education/electric-vehicles/business/contact-us?_gl=1*1sejpbx*_ga*NDkyMTYxOTIuMTY3NjkyMDEyNg..*_ga_HB58MJRNTY*MTY3Njk4ODg2Mi44LjEuMTY3Njk4OTA4OC4wLjAuMA..&_ga=2.250806406.1441956738.1676920127-49216192.1676920127
A80: A | B80: Qualified Heavy-Duty Alternative Fuel Vehicle (AFV) Tax Credit | C80: Funding | D80: Tax Credit | E80: State | F80: UT | G80: 10500 | H80: per bus | I80: Yes, unspecified | J80: MDHV vehicles only | K80: none | L80: n/a | M80: Not required | N80: Bus (&/or Battery) | O80: Rolling | P80: Successful applicants will have 180 calendar days after the approval of the application to provide the following items or the tax credit will no longer be reserved for the taxpayer | Q80: https://documents.deq.utah.gov/air-quality/clean-fuels/tax-credit/DAQ-2018-008465.pdf | R80: https://deq.utah.gov/air-quality/incentive-programs-aq/alternative-fuel-heavy-duty-vehicle-tax-credit-program | S80: https://afdc.energy.gov/laws/11624
A81: A | B81: Fleet Electrification Assessment Rochester Gas and Electric (RG&E) | C81: Other | D81: Technical Assistance | E81: Utility | F81: NY | G81: N/A | H81: N/A | I81: N/A | J81: MDHV vehicles only | K81: prioritization | L81: Pollution + Income | M81: Not required | N81: Anything | O81: Rolling | P81: Required for RG&E's Make Ready program | Q81: https://www.rge.com/en/smartenergy/electricvehicles/ev-fleet-assessment-program | R81: Microsoft Word - NY EV Infrastructure Medium- and Heavy-Duty Make-Ready Pilot Program Implementation Plan FINAL FINAL2.docx (azureedge.net)
A82: A | B82: Commercial EV Charging Station Rebate Program | C82: Funding | D82: Rebate | E82: Utility | F82: CA | G82: 125000 | H82: per charger | I82: Yes, unspecified | J82: EVs | K82: extra funds | L82: Pollution + Income | M82: Not required | N82: Charger + infrastructure | O82: Annual Window | P82: Only charging stations for MHDV available | Q82: https://www.ladwp.com/ladwp/faces/oracle/webcenter/portalapp/pagehierarchy/Page1888.jspx;jsessionid=yKBhk1BN2T5yphXSc7JGW258H22sGZLlV3GzPnkpV7wp2hSM2FrD!1109665642?_afrWindowId=null&_afrLoop=397725492306425&_afrWindowMode=0&_adf.ctrl-state=1a6nnraau9_162#%40%3F_afrWindowId%3Dnull%26_afrLoop%3D397725492306425%26_afrWindowMode%3D0%26_adf.ctrl-state%3Djn7pcpj5c_4 | R82: Commercial EV Charging Station Rebate Program FAQs (ladwp.com)
A83: A | B83: Electric School Bus and Infrastructure Rebate - Duke Energy (North Carolina) | C83: Funding | D83: Rebate | E83: Utility | F83: NC | G83: 215000 | H83: per applicant | I83: Yes, unspecified | J83: School Buses only | K83: none | L83: n/a | M83: Not required | N83: Bus (&/or Battery) | O83: Rolling | P83: Funding available for 15 ESBs. Duke Energy will own the charger and infrastructure for the program term (until December 2025), and buses will participate in a V2G technology demonstration and study. | Q83: https://www.duke-energy.com/business/products/park-and-plug/electric-school-buses | R83: https://dukeenergy.co1.qualtrics.com/jfe/form/SV_3shkKYf5250baIK
A84: A | B84: Electric School Bus and Infrastructure Rebate - Duke Energy (Indiana) | C84: Funding | D84: Rebate | E84: Utility | F84: IN | G84: 197000 | H84: per bus | I84: Yes, unspecified | J84: School Buses only | K84: none | L84: n/a | M84: Not required | N84: Bus + Charger | O84: Rolling | P84: Funding available for 6 buses, Duke Energy will own the charger and infrastructure for the program term (December 2025), and buses will participate in a V2G pilot program study Requirements: - Be a public or charter school customer with a bus fleet within Duke Energy's service territory. - Agree to participate in the program through December 2024 - Site host and funding agreement required - Meet school bus specifications from Duke Energy - Meet site location requirements | Q84: https://www.duke-energy.com/business/products/park-and-plug/electric-school-buses?_gl=1*cpadrt*_ga*NzYyNjUzMTQxLjE2Nzk0OTg0OTY.*_ga_HB58MJRNTY*MTY4MTIyMzIwOC43LjAuMTY4MTIyMzIwOC4wLjAuMA.. | R84: https://dukeenergy.co1.qualtrics.com/jfe/form/SV_3shkKYf5250baIK | S84: https://investors.duke-energy.com/news/news-details/2022/Duke-Energy-Indiana-plans-two-year-electric-transportation-pilot-programs/default.aspx
A85: A | B85: Electric School Bus Grant - Central Coast Community Energy (CCCE) | C85: Funding | D85: Rebate | E85: Utility | F85: CA | G85: 200000 | H85: per bus | I85: 0.5 | J85: School Buses only | K85: none | L85: n/a | M85: Not required | N85: Bus (&/or Battery) | O85: Rolling | P85: Be an individual public school or public-school district, or a transport business that offer farmworker trasnport services - Must have at least one site located within the 3CE service area. The account associated with the location of the school bus must be in “good standing.” | Q85: https://3cenergy.org/rebates/electric-bus-program/ | R85: https://3cenergy.org/wp-content/uploads/2023/02/3CE-PDIG_Electric-Bus_FY-22-23_2.28.23.pdf | S85: https://3cenergy.org/central-coast-community-energy-launches-electric-bus-rebates/
A86: A | B86: New York Truck Voucher Incentive Program (NYTVIP) | C86: Funding | D86: Discount/point of sale coupon or voucher | E86: VW Settlement | F86: NY | G86: 1 | H86: incremental cost | I86: Yes, unspecified | J86: MDHV vehicles only | K86: prioritization | L86: Income + Race/Ethinicity/Tribe | M86: Required | N86: New Bus or Repower Bus | O86: Rolling | P86: Refer to source tables for max amounts. Other trucks are eligible for repowering. | Q86: https://www.nyserda.ny.gov/All-Programs/Truck-Voucher-Program | R86: servlet.FileDownload (ny.gov) | S86: https://www.nyserda.ny.gov/All-Programs/Truck-Voucher-Program
A87: A | B87: Plug-In Electric Vehicle Credit - Vermont Electric Co-op (VEC) | C87: Funding | D87: Rebate | E87: Utility | F87: VT | G87: 250 | H87: per charger | I87: Yes, unspecified | J87: EVs | K87: none | L87: n/a | M87: Not required | N87: Charger | O87: Rolling | P87: If you purchase your own level II charger, you can receive a $250 incentive if you either 1) set a schedule to not charger from 5-9pm Monday through Friday, or 2) if it is a Flo or ChargePoint, enroll it in VEC's communications platform to receive another $50 upfront incentive and $8/month as long as you do not opt out of events. | Q87: https://vermontelectric.coop/energy-transformation-programs | R87: https://vermontelectric.coop/energy-transformation-programs
A88: C | B88: Reduced Vehicle License Tax | C88: Funding | D88: Tax Credit | E88: State | F88: AZ | G88: 5 | H88: per applicant | I88: Yes, unspecified | J88: EVs | K88: none | L88: n/a | M88: Not required | N88: Bus (&/or Battery) | O88: Rolling | P88: Repowers may be eligible "If a vehicle is converted to operate solely on alternative fuel, the Arizona Department of Environmental Quality must inspect the vehicle and issue an Alternative Fuel Certificate." Old note - can't find the formulas any longer: Use the formulas provided in the first link to understand what the reduced tax burden is for the AFV | Q88: https://azdot.gov/motor-vehicles/vehicle-services/vehicle-registration/alternative-fuel-vehicle | R88: https://www.azleg.gov/ars/28/05805.htm | S88: Alt-Fuel-VLT-infographic.pdf (azdot.gov) | T88: https://afdc.energy.gov/laws/4179
A89: B | B89: Alternative Fuel Vehicle (AFV) Conversion Tax Credit | C89: Funding | D89: Tax Credit | E89: City | F89: DC | G89: 0.5 | H89: per district | I89: 0.5 | J89: EVs | K89: none | L89: n/a | M89: Not required | N89: Bus + Charger | O89: Rolling | Q89: https://otr.cfo.dc.gov/sites/default/files/dc/sites/otr/publication/attachments/2016%20AFVC_Commercial_Fill-in.pdf | R89: https://otr.cfo.dc.gov/sites/default/files/dc/sites/otr/publication/attachments/AlternativeFuelVehicleInfrastructureandConversionCreditsFAQs.pdf | S89: https://afdc.energy.gov/laws/11493
A90: A | B90: Utah Conversion to Alternative Fuel Vehicle Grant Program | C90: Funding | D90: Rebate | E90: State | F90: UT | G90: 2500 | H90: per bus | I90: Yes, unspecified | J90: EVs | K90: none | L90: n/a | M90: Not required | N90: New Bus or Repower Bus | O90: Rolling | Q90: Preliminary Approval Application | R90: Application Instructions | S90: https://afdc.energy.gov/laws/11768
A91: A | B91: GaDOE School Bus Alternative Fuel Incentive Funding | C91: Funding | D91: Rebate | E91: State | F91: GA | G91: 100000 | H91: per bus | I91: Yes, unspecified | J91: School Buses only | K91: none | L91: n/a | M91: Not required | N91: Bus (&/or Battery) | O91: Rolling | P91: Maximim reimbursement for one electric bus. Model must be March 2023 or newer. No information on website. Reach out to GA Dept of Education. | Q91: https://onewri.sharepoint.com/:b:/s/TRBpaper/EVTPhqfjV_BMn7euwUI1zDwB0C1Xr9PN7H6CkdU98mFaXg?e=6FNbvy
A92: A | B92: Colorado Innovative Motor Vehicle and Truck Credits for Electric and Plug-in Hybrid Electric Vehicles | C92: Funding | D92: Tax Credit | E92: State | F92: CO | G92: 8000 | H92: per bus | I92: Yes, unspecified | J92: EVs | K92: none | L92: n/a | M92: Not required | N92: Bus (&/or Battery) | O92: Rolling | P92: Maximum amount varies depending upon the qualifying category and the tax year during which the vehicle is purchased, leased, converted, or modified | Q92: CO Innovative Truck Credit | R92: Income 69 Info Sheet
A93: A | B93: Plug-In Electric Vehicle (PEV) Tax Credit | C93: Funding | D93: Tax Credit | E93: Federal | F93: Federal | G93: 7500 | H93: per bus | I93: Yes, unspecified | J93: EVs | K93: none | L93: n/a | M93: Not required | N93: Bus (&/or Battery) | O93: Rolling | P93: For EVs purchased 2022 or earlier only. Gross Vehicle Weight 14000lbs or less (most ESBs not eligible). Maximum amount varies depending upon the qualifying category and the tax year during which the vehicle is purchased, leased, converted, or modified. | Q93: https://www.irs.gov/credits-deductions/credits-for-new-electric-vehicles-purchased-in-2022-or-before | R93: https://afdc.energy.gov/laws/409
A94: C | B94: Alternative Fuel Tax Exemption | C94: Other | D94: Law | E94: State | F94: NC | G94: N/A | H94: N/A | I94: N/A | J94: EVs | K94: none | L94: n/a | M94: Not required | N94: Maintenance Cost | O94: Rolling | P94: The retail sale, use, storage, and consumption of alternative fuels is exempt from the state retail sales and use tax. No information on how to apply exemption | Q94: https://www.ncleg.gov/EnactedLegislation/Statutes/HTML/BySection/Chapter_105/GS_105-164.13.html | R94: https://afdc.energy.gov/fuels/laws/NG?state=NC
A95: C | B95: PSE&G Electric Vehicle Charging Program | C95: Funding | D95: Incentive | E95: Utility | F95: NJ | G95: 100000 | H95: per site | I95: Yes, unpecified | J95: EVs | K95: none | L95: n/a | M95: Not required | N95: Charger + infrastructure | O95: Unknown | P95: Multi-family properties, government entities, and locations where property owners provide charger access to the public all may be considered for mixed use. - Account must be in good financial standing (no shut-off notice). - The DCFC/Level 2 smart charger must be WiFi or cellular network enabled and the customer must agree to provide EV charging data to PSE&G in order to receive any PSE&G-provided incentives. - The customer must complete the PSE&G electric service application process for EV smart charger installation upon request. - The customer must use New Jersey-licensed electricians and/or contractors for EV smart charger installation. | Q95: https://nj.myaccount.pseg.com/myservicepublic/electricvehicles
A96: C | B96: PGE Fleet Partner | C96: Other | D96: Technical Assistance | E96: Utility | F96: OR | G96: 400000 | H96: per applicant | I96: Yes, unspecified | J96: Any fleet vehicles | K96: none | L96: n/a | M96: Not required | N96: Charger + infrastructure | O96: Unknown | P96: All funding reserved as of Jan. 2023. Fleet Partner provides technical assistance and a feasbility study to plan the project. Once you're ready, they provide the make-ready program. The amount of the incentive is based on "the forecasted annual energy use of your chargers. This is your energy use commitment. The higher the energy use commitment, the higher the incentive could be." | Q96: https://portlandgeneral.com/fleet-partner | R96: Fleet Charging (portlandgeneral.com) | S96: Word Doc Template B (ctfassets.net) | T96: https://afdc.energy.gov/laws/12633
A97: A | B97: Medium-Duty Zero Emission Vehicle (ZEV) Voucher Program | C97: Funding | D97: Discount/point of sale coupon or voucher | E97: State | F97: NJ | G97: 175000 | H97: per bus | I97: Yes, unspecified | J97: MDHV vehicles only | K97: extra funds | L97: Income + Race/Ethinicity/Tribe | M97: Required | N97: Bus (&/or Battery) | O97: Annual Window | P97: Applications opened spring 2023, closed as of Dec 2023. | Q97: https://www.njeda.com/njzip/#eligibility | R97: Purchaser-Application_Read-Me-and-Walkthru.pdf (njeda.com) | S97: https://afdc.energy.gov/laws/12545
A98: C | B98: Zero Emission Vehicle (ZEV) Rebate | C98: Funding | D98: Rebate | E98: State | F98: NY | G98: 7500 | H98: per bus | I98: N/A | J98: Any public fleet vehicle | K98: prioritization | L98: Income + Race/Ethinicity/Tribe | M98: Not required | N98: Bus (&/or Battery) | O98: Unknown | P98: last Round closed June 2022. Scroll down to see Municipal Zero-emission Vehicle (ZEV) Program | Q98: https://www.dec.ny.gov/energy/109181.html
A99: A | B99: EV Fleet program | C99: Funding | D99: Rebate | E99: Utility | F99: CA | G99: 42000 | H99: per charger | I99: 0.5 | J99: Any fleet vehicles | K99: none | L99: n/a | M99: Not required | N99: Bus & Charger | O99: Rolling | P99: Consultation required before applying | Q99: https://www.pge.com/en/clean-energy/electric-vehicles/ev-fleet-program.html | R99: PG&E EV Fleet program overivew for public schools (pge.com) | S99: EV Fleet Program Terms and Conditions ("Contract") (pge.com) | T99: EV Guide Book (pge.com)
A100: C | B100: Texas Clean School Bus Program - Texas Emissions Reduction Plan (TERP) | C100: Funding | D100: Grant | E100: State | F100: TX | G100: 200000 | H100: per bus | I100: Yes, unspecified | J100: School Buses only | K100: none | L100: n/a | M100: Required | N100: New Bus or Repower Bus | O100: Unknown | P100: Last round was 2022 | Q100: Homepage - TCSB | R100: TERP Texas Clean School Bus Program Request for Grant Applications for Fiscal Year 2022 | S100: FY18 TCSB Workshop Presentation (texas.gov) | T100: https://afdc.energy.gov/laws/11499
...

Sheet US States + Territories
A1: US STATE | B1: POSTAL ABBREVIATION | C1: STANDARD ABBREVIATION | F1: Territory/Commonwealth | G1: Postal Abbreviation | H1: Standard Abbreviation
A2: Alabama | B2: AL | C2: Ala. | F2: District of Columbia | G2: DC | H2: D.C.
A3: Alaska | B3: AK | C3: Alaska | F3: Guam | G3: GU | H3: Guam
A4: Arizona | B4: AZ | C4: Ariz. | F4: Marshall Islands | G4: MH | H4: M.I.
A5: Arkansas | B5: AR | C5: Ark. | F5: Northern Mariana Island | G5: MP | H5: CNMI
A6: California | B6: CA | C6: Calif. | F6: Puerto Rico | G6: PR | H6: P.R. or PUR
A7: Colorado | B7: CO | C7: Color. | F7: Virgin Islands | G7: VI | H7: V.I.
A8: Connecticut | B8: CT | C8: Conn.
A9: Delaware | B9: DE | C9: Del.
A10: Florida | B10: FL | C10: Fla.
A11: Georgia | B11: GA | C11: Ga.
A12: Hawaii | B12: HI | C12: Hawaii
A13: Idaho | B13: ID | C13: Idaho
A14: Illinois | B14: IL | C14: Ill.
A15: Indiana | B15: IN | C15: Ind.
A16: Iowa | B16: IA | C16: Iowa
A17: Kansas | B17: KS | C17: Kan.
A18: Kentucky | B18: KY | C18: Ky.
A19: Louisiana | B19: LA | C19: La.
... A51: Wyoming | B51: WY | C51: Wyo.

Sheet AVG Awards
B3: $ | C3: % | F3: $ | G3: % | J3: $ | K3: %
A4: Anything | B4: =AVERAGE($B$5:$B$6) -> #REF! | C4: =AVERAGE(C5:C6) -> #REF! | E4: Any fleet vehicles | F4: =AVERAGE($F$5,$F$6:$F$9,$F$10) -> #REF! | G4: =AVERAGE($G$6,$G$9) -> #REF! | I4: Any fleet vehicles | J4: =AVERAGE($J$5:$J$8,$J$10) -> #REF! | K4: =AVERAGE(K7:K9,K5) -> #REF! | N4: Anything | O4: =AVERAGE($J$23,$J$26,$J$50) -> #REF! | R4: City | S4: State | T4: Utility | U4: VW | V4: Federal | W4: AVERAGE TECH
A5: per applicant | B5: =AVERAGE('Clearinghouse Official'!G$10,'Clearinghouse Official'!G$11,'Clearinghouse Official'!G$12,'Clearinghouse Official'!G$13,'Clearinghouse Official'!G$14,'Clearinghouse Official'!G$15,'Clearinghouse Official'!G$16,'Clearinghouse Official'!#REF!,'Clearinghouse Official'!G$17,'Clearinghouse Official'!G$19,'Clearinghouse Official'!G$23) -> #REF! | C5: =AVERAGE('Clearinghouse Official'!$G$10,'Clearinghouse Official'!#REF!) -> #REF! | E5: incremental cost | F5: =AVERAGE('Clearinghouse Official'!$G$7:$G$8) -> 300000 | I5: Bus (&/or Battery) | J5: =AVERAGE('Clearinghouse Official'!$G$8,'Clearinghouse Official'!$G$24,'Clearinghouse Official'!$G$36,'Clearinghouse Official'!$G$39:$G$40,'Clearinghouse Official'!$G$8) -> 310500 | K5: =AVERAGE('Clearinghouse Official'!#REF!,'Clearinghouse Official'!#REF!,'Clearinghouse Official'!G$32) -> #REF! | N5: Bus (&/or Battery) | O5: =AVERAGE(J$5,J$14,J$27,J$33,J$39,J$46,J$51) -> #REF! | Q5: Anything | S5: =AVERAGE('Clearinghouse Official'!$G$9,'Clearinghouse Official'!$G$12,'Clearinghouse Official'!$G$23) -> 833333.33 | V5: =AVERAGE('Clearinghouse Official'!$G$11,'Clearinghouse Official'!$G$13:$G$16,'Clearinghouse Official'!$G$19) -> 20901667 | W5: =AVERAGE($S$5,$V$5) -> 10867500
A6: per district | B6: ='Clearinghouse Official'!$G$131 -> 1000000 | C6: ='Clearinghouse Official'!$G$123 -> 975000 | E6: per applicant | F6: =AVERAGE('Clearinghouse Official'!$G39:$G40,'Clearinghouse Official'!$G49,'Clearinghouse Official'!$G82,'Clearinghouse Official'!$G84:$G85,'Clearinghouse Official'!$G105,'Clearinghouse Official'!$G112,'Clearinghouse Official'!$G126,'Clearinghouse Official'!$G36,'Clearinghouse Official'!$G65,'Clearinghouse Official'!$G102,'Clearinghouse Official'!$G121) -> 140090.97 | G6: =AVERAGE('Clearinghouse Official'!G$32:G$32,'Clearinghouse Official'!G$53,'Clearinghouse Official'!#REF!,'Clearinghouse Official'!G$49,'Clearinghouse Official'!#REF!) -> #REF! | I6: Bus + Charger | J6: ='Clearinghouse Official'!$G$53 -> 5000 | N6: Bus + Charger | O6: =AVERAGE($J$6,$J$15,$J$28,$J$40,$J$47) -> 135000 | Q6: Bus (&/or Battery) | R6: ='Clearinghouse Official'!$G$89 -> 0.5 | S6: =AVERAGE('Clearinghouse Official'!$G$96:$G$101,'Clearinghouse Official'!$G$92,'Clearinghouse Official'!$G$90:$G$91,'Clearinghouse Official'!#REF!,'Clearinghouse Official'!$G$80,'Clearinghouse Official'!$G$48,'Clearinghouse Official'!$G$40:$G$41,'Clearinghouse Official'!$G$24,'Clearinghouse Official'!$G$8) -> #REF! | T6: =AVERAGE('Clearinghouse Official'!$G$87,'Clearinghouse Official'!#REF!,'Clearinghouse Official'!$G$37) -> #REF! | U6: =AVERAGE('Clearinghouse Official'!$G$38,'Clearinghouse Official'!$G$42,'Clearinghouse Official'!$G$44:$G$44,'Clearinghouse Official'!$G$47,'Clearinghouse Official'!$G$50:$G$50,'Clearinghouse Official'!$G$72,'Clearinghouse Official'!$G$74,'Clearinghouse Official'!$G$79,'Clearinghouse Official'!$G$86,'Clearinghouse Official'!$G$111,'Clearinghouse Official'!$G$123,'Clearinghouse Official'!$G$130) -> 312009.4 | V6: =AVERAGE('Clearinghouse Official'!$G$10,'Clearinghouse Official'!$G$36,'Clearinghouse Official'!$G$39,'Clearinghouse Official'!$G$43,'Clearinghouse Official'!$G$45,'Clearinghouse Official'!$G$93,'Clearinghouse Official'!#REF!) -> #REF! | W6: =AVERAGE($R$6:$V$6) -> #REF!
E7: per bus | F7: ='Clearinghouse Official'!#REF! -> #REF! | I7: Charger | J7: =AVERAGE('Clearinghouse Official'!$G$141,'Clearinghouse Official'!$G$138,'Clearinghouse Official'!$G$134,'Clearinghouse Official'!#REF!,'Clearinghouse Official'!#REF!,'Clearinghouse Official'!$G$121,'Clearinghouse Official'!$G$112,'Clearinghouse Official'!$G$105,'Clearinghouse Official'!$G$102,'Clearinghouse Official'!$G$84:$G$85,'Clearinghouse Official'!$G$82) -> #REF! | K7: ='Clearinghouse Official'!$G$65 -> 0.65 | N7: Charger | O7: =AVERAGE($J$7,$J$16,$J$35,$J$41) -> #REF! | Q7: Bus + Charger | S7: =AVERAGE('Clearinghouse Official'!$G49,'Clearinghouse Official'!$G66) -> #DIV/0! | T7: =AVERAGE('Clearinghouse Official'!$G$55,'Clearinghouse Official'!$G$53) -> 5000 | U7: =AVERAGE('Clearinghouse Official'!$G$104) -> 375000 | W7: =AVERAGE($S$7:$U$7) -> #DIV/0!
A8: Bus (&/or Battery) | B8: =AVERAGE(B10:B12,B9) -> #REF! | C8: =AVERAGE(C12,C10:C11,C9) -> #REF! | E8: per charger | F8: =AVERAGE('Clearinghouse Official'!G$134,'Clearinghouse Official'!G$141,'Clearinghouse Official'!#REF!,'Clearinghouse Official'!G$146,'Clearinghouse Official'!G$149:G$150,'Clearinghouse Official'!G$152:G$153,'Clearinghouse Official'!G$138) -> #REF! | I8: Charger + infrastructure | J8: =AVERAGE('Clearinghouse Official'!$G$180,'Clearinghouse Official'!$G$177,'Clearinghouse Official'!$G$161,'Clearinghouse Official'!$G$152:$G$153,'Clearinghouse Official'!$G$150,'Clearinghouse Official'!$G$149,'Clearinghouse Official'!$G$146,'Clearinghouse Official'!$G$167) -> 20655.556 | K8: ='Clearinghouse Official'!#REF! -> #REF! | N8: Charger + infrastructure | O8: =AVERAGE($J$8,$J$17,$J$29,$J$36,$J$42,$J$52) -> #REF! | Q8: Charger | R8: ='Clearinghouse Official'!$G$133 -> 10000 | S8: =AVERAGE('Clearinghouse Official'!$G$141,'Clearinghouse Official'!$G$137:$G$138,'Clearinghouse Official'!$G$121:$G$121,'Clearinghouse Official'!$G$112) -> 10900 | T8: =AVERAGE('Clearinghouse Official'!$G$56:$G$59,'Clearinghouse Official'!$G$61:$G$63,'Clearinghouse Official'!$G$66:$G$67,'Clearinghouse Official'!$G$82,'Clearinghouse Official'!$G$84:$G$85,'Clearinghouse Official'!$G$95,'Clearinghouse Official'!$G$102:$G$103,'Clearinghouse Official'!$G$105:$G$107,'Clearinghouse Official'!$G$110,'Clearinghouse Official'!$G$114,'Clearinghouse Official'!$G$115,'Clearinghouse Official'!$G$117:$G$120,'Clearinghouse Official'!$G$122,'Clearinghouse Official'!$G$127:$G$129,'Clearinghouse Official'!$G$134,'Clearinghouse Official'!$G$135:$G$136,'Clearinghouse Official'!$G$143,'Clearinghouse Official'!$G$168,'Clearinghouse Official'!$G$171,'Clearinghouse Official'!$G$193:$G$194,'Clearinghouse Official'!$G$198,'Clearinghouse Official'!$G$199,'Clearinghouse Official'!$G$201) -> 37804.286 | U8: =AVERAGE('Clearinghouse Official'!$G$173,'Clearinghouse Official'!$G$154,'Clearinghouse Official'!#REF!,'Clearinghouse Official'!$G$70:$G$71) -> #REF! | W8: =AVERAGE($R$8:$U$8) -> #REF!
A9: incremental cost | B9: =AVERAGE('Clearinghouse Official'!$G$6:$G$8) -> 300000 | C9: =AVERAGE('Clearinghouse Official'!$G$18,'Clearinghouse Official'!$G$24) -> 75000.5 | E9: per district | F9: =AVERAGE('Clearinghouse Official'!$G$167,'Clearinghouse Official'!$G$161) -> 5000 | G9: =AVERAGE('Clearinghouse Official'!G$180,'Clearinghouse Official'!G$177) -> 75000 | I9: Infrastructure | K9: =AVERAGE('Clearinghouse Official'!$G$191,'Clearinghouse Official'!$G$186) -> 2350 | N9: Infrastructure | O9: =AVERAGE($J$18,$J$43,$J$56) -> 107500.4 | Q9: Charger + infrastructure | S9: =AVERAGE('Clearinghouse Official'!$G$131,'Clearinghouse Official'!#REF!,'Clearinghouse Official'!$G$155:$G$156,'Clearinghouse Official'!$G$158:$G$159,'Clearinghouse Official'!#REF!,'Clearinghouse Official'!$G$162:$G$163,'Clearinghouse Official'!$G$174,'Clearinghouse Official'!$G$180) -> #REF! | T9: =AVERAGE('Clearinghouse Official'!$G$146,'Clearinghouse Official'!$G$149:$G$150,'Clearinghouse Official'!$G$152:$G$153,'Clearinghouse Official'!$G$157,'Clearinghouse Official'!$G$160:$G$161,'Clearinghouse Official'!$G$165,'Clearinghouse Official'!$G$167,'Clearinghouse Official'!$G$177,'Clearinghouse Official'!$G$179) -> 11445.545 | V9: ='Clearinghouse Official'!$G$108 -> 80000 | W9: =AVERAGE($S$9:$T$9,V9) -> #REF!
A10: per applicant | B10: =AVERAGE('Clearinghouse Official'!$G$38:$G$41,'Clearinghouse Official'!$G$42,'Clearinghouse Official'!$G$43:$G$45,'Clearinghouse Official'!$G$47:$G$48,'Clearinghouse Official'!$G$50:$G$50,'Clearinghouse Official'!$G$29) -> 620850.15 | C10: =AVERAGE('Clearinghouse Official'!$G$36,'Clearinghouse Official'!$G$30:$G$33) -> 160000.36 | E10: per port | F10: =AVERAGE('Clearinghouse Official'!$G$191,'Clearinghouse Official'!$G$195:$G$196) -> 24500 | I10: Workforce Training | J10: ='Clearinghouse Official'!$G$196 -> 70000 | Q10: Infrastructure | T10: ='Clearinghouse Official'!$G$83 -> 215000 | V10: =AVERAGE('Clearinghouse Official'!$G$132,'Clearinghouse Official'!$G$178) -> 0.8 | W10: =AVERAGE($T$10,V10) -> 107500.4
A11: per bus | B11: =AVERAGE('Clearinghouse Official'!$G$72,'Clearinghouse Official'!$G$74,'Clearinghouse Official'!$G$80:$G$83,'Clearinghouse Official'!$G$86,'Clearinghouse Official'!$G$88:$G$92,'Clearinghouse Official'!$G$96:$G$102,'Clearinghouse Official'!$G$109,'Clearinghouse Official'!$G$113) -> 72710.913 | C11: =AVERAGE('Clearinghouse Official'!$G$64,'Clearinghouse Official'!$G$73,'Clearinghouse Official'!$G$77,'Clearinghouse Official'!$G$78) -> 0.675 | N11: Other | O11: =AVERAGE($J$50:$J$52) -> #REF! | Q11: AVERAGE FUNDER | R11: =AVERAGE(R8,R6) -> 5000.25 | S11: =AVERAGE($S$5:$S$9) -> #REF! | T11: =AVERAGE($T$6:$T$10) -> #REF! | U11: =AVERAGE($U$6:$U$8) -> #REF! | V11: =AVERAGE($V$5:$V$6,V9:V10) -> #REF!
A12: per district | B12: =AVERAGE('Clearinghouse Official'!G130,'Clearinghouse Official'!#REF!,'Clearinghouse Official'!G165) -> #REF! | C12: =AVERAGE('Clearinghouse Official'!#REF!,'Clearinghouse Official'!$G$116) -> #REF! | E12: Any public fleet vehicle | F12: =AVERAGE($F$13:$F$16) -> #DIV/0! | G12: =$G$14 -> 10000 | I12: Any public fleet vehicle | J12: =AVERAGE($J$13:$J$18) -> 113166.88 | K12: =$K$13 -> N/A | N12: Resilience investments | O12: =$J$54 -> Varies
E13: incremental cost | F13: =AVERAGE('Clearinghouse Official'!$G$6) -> #DIV/0! | I13: Anything | K13: ='Clearinghouse Official'!$G$6 -> N/A | N13: Economic development investments | O13: =$J$23 -> 26525000 | R13: Any fleet vehicles | S13: Any public fleet vehicle | T13: Economic development investments | U13: Energy | V13: ESBs only | W13: EVs | X13: MDHV vehicles only | Y13: Other | Z13: Resilience investments | AA13: AVERAGE TECH
E14: per applicant | F14: =AVERAGE('Clearinghouse Official'!$G38,'Clearinghouse Official'!$G79) -> 0.75 | G14: ='Clearinghouse Official'!$G$10 -> 10000 | I14: Bus (&/or Battery) | J14: =AVERAGE('Clearinghouse Official'!$G$98,'Clearinghouse Official'!$G$79,'Clearinghouse Official'!$G$38,'Clearinghouse Official'!$G$10) -> 5833.5833 | N14: Energy | O14: =AVERAGE($J$26:$J$29) -> #REF! | Q14: Anything | T14: 26462500 | U14: 2127500 | Y14: =AVERAGE('Clearinghouse Official'!$G$16,'Clearinghouse Official'!$G$19) -> 10150000 | AA14: =AVERAGE(T14:U14,Y14) -> 12913333
A15: Bus + Charger | B15: =AVERAGE(B16:B18) -> #DIV/0! | C15: =C16 -> 25000000 | E15: per bus | F15: =AVERAGE('Clearinghouse Official'!$G98,'Clearinghouse Official'!$G109) -> 8750 | I15: Bus + Charger | J15: ='Clearinghouse Official'!$G$109 -> 10000 | N15: EVs | O15: =AVERAGE($J$39:$J$43) -> #REF! | Q15: Bus (&/or Battery) | R15: 858750 | S15: 31250 | U15: 500000 | V15: =AVERAGE('Clearinghouse Official'!$G$123,'Clearinghouse Official'!$G$111,'Clearinghouse Official'!$G$100:$G$101,'Clearinghouse Official'!$G$91,'Clearinghouse Official'!$G$74,'Clearinghouse Official'!$G$72,'Clearinghouse Official'!$G$37) -> 203000.12 | W15: =AVERAGE('Clearinghouse Official'!$G$92:$G$93,'Clearinghouse Official'!$G$89:$G$90,'Clearinghouse Official'!#REF!,'Clearinghouse Official'!$G$87) -> #REF! | X15: =AVERAGE('Clearinghouse Official'!$G$130,'Clearinghouse Official'!$G$99,'Clearinghouse Official'!$G$96:$G$97,'Clearinghouse Official'!$G$86,'Clearinghouse Official'!$G$80,'Clearinghouse Official'!$G$50:$G$50,'Clearinghouse Official'!$G$48,'Clearinghouse Official'!$G$43:$G$45,'Clearinghouse Official'!$G$47) -> 528716.75 | Y15: =AVERAGE('Clearinghouse Official'!$G$42,'Clearinghouse Official'!#REF!) -> #REF! | AA15: =AVERAGE(R15:S15,U15:V15,W15:Y15) -> #REF!
A16: per applicant | B16: =AVERAGE('Clearinghouse Official'!$G$55,'Clearinghouse Official'!$G$49) -> #DIV/0! | C16: ='Clearinghouse Official'!$G$27 -> 25000000 | E16: per district | F16: =AVERAGE('Clearinghouse Official'!$G174,'Clearinghouse Official'!$G178,'Clearinghouse Official'!$G154) -> 183333.6 | I16: Charger | J16: ='Clearinghouse Official'!$G$154 -> 50000 | N16: Any public fleet vehicle | O16: =AVERAGE($J$13:$J$18) -> 113166.88 | Q16: Bus + Charger | R16: 12000 | S16: 120000 | U16: 55000 | W16: ='Clearinghouse Official'!$G$55 -> N/A | X16: ='Clearinghouse Official'!$G$104 -> 375000 | AA16: =AVERAGE(R16:S16,U16,W16:X16) -> 140500
A17: per bus | B17: ='Clearinghouse Official'!$G$104 -> 375000 | I17: Charger + infrastructure | J17: ='Clearinghouse Official'!$G$174 -> 500000 | N17: Any fleet vehicles | O17: =AVERAGE($J$5:$J$8,$J$10) -> #REF! | Q17: Charger | R17: 11745.833 | S17: 50000 | U17: 1000000 | V17: ='Clearinghouse Official'!$G$143 -> 120000 | W17: =AVERAGE('Clearinghouse Official'!$G$143,'Clearinghouse Official'!$G$138:$G$139,'Clearinghouse Official'!$G$127:$G$127,'Clearinghouse Official'!$G$126,'Clearinghouse Official'!$G$122:$G$123,'Clearinghouse Official'!$G$119,'Clearinghouse Official'!$G$117,'Clearinghouse Official'!$G$112,'Clearinghouse Official'!$G$110,'Clearinghouse Official'!$G$107,'Clearinghouse Official'!$G$105,'Clearinghouse Official'!$G$103,'Clearinghouse Official'!$G$95,'Clearinghouse Official'!$G$93,'Clearinghouse Official'!$G$92,'Clearinghouse Official'!$G$89,'Clearinghouse Official'!#REF!,'Clearinghouse Official'!$G$88,'Clearinghouse Official'!#REF!,'Clearinghouse Official'!$G$87,'Clearinghouse Official'!$G$85,'Clearinghouse Official'!$G$81:$G$84,'Clearinghouse Official'!$G$79,'Clearinghouse Official'!$G$76,'Clearinghouse Official'!$G$71,'Clearinghouse Official'!$G$70,'Clearinghouse Official'!$G$69,'Clearinghouse Official'!$G$67,'Clearinghouse Official'!$G$63,'Clearinghouse Official'!$G$53,'Clearinghouse Official'!$G$52) -> #REF! | AA17: =AVERAGE(R17:S17,U17:W17) -> #REF!
A18: per district | B18: =AVERAGE('Clearinghouse Official'!$G$174,'Clearinghouse Official'!$G$170) -> 275000 | E18: Disaster recovery investments | G18: =$G$19 -> #REF! | I18: Infrastructure | J18: ='Clearinghouse Official'!G178 -> 0.8 | N18: MDHV vehicles only | O18: =AVERAGE($J$46:$J$47) -> 451858.38 | Q18: Charger + infrastructure | R18: 31055.556 | S18: 500000 | V18: ='Clearinghouse Official'!$G$165 -> 1 | W18: =AVERAGE('Clearinghouse Official'!#REF!,'Clearinghouse Official'!$G$155:$G$160,'Clearinghouse Official'!#REF!,'Clearinghouse Official'!$G$162:$G$163,'Clearinghouse Official'!$G$179) -> #REF! | Y18: ='Clearinghouse Official'!$G$108 -> 80000 | Z18: ='Clearinghouse Official'!$G$132 -> Varies | AA18: =AVERAGE(R18:S18,V18:W18,Y18:Z18) -> #REF!
E19: per applicant | G19: =AVERAGE('Clearinghouse Official'!#REF!,'Clearinghouse Official'!$G$169) -> #REF! | N19: ESBs only | O19: =AVERAGE($J$35:$J$36,$J$33) -> 107667.04 | Q19: Infrastructure | S19: 25000000 | W19: ='Clearinghouse Official'!$G$83 -> 215000 | AA19: =AVERAGE(S19,W19) -> 12607500
A20: Charger | B20: =AVERAGE(B21:B24) -> #REF! | C20: =AVERAGE(C21:C24) -> #REF! | I20: Disaster recovery investments | Q20: AVERAGE SECTOR | R20: =AVERAGE(R15:R18) -> 228387.85 | S20: =AVERAGE(S15:S19) -> 5140250 | T20: =T14 -> 26462500 | U20: =AVERAGE(U14:U17) -> 920625 | V20: =AVERAGE(V15,V17:V18) -> 107667.04 | W20: =AVERAGE(W15:W19) -> #REF! | X20: =AVERAGE(X15:X16) -> 451858.38 | Y20: =AVERAGE(Y14:Y15,Y18) -> #REF! | Z20: =Z18 -> Varies
A21: per applicant | B21: =AVERAGE('Clearinghouse Official'!G$58,'Clearinghouse Official'!G$63,'Clearinghouse Official'!G$66:G$67,'Clearinghouse Official'!G$70:G$71,'Clearinghouse Official'!G$56,'Clearinghouse Official'!G$57,'Clearinghouse Official'!G$59,'Clearinghouse Official'!G$61:G$62,'Clearinghouse Official'!G$71) -> 37325.25 | C21: =AVERAGE('Clearinghouse Official'!$G$53,'Clearinghouse Official'!$G$69,'Clearinghouse Official'!#REF!) -> #REF! | E21: Economic development investments | F21: =$F$22 -> 26525000 | I21: Infrastructure | K21: =AVERAGE('Clearinghouse Official'!$G$169:$G$169) -> 0.9 | N21: City | O21: =J59 -> 5000.25
A22: per charger | B22: =AVERAGE('Clearinghouse Official'!G$84,'Clearinghouse Official'!G$85,'Clearinghouse Official'!G$87:G$90,'Clearinghouse Official'!G$92:G$95,'Clearinghouse Official'!G$103,'Clearinghouse Official'!G$107,'Clearinghouse Official'!G$110,'Clearinghouse Official'!G$114:G$115,'Clearinghouse Official'!G$117:G$120,'Clearinghouse Official'!G$122,'Clearinghouse Official'!G$106,'Clearinghouse Official'!#REF!,'Clearinghouse Official'!G$128,'Clearinghouse Official'!G$129,'Clearinghouse Official'!G$133:G$134,'Clearinghouse Official'!G$135:G$138,'Clearinghouse Official'!G$141,'Clearinghouse Official'!#REF!,'Clearinghouse Official'!G$146,'Clearinghouse Official'!G$149:G$150) -> #REF! | C22: =AVERAGE('Clearinghouse Official'!$G$111,'Clearinghouse Official'!$G$151) -> 45000.25 | E22: per applicant | F22: =AVERAGE('Clearinghouse Official'!$G$14:$G$15,'Clearinghouse Official'!$G$12,'Clearinghouse Official'!$G$11) -> 26525000 | I22: Economic development investments | J22: =$J$23 -> 26525000 | N22: Federal | O22: =J63 -> #REF! | R22: incremental cost | S22: per applicant | T22: per bus | U22: per district | V22: per charger | W22: per port | X22: AVERAGE TECH
A23: per district | B23: =AVERAGE('Clearinghouse Official'!$G$154,'Clearinghouse Official'!$G$161,'Clearinghouse Official'!$G$167,'Clearinghouse Official'!$G$168,'Clearinghouse Official'!$G$171,'Clearinghouse Official'!$G$173) -> 19583.333 | C23: =AVERAGE('Clearinghouse Official'!$G$172,'Clearinghouse Official'!#REF!) -> #REF! | I23: Anything | J23: =AVERAGE('Clearinghouse Official'!$G12,'Clearinghouse Official'!$G11,'Clearinghouse Official'!$G14,'Clearinghouse Official'!$G15) -> 26525000 | N23: State | O23: =J69 -> #REF! | Q23: Anything | S23: 10385000 | U23: ='Clearinghouse Official'!$G$131 -> 1000000 | X23: =AVERAGE(S23,$U$23) -> 5692500.1
A24: per port | B24: =AVERAGE('Clearinghouse Official'!#REF!,'Clearinghouse Official'!$G$191,'Clearinghouse Official'!$G$193:$G$196,'Clearinghouse Official'!$G$198,'Clearinghouse Official'!$G$199,'Clearinghouse Official'!$G$201) -> #REF! | C24: =AVERAGE('Clearinghouse Official'!$G$192) -> 2000 | E24: Energy | F24: =AVERAGE(F25:$F$26) -> #REF! | G24: =AVERAGE($G25:G$26) -> #REF! | N24: Utility | O24: =J77 -> #REF! | Q24: Bus (&/or Battery) | R24: =AVERAGE('Clearinghouse Official'!$G$6:$G$8) -> 300000 | S24: =AVERAGE('Clearinghouse Official'!$G$38:$G$41,'Clearinghouse Official'!$G$42,'Clearinghouse Official'!$G$43:$G$45,'Clearinghouse Official'!$G$47:$G$48,'Clearinghouse Official'!$G$50:$G$50,'Clearinghouse Official'!$G$29) -> 620850.15 | T24: 81334.783 | U24: 675000 | X24: =AVERAGE($R$24:$U$24) -> 419296.23
E25: per applicant | F25: =AVERAGE('Clearinghouse Official'!$G$13,'Clearinghouse Official'!$G$17,'Clearinghouse Official'!$G$23,'Clearinghouse Official'!$G$41,'Clearinghouse Official'!#REF!) -> #REF! | G25: =AVERAGE('Clearinghouse Official'!#REF!,'Clearinghouse Official'!G$131) -> #REF! | I25: Energy | J25: =AVERAGE($J$26:$J$29) -> #REF! | K25: =AVERAGE($K$26,$K$29:$K$30) -> #REF! | N25: VW Settlement | O25: =J84 -> #REF! | Q25: Bus + Charger | S25: 8500 | T25: 375000 | U25: 87500 | X25: =AVERAGE($S$25:$U$25) -> 157000
A26: Charger + infrastructure | B26: =AVERAGE(B27:B29) -> #REF! | C26: =AVERAGE(C27:C29) -> #REF! | E26: per district | F26: =AVERAGE('Clearinghouse Official'!$G170,'Clearinghouse Official'!$G144) -> 25000.5 | G26: ='Clearinghouse Official'!$G$175 -> 1 | I26: Anything | J26: =AVERAGE('Clearinghouse Official'!$G$23,'Clearinghouse Official'!#REF!,'Clearinghouse Official'!$G$13,'Clearinghouse Official'!$G$9) -> #REF! | K26: ='Clearinghouse Official'!#REF! -> #REF! | Q26: Charger | S26: 19650 | U26: 34208.333 | V26: 4833.3307 | W26: =AVERAGE('Clearinghouse Official'!#REF!,'Clearinghouse Official'!$G$191,'Clearinghouse Official'!$G$193:$G$196,'Clearinghouse Official'!$G$198,'Clearinghouse Official'!$G$199,'Clearinghouse Official'!$G$201) -> #REF! | X26: =AVERAGE($S$26,$U$26:$W$26) -> #REF!
A27: per applicant | B27: =AVERAGE('Clearinghouse Official'!$G$82,'Clearinghouse Official'!$G$84:$G$85,'Clearinghouse Official'!$G$105,'Clearinghouse Official'!$G$108,'Clearinghouse Official'!$G$112,'Clearinghouse Official'!$G$121,'Clearinghouse Official'!#REF!,'Clearinghouse Official'!$G$126) -> #REF! | C27: =AVERAGE('Clearinghouse Official'!$G$65,'Clearinghouse Official'!$G$75,'Clearinghouse Official'!$G$76) -> 0.65 | I27: Bus (&/or Battery) | J27: ='Clearinghouse Official'!$G$41 -> 500000 | Q27: Charger + infrastructure | S27: 189444 | U27: 500000 | V27: 13654 | X27: =AVERAGE($U$27:$V$27,$S$27) -> 234366
A28: per charger | B28: =AVERAGE('Clearinghouse Official'!#REF!,'Clearinghouse Official'!#REF!,'Clearinghouse Official'!$G$152:$G$153,'Clearinghouse Official'!$G$155,'Clearinghouse Official'!$G$156:$G$160,'Clearinghouse Official'!#REF!,'Clearinghouse Official'!$G$162:$G$163) -> #REF! | C28: =AVERAGE('Clearinghouse Official'!$G$139:$G$140,'Clearinghouse Official'!$G$142,'Clearinghouse Official'!$G$145) -> 5875.075 | E28: ESBs only | F28: =AVERAGE($F$29:$F$33) -> #REF! | G28: =AVERAGE($G$29,$G$31:$G$32) -> 12500500 | I28: Bus + Charger | J28: ='Clearinghouse Official'!$G$126 -> 150000 | Q28: Infrastructure | S28: 9005003 | X28: =S28 -> 9005003
A29: per district | B29: =AVERAGE('Clearinghouse Official'!$G$178:$G$179) -> 0.8 | C29: =AVERAGE('Clearinghouse Official'!$G$175,'Clearinghouse Official'!#REF!) -> #REF! | E29: per applicant | F29: ='Clearinghouse Official'!$G$29 -> N/A | G29: ='Clearinghouse Official'!$G$27 -> 25000000 | I29: Charger + infrastructure | J29: ='Clearinghouse Official'!$G$131 -> 1000000 | K29: ='Clearinghouse Official'!G144 -> 1 | Q29: AVERAGE PER UNIT | R29: =R24 -> 300000 | S29: =AVERAGE($S$23:$S$28) -> 3371407.9 | T29: =AVERAGE($T$24:$T$25) -> 228167.39 | U29: =AVERAGE($U$23:$U$27) -> 459341.67 | V29: =AVERAGE($V$26:$V$27) -> 9243.6653 | W29: =$W$26 -> #REF!
E30: per bus | F30: =AVERAGE('Clearinghouse Official'!$G72,'Clearinghouse Official'!$G74,'Clearinghouse Official'!$G91,'Clearinghouse Official'!$G100:$G101,'Clearinghouse Official'!$G111) -> 74333.475 | I30: Infrastructure | K30: ='Clearinghouse Official'!$G$175 -> 1
A31: Infrastructure | B31: =B32 -> 13630 | C31: =AVERAGE(C32:C33) -> #REF! | E31: per charger | F31: =AVERAGE('Clearinghouse Official'!$G$123) -> 975000 | G31: ='Clearinghouse Official'!$G$113 -> N/A | I31: ESBs only | J31: =AVERAGE($J$35:$J$36,$J$33) -> 107667.04 | K31: =AVERAGE($K$34:$K$35,$K$32) -> #REF! | R31: Any fleet vehicles | S31: Any public fleet vehicle | T31: Economic development investments | U31: Energy | V31: ESBs only | W31: EVs | X31: MDHV vehicles only | Y31: Other | Z31: Resilience investments | AA31: AVG. UNIT
A32: per applicant | B32: =AVERAGE('Clearinghouse Official'!$G$79,'Clearinghouse Official'!$G$127,'Clearinghouse Official'!$G$132) -> 13630 | C32: =AVERAGE('Clearinghouse Official'!#REF!,'Clearinghouse Official'!$G$169) -> #REF! | E32: per district | F32: ='Clearinghouse Official'!$G$165 -> 1 | G32: ='Clearinghouse Official'!$G$124 -> 1000 | I32: Anything | K32: ='Clearinghouse Official'!$G$27 -> 25000000 | Q32: incremental cost | R32: 125000 | S32: 10000 | AA32: =AVERAGE($R$32:$S$32) -> 67500
A33: per district | C33: =AVERAGE('Clearinghouse Official'!$G$177,'Clearinghouse Official'!$G$180:$G$183) -> 31800 | E33: per port | F33: ='Clearinghouse Official'!#REF! -> #REF! | I33: Bus (&/or Battery) | J33: =AVERAGE('Clearinghouse Official'!$G$123,'Clearinghouse Official'!$G$111,'Clearinghouse Official'!$G$100:$G$101,'Clearinghouse Official'!$G$91,'Clearinghouse Official'!$G$74,'Clearinghouse Official'!$G$72,'Clearinghouse Official'!$G$37) -> 203000.12 | Q33: per applicant | R33: 465538.51 | S33: 12550000 | T33: 26462500 | U33: 2127500 | V33: 215000 | W33: 13343.5 | X33: 1282000 | Y33: 288750 | Z33: 2000000 | AA33: =AVERAGE($R$33:$Z$33) -> 5044959.1
I34: Bus + Charger | K34: ='Clearinghouse Official'!$G$124 -> 1000 | Q34: per bus | R34: 2500 | S34: 7500 | V34: 86266.667 | W34: 5742.8571 | X34: 217000 | AA34: =AVERAGE($V$34:$X$34,$R$34:$S$34) -> 63801.905
I35: Charger | J35: ='Clearinghouse Official'!$G$143 -> 120000 | K35: ='Clearinghouse Official'!#REF! -> #REF! | Q35: per charger | R35: 9327.7778 | V35: 10000 | W35: 96966.842 | AA35: =AVERAGE($V$35:$W$35,$R$35) -> 38764.873
E36: EVs | F36: =AVERAGE(F37:$F$41) -> #REF! | G36: =AVERAGE($G$37,G39:$G$41) -> #REF! | I36: Charger + infrastructure | J36: ='Clearinghouse Official'!$G$165 -> 1 | Q36: per district | R36: 50000 | S36: 223333.33 | U36: 277500 | V36: 975000 | W36: 138812.5 | X36: 500000 | Y36: 550000 | AA36: =AVERAGE($U$36:$Y$36,$R$36:$S$36) -> 387806.55
E37: per applicant | F37: =AVERAGE('Clearinghouse Official'!$G81, 'Clearinghouse Official'!$G70:$G71,'Clearinghouse Official'!$G66:$G67,'Clearinghouse Official'!$G61:$G63,'Clearinghouse Official'!$G55:$G59,'Clearinghouse Official'!$G83) -> 73575.25 | G37: =AVERAGE('Clearinghouse Official'!$G$69:$G$69,'Clearinghouse Official'!$G$75:$G$76) -> 0.5 | Q37: per port | R37: 3833.3333 | V37: 6000 | W37: 2730 | AA37: =AVERAGE($V$37:$W$37,$R$37) -> 4187.7778
E38: per bus | F38: =AVERAGE('Clearinghouse Official'!$G$92,'Clearinghouse Official'!$G$89:$G$90,'Clearinghouse Official'!#REF!,'Clearinghouse Official'!$G$87,'Clearinghouse Official'!$G$93) -> #REF! | I38: EVs | J38: =AVERAGE($J$39:$J$43) -> #REF! | K38: =AVERAGE($K$41:$K$43,$K$39) -> #REF! | Q38: AVG. SECTOR | R38: =AVERAGE($R$32:$R$37) -> 109366.6 | S38: =AVERAGE(S36,$S$32:$S$34) -> 3197708.3 | T38: =$T$33 -> 26462500 | U38: =AVERAGE(U36,U33) -> 1202500 | V38: =AVERAGE($V$33:$V$37) -> 258453.33 | W38: =AVERAGE($W$33:$W$37) -> 51519.14 | X38: =AVERAGE(X36,$X$33:$X$34) -> 666333.33 | Y38: =AVERAGE(Y36,Y33) -> 419375 | Z38: =$Z$33 -> 2000000
E39: per charger | F39: =AVERAGE('Clearinghouse Official'!$G95,'Clearinghouse Official'!$G103,'Clearinghouse Official'!$G106:$G107,'Clearinghouse Official'!$G110,'Clearinghouse Official'!$G114:$G115,'Clearinghouse Official'!$G117:$G120,'Clearinghouse Official'!$G122,'Clearinghouse Official'!$G128:$G129,'Clearinghouse Official'!$G133,'Clearinghouse Official'!$G136:$G137,'Clearinghouse Official'!#REF!,'Clearinghouse Official'!$G155:$G160,'Clearinghouse Official'!#REF!,'Clearinghouse Official'!$G162:$G163,'Clearinghouse Official'!$G135,'Clearinghouse Official'!$G127) -> #REF! | G39: =AVERAGE('Clearinghouse Official'!$G$145,'Clearinghouse Official'!$G$142,'Clearinghouse Official'!$G$139:$G$140) -> 5875.075 | I39: Bus (&/or Battery) | J39: =AVERAGE('Clearinghouse Official'!$G$92:$G$93,'Clearinghouse Official'!$G$89:$G$90,'Clearinghouse Official'!#REF!,'Clearinghouse Official'!$G$87) -> #REF! | K39: ='Clearinghouse Official'!#REF! -> #REF!
E40: per district | F40: =AVERAGE('Clearinghouse Official'!$G$179,'Clearinghouse Official'!$G$173,'Clearinghouse Official'!$G$171,'Clearinghouse Official'!$G$168) -> 19166.667 | G40: =AVERAGE('Clearinghouse Official'!#REF!,'Clearinghouse Official'!#REF!,'Clearinghouse Official'!#REF!,'Clearinghouse Official'!$G$181:$G$183) -> #REF! | I40: Bus + Charger | J40: ='Clearinghouse Official'!$G$55 -> N/A
E41: per port | F41: =AVERAGE('Clearinghouse Official'!$G$201,'Clearinghouse Official'!$G$199,'Clearinghouse Official'!$G$198,'Clearinghouse Official'!$G$193:$G$194) -> 1600 | G41: ='Clearinghouse Official'!$G$192 -> 2000 | I41: Charger | J41: =AVERAGE('Clearinghouse Official'!$G$143,'Clearinghouse Official'!$G$138:$G$139,'Clearinghouse Official'!$G$127:$G$127,'Clearinghouse Official'!$G$126,'Clearinghouse Official'!$G$122:$G$123,'Clearinghouse Official'!$G$119,'Clearinghouse Official'!$G$117,'Clearinghouse Official'!$G$112,'Clearinghouse Official'!$G$110,'Clearinghouse Official'!$G$107,'Clearinghouse Official'!$G$105,'Clearinghouse Official'!$G$103,'Clearinghouse Official'!$G$95,'Clearinghouse Official'!$G$93,'Clearinghouse Official'!$G$92,'Clearinghouse Official'!$G$89,'Clearinghouse Official'!#REF!,'Clearinghouse Official'!$G$88,'Clearinghouse Official'!#REF!,'Clearinghouse Official'!$G$87,'Clearinghouse Official'!$G$85,'Clearinghouse Official'!$G$81:$G$84,'Clearinghouse Official'!$G$79,'Clearinghouse Official'!$G$76,'Clearinghouse Official'!$G$71,'Clearinghouse Official'!$G$70,'Clearinghouse Official'!$G$69,'Clearinghouse Official'!$G$67,'Clearinghouse Official'!$G$63,'Clearinghouse Official'!$G$53,'Clearinghouse Official'!$G$52) -> #REF! | K41: =AVERAGE('Clearinghouse Official'!$G$69:$G$69,'Clearinghouse Official'!#REF!,'Clearinghouse Official'!$G$192) -> #REF!
I42: Charger + infrastructure | J42: =AVERAGE('Clearinghouse Official'!#REF!,'Clearinghouse Official'!$G$155:$G$160,'Clearinghouse Official'!#REF!,'Clearinghouse Official'!$G$162:$G$163,'Clearinghouse Official'!$G$179) -> #REF! | K42: =AVERAGE('Clearinghouse Official'!#REF!,'Clearinghouse Official'!$G$145,'Clearinghouse Official'!$G$142,'Clearinghouse Official'!$G$139:$G$140,'Clearinghouse Official'!$G$76,'Clearinghouse Official'!$G$75) -> #REF!
E43: MDHV vehicles only | F43: =AVERAGE($F$45:$F$47) -> 376394.5 | G43: =AVERAGE($G$44:$G$47) -> #REF! | I43: Infrastructure | J43: ='Clearinghouse Official'!$G$83 -> 215000 | K43: =AVERAGE('Clearinghouse Official'!$G$181:$G$183) -> 3000
E44: incremental cost | G44: =AVERAGE('Clearinghouse Official'!#REF!,'Clearinghouse Official'!$G$18,'Clearinghouse Official'!$G$22) -> #REF!
E45: per applicant | F45: =AVERAGE('Clearinghouse Official'!$G$43:$G$45,'Clearinghouse Official'!$G$47:$G$48,'Clearinghouse Official'!$G$50:$G$50) -> 951000 | G45: =AVERAGE('Clearinghouse Official'!$G$33,'Clearinghouse Official'!$G$30:$G$31) -> 0.45 | I45: MDHV vehicles only | J45: =AVERAGE($J$46:$J$47) -> 451858.38 | K45: =$K$46 -> #REF!
E46: per bus | F46: =AVERAGE('Clearinghouse Official'!$G$104,'Clearinghouse Official'!$G$99,'Clearinghouse Official'!$G$96:$G$97,'Clearinghouse Official'!$G$86,'Clearinghouse Official'!$G$80) -> 167083.5 | G46: =AVERAGE('Clearinghouse Official'!$G$77:$G$78,'Clearinghouse Official'!$G$73,'Clearinghouse Official'!$G$64) -> 0.675 | I46: Bus (&/or Battery) | J46: =AVERAGE('Clearinghouse Official'!$G$130,'Clearinghouse Official'!$G$99,'Clearinghouse Official'!$G$96:$G$97,'Clearinghouse Official'!$G$86,'Clearinghouse Official'!$G$80,'Clearinghouse Official'!$G$50:$G$50,'Clearinghouse Official'!$G$48,'Clearinghouse Official'!$G$43:$G$45,'Clearinghouse Official'!$G$47) -> 528716.75 | K46: =AVERAGE('Clearinghouse Official'!#REF!,'Clearinghouse Official'!$G$18,'Clearinghouse Official'!$G$22,'Clearinghouse Official'!$G$30:$G$31,'Clearinghouse Official'!$G$33,'Clearinghouse Official'!$G$64,'Clearinghouse Official'!$G$73,'Clearinghouse Official'!$G$77:$G$78,'Clearinghouse Official'!$G$116) -> #REF!
E47: per district | F47: ='Clearinghouse Official'!$G$130 -> 11100 | G47: ='Clearinghouse Official'!$G$116 -> 0.45 | I47: Bus + Charger | J47: ='Clearinghouse Official'!$G$104 -> 375000
E49: Other | F49: =AVERAGE($F$50:$F$51) -> #REF! | I49: Other | J49: =AVERAGE($J$50:$J$52) -> #REF!
E50: per applicant | F50: =AVERAGE('Clearinghouse Official'!$G$16,'Clearinghouse Official'!$G$19,'Clearinghouse Official'!$G$42,'Clearinghouse Official'!$G$108) -> 5095000.2 | I50: Anything | J50: =AVERAGE('Clearinghouse Official'!$G$16,'Clearinghouse Official'!$G$19) -> 10150000
E51: per district | F51: ='Clearinghouse Official'!#REF! -> #REF! | I51: Bus (&/or Battery) | J51: =AVERAGE('Clearinghouse Official'!$G$42,'Clearinghouse Official'!#REF!) -> #REF!
I52: Charger + infrastructure | J52: ='Clearinghouse Official'!$G$108 -> 80000
E53: Resilience investments | F53: =$F$54 -> Varies | G53: =AVERAGE($G$55:$G$56) -> 0.475
E54: per applicant | F54: ='Clearinghouse Official'!$G$132 -> Varies | I54: Resilience investments or Infrastructure | J54: =$J$56 -> Varies
E55: per charger | G55: ='Clearinghouse Official'!$G$151 -> 0.5 | I55: Charger | K55: =AVERAGE('Clearinghouse Official'!$G$151,'Clearinghouse Official'!$G$172) -> 0.475
E56: per district | G56: ='Clearinghouse Official'!G172 -> 0.45 | I56: Infrastructure | J56: ='Clearinghouse Official'!$G$132 -> Varies
I59: City | J59: =AVERAGE($J$60:$J$61) -> 5000.25
I60: Bus (&/or Battery) | J60: ='Clearinghouse Official'!$G$89 -> 0.5
I61: Charger | J61: ='Clearinghouse Official'!$G$133 -> 10000
I63: Federal | J63: =AVERAGE($J$64:$J$67) -> #REF! | K63: =AVERAGE(K64:K67) -> #REF!
I64: Anything | J64: =AVERAGE('Clearinghouse Official'!$G$11,'Clearinghouse Official'!$G$13:$G$16,'Clearinghouse Official'!$G$19) -> 20901667 | K64: =AVERAGE('Clearinghouse Official'!$G$6,'Clearinghouse Official'!#REF!) -> #REF!
I65: Bus (&/or Battery) | J65: =AVERAGE('Clearinghouse Official'!$G$10,'Clearinghouse Official'!$G$36,'Clearinghouse Official'!$G$39,'Clearinghouse Official'!$G$43,'Clearinghouse Official'!$G$45,'Clearinghouse Official'!$G$93,'Clearinghouse Official'!#REF!) -> #REF! | K65: =AVERAGE('Clearinghouse Official'!$G$33,'Clearinghouse Official'!#REF!,'Clearinghouse Official'!$G$64,'Clearinghouse Official'!$G$73) -> #REF!
I66: Charger + infrastructure | J66: ='Clearinghouse Official'!$G$108 -> 80000 | K66: ='Clearinghouse Official'!$G$139 -> 0.3
I67: Infrastructure | J67: =AVERAGE('Clearinghouse Official'!$G$132,'Clearinghouse Official'!$G$178) -> 0.8 | K67: =AVERAGE('Clearinghouse Official'!$G$169:$G$169) -> 0.9
I69: State | J69: =AVERAGE($J$70:$J$74) -> #REF!
I70: Anything | J70: =AVERAGE('Clearinghouse Official'!$G$9,'Clearinghouse Official'!$G$12,'Clearinghouse Official'!$G$23) -> 833333.33 | K70: ='Clearinghouse Official'!$G$27 -> 25000000
I71: Bus (&/or Battery) | J71: =AVERAGE('Clearinghouse Official'!$G$96:$G$101,'Clearinghouse Official'!$G$92,'Clearinghouse Official'!$G$90:$G$91,'Clearinghouse Official'!#REF!,'Clearinghouse Official'!$G$80,'Clearinghouse Official'!$G$48,'Clearinghouse Official'!$G$40:$G$41,'Clearinghouse Official'!$G$24,'Clearinghouse Official'!$G$8) -> #REF! | K71: =AVERAGE('Clearinghouse Official'!#REF!,'Clearinghouse Official'!$G$32,'Clearinghouse Official'!$G$77,'Clearinghouse Official'!#REF!) -> #REF!
I72: Bus + Charger | J72: =AVERAGE('Clearinghouse Official'!$G109,'Clearinghouse Official'!$G126) -> 80000
I73: Charger | J73: =AVERAGE('Clearinghouse Official'!$G$141,'Clearinghouse Official'!$G$137:$G$138,'Clearinghouse Official'!$G$121:$G$121,'Clearinghouse Official'!$G$112) -> 10900 | K73: =AVERAGE('Clearinghouse Official'!$G$69,'Clearinghouse Official'!$G$151,'Clearinghouse Official'!$G$172) -> 0.48333333
I74: Charger + infrastructure | J74: =AVERAGE('Clearinghouse Official'!$G$131,'Clearinghouse Official'!#REF!,'Clearinghouse Official'!$G$155:$G$156,'Clearinghouse Official'!$G$158:$G$159,'Clearinghouse Official'!#REF!,'Clearinghouse Official'!$G$162:$G$163,'Clearinghouse Official'!$G$174,'Clearinghouse Official'!$G$180) -> #REF!
I75: Infrastructure | K75: ='Clearinghouse Official'!$G$175 -> 1
I77: Utility | J77: =AVERAGE(J78:J82) -> #REF! | K77: =AVERAGE(K79:K82) -> #REF!
I78: Bus (&/or Battery) | J78: =AVERAGE('Clearinghouse Official'!$G$87,'Clearinghouse Official'!#REF!,'Clearinghouse Official'!$G$37) -> #REF!
I79: Bus + Charger | J79: =AVERAGE('Clearinghouse Official'!$G$55,'Clearinghouse Official'!$G$53) -> 5000 | K79: ='Clearinghouse Official'!$G$124 -> 1000
I80: Charger | J80: =AVERAGE('Clearinghouse Official'!$G$56:$G$59,'Clearinghouse Official'!$G$61:$G$63,'Clearinghouse Official'!$G$66:$G$67,'Clearinghouse Official'!$G$82,'Clearinghouse Official'!$G$84:$G$85,'Clearinghouse Official'!$G$95,'Clearinghouse Official'!$G$102:$G$103,'Clearinghouse Official'!$G$105:$G$107,'Clearinghouse Official'!$G$110,'Clearinghouse Official'!$G$114,'Clearinghouse Official'!$G$115,'Clearinghouse Official'!$G$117:$G$120,'Clearinghouse Official'!$G$122,'Clearinghouse Official'!$G$127:$G$129,'Clearinghouse Official'!$G$134,'Clearinghouse Official'!$G$135:$G$136,'Clearinghouse Official'!$G$143,'Clearinghouse Official'!$G$168,'Clearinghouse Official'!$G$171,'Clearinghouse Official'!$G$193:$G$194,'Clearinghouse Official'!$G$198,'Clearinghouse Official'!$G$199,'Clearinghouse Official'!$G$201) -> 37804.286 | K80: =AVERAGE('Clearinghouse Official'!#REF!,'Clearinghouse Official'!#REF!,'Clearinghouse Official'!$G$192) -> #REF!
I81: Charger + infrastructure | J81: =AVERAGE('Clearinghouse Official'!$G$146,'Clearinghouse Official'!$G$149:$G$150,'Clearinghouse Official'!$G$152:$G$153,'Clearinghouse Official'!$G$157,'Clearinghouse Official'!$G$160:$G$161,'Clearinghouse Official'!$G$165,'Clearinghouse Official'!$G$167,'Clearinghouse Official'!$G$177,'Clearinghouse Official'!$G$179) -> 11445.545 | K81: =AVERAGE('Clearinghouse Official'!$G$75:$G$76,'Clearinghouse Official'!$G$140,'Clearinghouse Official'!$G$142:$G$142,'Clearinghouse Official'!$G$145,'Clearinghouse Official'!#REF!) -> #REF!
I82: Infrastructure | J82: ='Clearinghouse Official'!$G$83 -> 215000 | K82: =AVERAGE('Clearinghouse Official'!$G$191,'Clearinghouse Official'!$G$186,'Clearinghouse Official'!$G$181:$G$183) -> 2740
I84: VW Settlement | J84: =AVERAGE($J$85:$J$87) -> #REF! | K84: =AVERAGE(K85,K87) -> #REF!
I85: Bus (&/or Battery) | J85: =AVERAGE('Clearinghouse Official'!$G$38,'Clearinghouse Official'!$G$42,'Clearinghouse Official'!$G$44:$G$44,'Clearinghouse Official'!$G$47,'Clearinghouse Official'!$G$50:$G$50,'Clearinghouse Official'!$G$72,'Clearinghouse Official'!$G$74,'Clearinghouse Official'!$G$79,'Clearinghouse Official'!$G$86,'Clearinghouse Official'!$G$111,'Clearinghouse Official'!$G$123,'Clearinghouse Official'!$G$130) -> 312009.4 | K85: =AVERAGE('Clearinghouse Official'!$G$18,'Clearinghouse Official'!$G$22,'Clearinghouse Official'!$G$30:$G$31,'Clearinghouse Official'!#REF!,'Clearinghouse Official'!$G$78,'Clearinghouse Official'!$G$116) -> #REF!
I86: Bus + Charger | J86: =AVERAGE('Clearinghouse Official'!$G$104) -> 375000
I87: Charger | J87: =AVERAGE('Clearinghouse Official'!$G$173,'Clearinghouse Official'!$G$154,'Clearinghouse Official'!#REF!,'Clearinghouse Official'!$G$70:$G$71) -> #REF! | K87: =AVERAGE('Clearinghouse Official'!#REF!,'Clearinghouse Official'!$G$65) -> #REF!

Sheet Vizualizations 2022.12

Sheet PIVOT 2022.12
D2: Type of Program | E2: Count | G2: Type of Funder | H2: Count | J2: Eligible/Sector | K2: Count | N2: City | O2: Federal | P2: Regional jurisdiction | Q2: State | R2: Utility | S2: VW Settlement
D3: Bill Credit | E3: 4 | G3: City | H3: 2 | J3: Disaster recovery investments | K3: 3 | M3: exclusive to | O3: 8 | P3: 1 | Q3: 1 | R3: 1 | S3: 1
A4: Row Labels | B4: Count of Geography | D4: Discount/point of sale coupon or voucher | E4: 5 | G4: Federal | H4: 37 | J4: Other | K4: 9 | M4: extra funds | O4: 4 | Q4: 16 | R4: 14
A5: AK | B5: 2 | D5: Equipment | E5: 1 | G5: Regional jurisdiction | H5: 2 | J5: Technology innovation | K5: 4 | M5: none | N5: 2 | O5: 11 | P5: 1 | Q5: 35 | R5: 67 | S5: 9
A6: AL | B6: 3 | D6: Grant | E6: 67 | G6: State | H6: 65 | J6: Economic development investments | K6: 6 | M6: process priority | O6: 14 | Q6: 13 | R6: 3 | S6: 22
A7: AR | B7: 5 | D7: Incentive | E7: 10 | G7: Utility | H7: 85 | J7: Resilience investments or Infrastructure | K7: 4
A8: AZ | B8: 9 | D8: Law | E8: 9 | G8: VW Settlement | H8: 32 | J8: Energy | K8: 15
A9: CA | B9: 46 | D9: Loan | E9: 9 | J9: EVs | K9: 91
A10: CO | B10: 17 | D10: Rate | E10: 7 | G10: Technology Type | H10: Count | J10: Any public fleet vehicle | K10: 9
A11: CT | B11: 9 | D11: Rebate | E11: 95 | G11: Anything | H11: 23 | J11: Any fleet vehicles | K11: 39
A12: DC | B12: 2 | D12: Sales/use tax exemption | E12: 2 | G12: Bus (&/or Battery) | H12: 66 | J12: MDHV vehicles only | K12: 27
A13: DE | B13: 3 | D13: Tax Credit | E13: 11 | G13: Bus + Charger | H13: 7 | J13: ESBs only | K13: 16
A14: Federal | B14: 12 | D14: Technical Assistance | E14: 3 | G14: Charger | H14: 61
A15: Federal - competitive | B15: 15 | G15: Charger + infrastructure | H15: 33
A16: Federal - state admin | B16: 8 | D16: EJ Approach | E16: Count | G16: Infrastructure | H16: 17 | J16: Programs NO EJ Considerations
A17: FL | B17: 5 | D17: exclusive to | E17: 11 | G17: Maintenance Cost | H17: 14 | J17: Any fleet vehicles | K17: 26
A18: GA | B18: 3 | D18: extra funds | E18: 35 | G18: Workforce Training | H18: 2 | J18: Any public fleet vehicle | K18: 2
A19: HI | B19: 4 | D19: none | E19: 125 | J19: Disaster recovery investments | K19: 3
A20: IA | B20: 4 | D20: process priority | E20: 52 | J20: Energy | K20: 9
A21: ID | B21: 3 | J21: ESBs only | K21: 13
A22: IL | B22: 7 | D22: Application Status | E22: Number | J22: EVs | K22: 65
A23: IN | B23: 10 | D23: Annual Window | E23: 34 | J23: MDHV vehicles only | K23: 6
A24: LA | B24: 4 | D24: Rolling | E24: 137 | J24: No bounds | K24: 5
A25: MA | B25: 10 | D25: Unknown | E25: 52 | J25: Other | K25: 7
A26: MD | B26: 13 | E26: =SUM(E23:E25) -> 223 | J26: Resilience investments or Infrastructure | K26: 2
A27: ME | B27: 4 | J27: Technology innovation | K27: 4
A28: MI | B28: 11 | K28: =SUM(K17:K27) -> 142
A29: MN | B29: 6
A30: MO | B30: 4 | J30: Bill Credit | K30: 5
A31: MS | B31: 4 | J31: Discount/point of sale coupon or grant | K31: 1
A32: MT | B32: 1 | J32: Discount/point of sale coupon or voucher | K32: 1
A33: NC | B33: 10 | J33: Equipment | K33: 1
A34: NE | B34: 5 | J34: Grant | K34: 27
A35: NH | B35: 2 | J35: Incentive | K35: 11
A36: NJ | B36: 10 | J36: Law | K36: 5
A37: NM | B37: 8 | J37: Loan | K37: 7
A38: NV | B38: 7 | J38: Penalty/disincentive | K38: 2
A39: NY | B39: 25 | J39: Rate | K39: 8
A40: OH | B40: 6 | J40: Rebate | K40: 58
A41: OK | B41: 6 | J41: Sales/use tax exemption | K41: 4
... A43: PA | B43: 8 | J43: Technical Assistance | K43: 2
A44: Regional - state admin | B44: 2
A45: RI | B45: 2
A46: SC | B46: 4
A47: SD | B47: 3
A48: TN | B48: 2
A49: TX | B49: 8
A50: UT | B50: 7
A51: VA | B51: 3
A52: VT | B52: 5
A53: WA | B53: 10
A54: WI | B54: 6
A55: WV | B55: 2
A56: WY | B56: 4
A57: (blank)
A58: Tribal Government or Indigenous Communities | B58: 4
A59: ND | B59: 1
A60: CO | B60: 1
A61: KS | B61: 1
A62: Grand Total | B62: 387
A63: #VALUE! | B63: 3
A64: #VALUE! | B64: 7
A65: #VALUE! | B65: 4
A66: #VALUE! | B66: 3
A67: #VALUE! | B67: 0
A68: #VALUE! | B68: 3
A69: NA Tribe | B69: 3
A70: #VALUE! | B70: 6
A71: #VALUE! | B71: 0
A72: #VALUE! | B72: 3
A73: #VALUE! | B73: 2
A74: #VALUE! | B74: 4
A75: #VALUE! | B75: 2
A76: #VALUE! | B76: 7
A77: #VALUE! | B77: 16
A78: #VALUE! | B78: 2
A79: #VALUE! | B79: 6
A80: #VALUE! | B80: 10
A81: #VALUE! | B81: 4
A82: Regional - state admin | B82: 2
A83: #VALUE! | B83: 2
A84: #VALUE! | B84: 3
A85: #VALUE! | B85: 1
A86: #VALUE! | B86: 1
A87: #VALUE! | B87: 6
A88: #VALUE! | B88: 4
A89: #VALUE! | B89: 3
A90: #VALUE! | B90: 6
A91: #VALUE! | B91: 5
A92: #VALUE! | B92: 0
A93: #VALUE! | B93: 4
A94: #VALUE! | B94: 0
B96: =AVERAGE(B41:B94) -> 11.301887
B97: =COUNTIF(B41:B94, 0) -> 4

Sheet AFDC laws_and_incentives Nov 10
A1: Law Id | B1: Relevant? | C1: Complete? | D1: State | E1: Title | F1: Text | G1: Enacted Date | H1: Amended Date | I1: Recent? | J1: Sequence Number | K1: Type | L1: Agency | M1: Significant Update Date | N1: Expired Date | O1: Archived Date | P1: Repealed Date | Q1: Topic | R1: Technology Categories | S1: Incentive Categories | T1: Regulation Categories | U1: User Categories | V1: References
A2: 5197 | B2: N | D2: AK | E2: Alternative Fuel Vehicle Acquisition Requirement | F2: The Alaska Department of Transportation and Public Facilities (Department) must evaluate the cost, efficiency, and commercial availability of alternative fuels for automotive purposes every five years, and purchase or convert to vehicles that operate using alternative fuels whenever practical. The Department may participate in joint ventures with public or private partners to foster the availability of alternative fuels for consumers. (Reference [Alaska Statutes](http://www.akleg.gov/basis/statutes.asp) 44.42.020) | I2: FALSE | J2: 25 | K2: Laws and Regulations | R2: AFTMKTCONV|BIOD|ETH|ELEC|HY|NG|PHEV|LPG | T2: REQ | U2: OTHER | V2: http://www.akleg.gov/basis/statutes.asp
A3: 12571 | B3: N | D3: AK | E3: Residential Electric Vehicle Supply Equipment (EVSE) Credit â€“ Chugach Electric Association (CEA) | F3: CEA provides eligible residential customers a \$200 bill credit per residential charger, up to two chargers per household, for sharing information on plug-in electric vehicles, EVSEs, and average miles driven per year. For more information, including eligibility requirements, see the CEA [Electric Vehicles](https://www.chugachelectric.com/energy-solutions/electric-vehicles) page. | I3: FALSE | J3: 15 | K3: Utility/Private Incentives | M3: 2021-05-11 17:12:30 UTC | Q3: Vehicle Purchase and Infrastructure Development Incentives | R3: ELEC|PHEV | S3: RBATE | U3: IND
A4: 12572 | B4: Y | C4: Y | D4: AK | E4: Commercial Electric Vehicle Supply Equipment (EVSE) Rebates - Chugach Electric Association (CEA) | F4: CEA offers rebates to commercial customers for the purchase and installation of Level 2 EVSE. Rebates are available in the following amounts: Applicant Type Rebate Amounts --------------------------------------------------------------------- ----------------------------------------------- Workplace \$5,000 per EVSE; up to \$15,000 per location Hotel Up to \$2,500 per location Fleet \$1,500 per EVSE; up to \$3,000 per location Rental Car Companies at Ted Stevens Anchorage International Airport \$1,500 per EVSE; up to \$3,000 per location Commercial \$500 per EVSE; up to \$1,000 per location Fleet recipients must agree to share observations regarding the use and economy of an electric vehicle in their fleet with CEA. Workplace recipients must agree to provide information about the usage of EVSE with CEA for 36 months after installation. For more information, including eligibility requirements, see the CEA [Electric Vehicles] https://www.chugachelectric.com/energy-solutions/electric-vehicles) page. | I4: FALSE | J4: 16 | K4: Utility/Private Incentives | M4: 2021-05-11 17:17:06 UTC | Q4: Vehicle Purchase and Infrastructure Development Incentives | R4: ELEC|PHEV | S4: RBATE | U4: STATION|FLEET | V4: https://www.chugachelectric.com/energy-solutions/electric-vehicles/fleet-ev-charging-program
A5: 12573 | B5: N | D5: AK | E5: Electric Vehicle (EV) Rebate â€“ Alaska Power and Telephone (AP&T) | F5: AP&T offers a rebate of \$1,000 to residential customers who own a new or used EV, including electric motorcycles, with a minimum battery size of at least 16 kilowatts. For more information, see the AP&T [Amp-Up](https://www.aptalaska.com/amp-up/) website. | I5: FALSE | J5: 17 | K5: Utility/Private Incentives | M5: 2021-05-11 17:21:47 UTC | Q5: Vehicle Purchase and Infrastructure Development Incentives | R5: ELEC | S5: RBATE | U5: IND
A6: 12574 | B6: N | D6: AK | E6: Plug-In Electric Vehicle (PEV) Time-of-Use (TOU) Rate â€“ Alaska Electric Light & Power (AELP) | F6: AELP offers a TOU rate to residential customers that own or lease PEVs with batteries greater than 16 kilowatts. For more information, see the AELP [Electric Vehicle](https://www.aelp.com/Energy-Conservation/Electric-Vehicles) website. | I6: FALSE | J6: 18 | K6: Utility/Private Incentives | M6: 2021-05-11 17:23:27 UTC | R6: ELEC|PHEV | S6: OTHER | U6: IND
A7: 6546 | B7: N | D7: AL | E7: Fuel-Efficient Green Fleets Policy and Fleet Management Program Development | F7: The Alabama Legislature established a Green Fleets Review Committee (Committee) and Green Fleets Policy (Policy) outlining a procedure for procuring state vehicles based on criteria that includes fuel economy and life cycle costing. State fleet managers must classify their vehicle inventory for compliance with the Policy and submit annual plans for procuring fuel-efficient vehicles. These plans must reflect a 4% annual increase in average fleet fuel economy for light-duty vehicles, a 3% annual increase in average fleet fuel economy for medium-duty vehicles, and a 2% annual increase in average fleet fuel economy for heavy-duty vehicles per fiscal year. Government entities must manage and operate their fleets in a manner that is energy efficient, minimizes emissions, and reduces petroleum dependency by using specified proven technology the Committee identifies. (Reference [Code of Alabama](http://alisondb.legislature.state.al.us/acas/ACASLoginfire.asp) 41-17A-1 through 41-17A-6) | G7: 2009-01-01 00:00:00 UTC | H7: 2013-03-21 00:00:00 UTC | I7: FALSE | J7: 25 | K7: Laws and Regulations | R7: BIOD|ETH|ELEC|EFFEC|HEV|HY|IR|NG|PHEV|LPG | T7: REQ | U7: GOV | V7: http://alisondb.legislature.state.al.us/acas/ACASLoginfire.asp|http://governor.alabama.gov/news/newsroom.aspx?t=29
A8: 9374 | B8: N | D8: AL | E8: Residential Plug-In Electric Vehicle (PEV) Time-Of-Use (TOU) Rates - Alabama Power | F8: Alabama Power offers a discounted TOU rate to residential customers that own or lease a PEV. Under this rate rider, customers receive a discount on all energy consumed during the discount period without separately metering PEV charging. For more information, see the Alabama Power [PEV rate](https://www.alabamapower.com/content/dam/alabamapower/Rates/pev.pdf) website. | I8: FALSE | J8: 20 | K8: Utility/Private Incentives | R8: ELEC|PHEV | S8: OTHER | U8: STATION|PURCH|IND
A9: 12015 | B9: N | D9: AL | E9: Public Utility Definition | F9: An entity that owns, operates, leases, or controls electric vehicle supply equipment is not defined as a public utility. (Reference [Alabama Public Service Commission](https://www.pscpublicaccess.alabama.gov/pscpublicaccess/page/psc-searches/portal.aspx) Docket No. 32694) | G9: 2018-06-22 00:00:00 UTC | I9: FALSE | J9: 22 | K9: Laws and Regulations | M9: 2018-08-06 19:09:33 UTC | R9: ELEC|PHEV | T9: UTILITY | U9: STATION
A10: 12205 | B10: N | D10: AL | E10: Plug-In Electric Vehicle (PEV) Fee | F10: Effective January 1, 2020, PEV owners must pay an annual fee in addition to standard registration fees. All-electric vehicle owners must pay an annual fee of \$200 and plug-in hybrid electric vehicle owners must pay an annual fee of \$100. Beginning July 1, 2023 and every fourth year thereafter, PEV fees will increase by \$3. A portion of fees contribute to the Electric Transportation Infrastructure Grant Program, which provides grants for electric vehicle supply equipment. (Reference [Code of Alabama](http://alisondb.legislature.state.al.us/acas/ACASLogin.asp) 40-12-242) | G10: 2019-03-12 00:00:00 UTC | I10: FALSE | J10: 23 | K10: Laws and Regulations | M10: 2019-05-01 16:40:48 UTC | R10: ELEC|PHEV | T10: FUEL | U10: IND | V10: http://www.legislature.state.al.us/aliswww/default.aspx|http://alisondb.legislature.state.al.us/acas/ACASLogin.asp
A11: 12206 | B11: N | D11: AL | E11: Electric Vehicle Supply Equipment (EVSE) Grant Program | F11: The Alabama Department of Transportation is authorized to administer the Electric Transportation Infrastructure Grant Program to distribute grants for EVSE infrastructure expansion. (Reference [Code of Alabama](http://alisondb.legislature.state.al.us/acas/ACASLogin.asp) 40-12-242) | G11: 2019-03-12 00:00:00 UTC | I11: FALSE | J11: 3 | K11: State Incentives | M11: 2019-05-01 16:43:40 UTC | R11: ELEC|PHEV | T11: OTHER | U11: STATION | V11: http://www.legislature.state.al.us/aliswww/default.aspx|http://alisondb.legislature.state.al.us/acas/ACASLogin.asp
A12: 12273 | B12: Y | C12: Y | D12: AL | E12: Medium- and Heavy-Duty Diesel Vehicle Replacement Rebates | F12: The Alabama Department of Economic and Community Affairs (ADECA) offers grants for light-duty electric vehicle supply equipment (EVSE) and the replacement of qualified medium- and heavy-duty diesel vehicles with new diesel or alternative fuel vehicles. Grants are available for EVSE; medium- and heavy-duty trucks; school, shuttle, and transit buses; freight switchers; airport ground support equipment; and forklifts and port cargo handling equipment. Vehicles must meet model year requirements. Funding amounts are based on vehicle type, fuel type, and applicant type. The program is funded by Alabama's portion of the [Volkswagen Environmental Mitigation Trust](https://www.epa.gov/enforcement/volkswagen-clean-air-act-civil-settlement). For more information, including program guidance and the application, see the ADECA [Volkswagen Settlement](https://adeca.alabama.gov/Divisions/energy/vw/Pages/default.aspx) website. | I12: FALSE | J12: 8 | K12: State Incentives | M12: 2019-09-06 19:39:28 UTC | R12: AFTMKTCONV|ELEC|HEV|NG|PHEV|LPG | S12: RBATE | U12: FLEET|GOV
A13: 12642 | B13: Y | C13: Y | D13: AL | E13: Commercial Plug-In Electric Vehicle (PEV) Time-Of-Use (TOU) Rates - Alabama Power | F13: Alabama Power offers a discounted Business Electric Vehicle TOU (BEVT) rate to commercial and industrial customers to charge fleet-owned PEV or to provide electric vehicle supply equipment (EVSE) for the purpose of public charging. Eligible customers electricity usage must be separately metered from all other electrical load and be for the exclusive purpose of charging PEVs. For more information, see the Alabama Power [BEVT rate](https://www.alabamapower.com/business/pricing-and-rates/about-our-pricing.html) website. | I13: FALSE | J13: 24 | K13: Utility/Private Incentives | M13: 2021-07-22 16:36:58 UTC | R13: ELEC|PHEV | S13: OTHER | U13: STATION|PURCH|FLEET
A14: 5815 | B14: N | D14: AR | E14: Alternative Fuels Tax and Reporting | F14: Excise taxes on alternative fuels are imposed on a gasoline gallon equivalent (GGE) basis. The tax rate for each alternative fuel type is based on the number of motor vehicles licensed in the state that use the specific fuel, not including vehicles the federal government owns or leases. The Arkansas Department of Finance and Administration (DFA) and the Arkansas State Highways and Transportation Department must prepare an annual report with the number of alternative fuel vehicles licensed in the state and the tax revenue generated. The DFA must establish the tax rate annually by April 1. Licensed alternative fuel suppliers must pay alternative fuel taxes for product dispensed, sold to a dealer or user, or used in a motor vehicle owned or operated by the alternative fuel supplier. Alternative fuel suppliers must prepare a monthly report on the number of GGEs of alternative fuels sold and possess a sufficient number of credits (also known as sales tickets) to cover the alternative fuel sales tax. (Reference [Arkansas Code](http://www.lexisnexis.com/hottopics/arcode/Default.asp) 19-6-301, 26-56-502, 26-56-601, and 26-62-201 through 26-62-209) | I14: FALSE | J14: 33 | K14: Laws and Regulations | R14: BIOD|ETH|ELEC|HY|NG|PHEV|LPG | T14: FUEL | U14: STATION|PURCH | V14: http://www.arkleg.state.ar.us/
A15: 5817 | B15: N | D15: AR | E15: Alternative Fuel Vehicle Conversion Notification | F15: Any individual or company who converts a vehicle to operate on an alternative fuel must report the conversion to the Arkansas Department of Finance and Administration (DFA) within 10 days of the conversion. An owner or operator who fails to report such a conversion may be subject to a penalty. For more information, including reporting forms, see the [DFA](https://www.dfa.arkansas.gov/excise-tax/motor-fuel-tax/motor-fuel-tax-forms/) website. (Reference [Arkansas Code](http://www.lexisnexis.com/hottopics/arcode/Default.asp) 26-56-315 and 26-62-214) | I15: FALSE | J15: 31 | K15: Laws and Regulations | R15: AFTMKTCONV|BIOD|ETH|ELEC|HY|NG|PHEV|LPG | T15: REGIS | U15: MAN|FLEET|GOV|IND | V15: http://www.arkleg.state.ar.us/
A16: 11930 | B16: N | D16: AR | E16: Public Utility Definition | F16: A person or corporation that supplies electricity to the public exclusively to charge plug-in electric vehicles is not defined as a public utility. (Reference [Arkansas Code](http://www.lexisnexis.com/hottopics/arcode/Default.asp) 23-1-101(9)) | G16: 2017-02-28 00:00:00 UTC | I16: FALSE | J16: 25 | K16: Laws and Regulations | M16: 2018-03-21 14:55:38 UTC | R16: ELEC|PHEV | T16: UTILITY | U16: STATION | V16: http://www.arkleg.state.ar.us/assembly/2017/2017R/Pages/Home.aspx|https://advance.lexis.com/container?config=00JAA3ZTU0NTIzYy0zZDEyLTRhYmQtYmRmMS1iMWIxNDgxYWMxZTQKAFBvZENhdGFsb2cubRW4ifTiwi5vLw6cI1uX&crid=79b4d9b8-36cd-45b0-b1db-b4ec11e70050&prid=0dd0dc87-14ec-4c78-b77a-c2de7318afdb
A17: 12182 | B17: N | D17: AR | E17: Hybrid Electric Vehicle (HEV) and Plug-In Electric Vehicle (PEV) Fee | F17: HEV and PEV owners must pay an annual fee in addition to other registration fees. The fee is \$200 for all-electric vehicles and \$100 for plug-in hybrid electric vehicles. Beginning January 1, 2022, HEV owners must pay an annual fee of \$50 for HEVs. Fees contribute to the State Highway and Transportation Department Fund. Vehicles that are registered with a special license plate or special license plate with permanent decal pursuant to Arkansas Code 27-24-201 are exempt from the annual fee. (Reference [Senate Bill](http://www.arkleg.state.ar.us/assembly/) 225, 2021, [Senate Bill](http://www.arkleg.state.ar.us/assembly/%22) 246, 2021, and [Arkansas Code](http://www.lexisnexis.com/hottopics/arcode/Default.asp) 27-14-614 and 27-24-201) | G17: 2019-03-05 00:00:00 UTC | H17: 2021-03-17 00:00:00 UTC | I17: FALSE | J17: 25 | K17: Laws and Regulations | M17: 2019-04-02 15:10:55 UTC | R17: ELEC|HEV|PHEV | T17: FUEL | U17: IND | V17: http://www.lexisnexis.com/hottopics/arcode/Default.asp|http://www.arkleg.state.ar.us/assembly/2019/2019R/Pages/Home.aspx|http://www.arkleg.state.ar.us/assembly/
A18: 12667 | B18: Y | C18: Y | D18: AR | E18: Electric Vehicle Supply Equipment (EVSE) Grants | F18: The Arkansas Department of Environmental Quality\'s (ADEQ) Level 2 EVSE Rebate program offers rebates to government, private, and non-profit entities for the construction and installation costs of Level 2 EVSE. Funding is available in the following amounts: Access Applicant Type Maximum Rebate (One EVSE Port) Maximum Rebate (Two or More EVSE Ports) Public Government \$6,850 \$9,300 Public Non-Government \$5,325 \$7,225 Private Workplace \$1,875 \$3,375 Private Multi-Unit Dwelling \$1,875 \$3,375 Rebates are awarded on a first-come, first served basis. The program is funded by Arkansas\'s portion of the Volkswagen Environmental Mitigation Trust. For more information, including eligibility and how to apply, see the ADEQ\'s Volkswagen Settlement website. (Reference [Arkansas Code](http://www.lexisnexis.com/hottopics/arcode/Default.asp) 15-10-101 and 19-5-1273) | I18: TRUE | J18: 150 | K18: State Incentives | M18: 2021-09-13 18:03:00 UTC | R18: ELEC|PHEV | S18: GNT | U18: STATION|FLEET|GOV|MUD|IND | V18: https://www.adeq.state.ar.us/air/planning/vw.aspx
A19: 4178 | B19: N | D19: AZ | E19: Alternative Fuel Vehicle (AFV) Emissions Test Exemption | F19: Qualified AFVs registered for the first time in Arizona are not required to complete emissions testing. This exemption does not apply after the first registration year. All AFVs, excluding electric, solar, and hydrogen vehicles, used to commute into Phoenix or Tucson, are required to be emissions tested before they are registered. For more information, visit the [Arizona Department of Environmental Quality](https://www.azdeq.gov/) website. (Reference [Arizona Revised Statutes](http://www.azleg.gov/ArizonaRevisedStatutes.asp) 49-542 and 49-542.05) | G19: 2016-01-01 00:00:00 UTC | I19: FALSE | J19: 42 | K19: State Incentives | M19: 2015-05-13 18:37:27 UTC | R19: ELEC|HY|NG|LPG | S19: EXEM | U19: FLEET|GOV|IND | V19: http://www.azleg.gov/ArizonaRevisedStatutes.asp
A20: 4179 | B20: Y | C20: Y | D20: AZ | E20: Reduced Alternative Fuel Vehicle (AFV) License Tax | F20: The vehicle license tax for an AFV registered in Arizona is \$4 for every \$100 in assessed value. The minimum amount of the annual AFV license tax is \$5. AFV assessed values are determined as follows: - AFVs registered prior to January 1, 2022: 1% of the manufacturer's suggested retail price (MSRP) - AFVs initially registered between January 1, 2022 and December 31, 2022: 20% of the MSRP. For each succeeding year, for the purpose of calculating the license tax, the value of the AFV is reduced by 15% from the value from the preceding year. For the purpose of this tax, AFVs include those powered exclusively by propane, natural gas, electricity, hydrogen, or a blend of hydrogen with propane or natural gas. For more information, see the ADOT [AFV](https://azdot.gov/motor-vehicles/vehicle-services/vehicle-registration/alternative-fuel-vehicle) website. The reduced alternative fuel vehicle license tax does not apply to any vehicle purchased on or after December 31, 2022. (Reference [Arizona Revised Statutes](http://www.azleg.gov/ArizonaRevisedStatutes.asp) 1-215, 28-5801, 28-5805) | G20: 2018-04-25 00:00:00 UTC | H20: 2019-06-07 00:00:00 UTC | I20: FALSE | J20: 30 | K20: State Incentives | M20: 2019-06-28 23:33:14 UTC | R20: ELEC|HY|NG|PHEV|LPG | S20: TAX | U20: FLEET|GOV|IND | V20: http://www.azleg.gov/ArizonaRevisedStatutes.asp|https://www.azleg.gov/|https://www.azleg.gov/
A21: 5188 | B21: N | D21: AZ | E21: State Vehicle Acquisition and Fuel Use Requirements | F21: Arizona state agencies, boards, and commissions must purchase hybrid electric vehicles, alternative fuel vehicles (AFVs), or vehicles that meet set greenhouse gas emissions standards. At least 75% of light-duty state fleet vehicles operating in counties with a population of more than 250,000 people must be capable of operating on alternative fuels. If the AFVs operate in counties with populations of more than 1.2 million people, those vehicles must meet U.S. Environmental Protection Agency emissions standards for Low Emission Vehicles. Alternatively, the state fleet may meet AFV acquisition requirements through biodiesel or alternative fuel use or apply for waivers. For the purpose of these requirements, alternative fuels include propane, natural gas, electricity, hydrogen, qualified diesel fuel substitutes, E85, and a blend of hydrogen with propane or natural gas. (Reference [Arizona Revised Statutes](http://www.azleg.gov/ArizonaRevisedStatutes.asp) 41-803) | H21: 2010-02-02 00:00:00 UTC | I21: FALSE | J21: 85 | K21: Laws and Regulations | R21: BIOD|ETH|ELEC|HEV|HY|NG|PHEV|LPG | T21: REQ | U21: GOV | V21: http://azmemory.azlibrary.gov/cdm/singleitem/collection/execorders/id/700|http://www.azleg.gov/ArizonaRevisedStatutes.asp
A22: 5426 | B22: N | D22: AZ | E22: Alternative Fuel Vehicle (AFV) Parking Incentive | F22: An individual driving a dedicated AFV may park without penalty in parking areas that are designated for carpool operators, provided the vehicle is using alternative fuel. Recognized alternative fuels include propane, natural gas, electricity, hydrogen, and a blend of hydrogen with propane or natural gas. (Reference [Arizona Revised Statutes](http://www.azleg.gov/ArizonaRevisedStatutes.asp) 1-215 and 28-877) | G22: 2013-01-01 00:00:00 UTC | I22: FALSE | J22: 25 | K22: State Incentives | R22: ELEC|HY|NG|PHEV|LPG | S22: EXEM | U22: FLEET|GOV|IND | V22: http://www.azleg.gov/ArizonaRevisedStatutes.asp|http://www.azleg.gov/ArizonaRevisedStatutes.asp
A23: 5595 | B23: N | D23: AZ | E23: Alternative Fuel Vehicle (AFV) Dealer Information Dissemination Requirement | F23: New motor vehicle dealers must make information about AFVs and Arizona-based incentives for purchasing or leasing AFVs available to the public. For the purpose of these requirements, alternative fuels include propane, natural gas, electricity, hydrogen, and a blend of hydrogen with propane or natural gas. (Reference [Arizona Revised Statutes] http://www.azleg.gov/ArizonaRevisedStatutes.asp) 28-4414) | I23: FALSE | J23: 110 | K23: Laws and Regulations | R23: ELEC|HY|NG|PHEV|LPG | T23: OTHER | U23: OTHER | V23: http://www.azleg.gov/ArizonaRevisedStatutes.asp
A24: 5596 | B24: N | D24: AZ | E24: Electric Vehicle (EV) Parking Space Regulation | F24: An individual is not allowed to stop, stand, or park a motor vehicle within any parking space specifically designated for parking and charging EVs unless the motor vehicle is an EV and has been issued an alternative fuel vehicle special plate or sticker. Violators may be subject to a civil penalty of at least \$350. (Reference [Arizona Revised Statutes](http://www.azleg.gov/ArizonaRevisedStatutes.asp) 28-876) | I24: FALSE | J24: 60 | K24: Laws and Regulations | R24: ELEC|PHEV | T24: OTHER | U24: FLEET|GOV|IND | V24: http://www.azleg.gov/ArizonaRevisedStatutes.asp
A25: 5872 | B25: N | D25: AZ | E25: Alternative Fuel Vehicle (AFV) Special License Plate | F25: The Arizona Department of Transportation (ADOT) must issue a special license plate to dedicated AFVs. Dedicated AFVs are defined as vehicles powered exclusively by propane, compressed natural gas, electricity, or hydrogen. AFVs must not be capable of operating on any other fuel type. There is no limit to the number of AFV license plates ADOT can issue. The Arizona Department of Environmental Quality (ADEQ) must inspect vehicles converted to operate solely on alternative fuel and issue an Alternative Fuel Certificate before converted vehicles may receive the AFV special plate. State or agency directors who conduct activities of a confidential nature and use AFVs are exempt from the requirement to display an AFV special license plate. For more information, see the ADOT [Specialty Plates](https://azdot.gov/motor-vehicles/vehicle-services/plates-and-placards) and ADEQ [Vehicle Emissions Testing](http://www.azdeq.gov/EmissionsTest) website. (Reference [Arizona Revised Statutes](https://www.azleg.gov/arstitle/) 1-215 and 28-2416) | I25: FALSE | J25: 50 | K25: Laws and Regulations | M25: 2020-06-12 19:43:42 UTC | R25: ELEC|HY|NG|LPG | T25: REGIS | U25: FLEET|GOV|IND | V25: http://www.azleg.gov/ArizonaRevisedStatutes.asp
A26: 5874 | B26: N | D26: AZ | E26: Alternative Fuel and Alternative Fuel Vehicle (AFV) Use Tax Exemption | F26: Arizona use taxes do not apply to natural gas or propane used in an AFV, AFVs converted to operate on alternative fuels, or the equipment used to convert a diesel vehicle to an AFV. Recognized alternative fuels include propane, natural gas, electricity, hydrogen, and a blend of hydrogen with propane or natural gas. (Reference [Arizona Revised Statutes](http://www.azleg.gov/ArizonaRevisedStatutes.asp) 42-5159) | I26: FALSE | J26: 35 | K26: State Incentives | R26: ELEC|HY|NG|PHEV|LPG | S26: EXEM|TAX | U26: AFP|PURCH|FLEET|GOV|IND | V26: http://www.azleg.gov/ArizonaRevisedStatutes.asp
A27: 6206 | B27: N | D27: AZ | E27: Joint Use of Government Fueling Infrastructure | F27: To the extent practical, an Arizona state agency or political subdivision that operates an alternative fueling station must allow vehicles, other state agencies, or political subdivisions to fuel at the station. For the purpose of this requirement, alternative fuels include propane, natural gas, electricity, hydrogen, and a blend of hydrogen with propane or natural gas. (Reference [Arizona Revised Statutes](http://www.azleg.gov/ArizonaRevisedStatutes.asp) 49-572) | I27: FALSE | J27: 80 | K27: Laws and Regulations | R27: ELEC|HY|NG|PHEV|LPG | T27: REQ | U27: STATION|OTHER | V27: http://www.azleg.gov/ArizonaRevisedStatutes.asp
A28: 8400 | B28: N | D28: AZ | E28: Municipal Alternative Fuel Vehicle (AFV) Acquisition Requirements | F28: Local governments in Maricopa, Pinal, and Yavapai counties with a population of more than 1.2 million people must develop and implement vehicle fleet plans to encourage and increase the use of alternative fuels in municipal fleets. At least 75% of the total municipal fleet must operate on alternative fuels. Alternatively, municipal fleets may meet AFV acquisition requirements through biodiesel or other alternative fuel use or apply for waivers. Local governments in counties with populations of more than 500,000 people with bus fleets must purchase or convert buses to operate on alternative fuels. For the purpose of these requirements, alternative fuels include propane, natural gas, electricity, hydrogen, qualified diesel fuel substitutes, E85, and a blend of hydrogen with propane or natural gas. (Reference [Arizona Revised Statutes](https://www.azleg.gov/arstitle/) 9-500.04, 49-474.01, 49-541, and 49-571) | I28: FALSE | J28: 90 | K28: Laws and Regulations | R28: BIOD|ETH|ELEC|HY|NG|PHEV|LPG | T28: REQ | U28: GOV | V28: http://www.azleg.state.az.us/
A29: 8402 | B29: N | D29: AZ | E29: Federal Fleet Operation Regulations | F29: Federal fleets based in Arizona that operate primarily in counties with a population of more than 1.2 million people must be comprised of at least 90% alternative fuel vehicles. Alternatively, federal fleets may meet acquisition requirements through alternative fuel use or apply for waivers. For the purpose of these requirements, alternative fuels include propane, natural gas, electricity, hydrogen, qualified diesel fuel substitutes, E85, and a blend of hydrogen with propane or natural gas. (Reference [Arizona Revised Statutes](https://www.azleg.gov/arstitle/) 49-573) | I29: FALSE | J29: 105 | K29: Laws and Regulations | R29: BIOD|ETH|ELEC|HEV|HY|NG|PHEV|LPG | T29: REQ | U29: GOV | V29: http://www.azleg.state.az.us/
A30: 11625 | B30: N | D30: AZ | E30: Plug-in Electric Vehicle (PEV) Time-Of-Use (TOU) Rate - Salt River Project (SRP) | F30: SRP offers a TOU rate for residential customers that own or lease a PEV. The TOU rate applies to daily super off-peak hours and additional off-peak hours on weekends, holidays, and some weekday hours. Eligible customers must be able to separately meter EV charger usage. For more information, including how to enroll, see the SRP [Electric Vehicle Price Plan](https://www.srpnet.com/prices/home/electricvehicle.aspx) website. | I30: FALSE | J30: 46 | K30: Utility/Private Incentives | M30: 2020-05-11 15:24:11 UTC | R30: ELEC|PHEV | S30: OTHER | U30: IND
A31: 11881 | B31: N | D31: AZ | E31: Regional Electric Vehicle (REV) West Plan | F31: Arizona joined Colorado, Idaho, Montana, Nevada, New Mexico, Utah, and Wyoming (Signatory States) in signing the REV West [memorandum of understanding](https://www.naseo.org/Data/Sites/1/revwest_mou.pdf) (MOU) to create an Intermountain West Electric Vehicle (EV) Corridor that will make it possible to seamlessly drive an EV across the Signatory States\' major transportation corridors. In 2019, the Signatory States signed a revised [REV West MOU](https://www.naseo.org/issues/transportation/rev-west) to update their EV corridor goals based on progress to date. Signatory States are committed to: - Educate consumers and fleet owners to raise EV awareness, reduce range anxiety, and increase EV adoption; - Coordinate on EV charging station locations to achieve a consistent user experience across Signatory States; - Use and promote the REV West [Voluntary Minimum Standards](https://www.naseo.org/Data/Sites/1/revwest_volminimumstandards.pdf) for EV charging stations and explore opportunities for implementing the standards in Signatory States; - Identify and develop opportunities to incorporate EV charging stations into planning and development processes such as building codes, metering policies, and renewable energy generation projects; - Encourage EV manufacturers to stock and market a wide variety of EVs within the Signatory States; - Identify, respond to, and collaborate on funding opportunities to support the development of the plan; and - Support the build-out of direct current (DC) fast charging stations along EV corridors through investments, partnerships, and other mechanisms. The Signatory States maintain a coordination group composed of senior leadership from each state who meet on a quarterly basis and report on the above actions. For more information, see the [REV West](https://www.naseo.org/issues/transportation/rev-west) website. | G31: 2017-10-04 00:00:00 UTC | H31: 2019-12-13 00:00:00 UTC | I31: FALSE | J31: 48 | K31: Laws and Regulations | M31: 2020-02-03 19:45:02 UTC | R31: ELEC|PHEV | T31: REQ|OTHER | U31: STATION|MAN|OTHER
A32: 11994 | B32: Y | C32: Y | D32: AZ | E32: Electric Vehicle Supply Equipment (EVSE) Rebate - Salt River Project (SRP) | F32: SRP offers a rebate of \$1,500 per port for commercial, workplace, and multifamily customers who install networked Level 2 EVSE. EVSE must be installed between May 1, 2021, and April 30, 2022. To receive a rebate, customers must apply on or before July 31, 2022. Applicants may receive a maximum of 50 rebates per program year. Funds will be awarded on a first-come, first-served basis. For more information, including how to apply, see the SRP [Business EV Charger Rebate](https://savewithsrpbiz.com/rebates/evcharger.aspx) website. | I32: FALSE | J32: 47 | K32: Utility/Private Incentives | M32: 2020-05-11 15:20:12 UTC | N32: 2022-07-31 00:00:00 UTC | R32: ELEC|PHEV | S32: RBATE | U32: STATION|PURCH|FLEET
A33: 12349 | B33: N | D33: AZ | E33: Electric Vehicle (EV) Definition and Implementation Plan | F33: The Arizona Corporation Commission (Commission) defines EVs as transportation vehicles that use electricity for propulsion. The Commission issued an EV policy statement that provides guidelines on EVs, charging infrastructure, and transportation electrification to utilities the Commission regulates. The policy addresses the state of EVs in Arizona, EV benefits, and barriers to adoption. This policy purposefully does not define the Commission's role with respect to electric vehicle charging infrastructure operated by non-utilities at this time, but will explore it in the future. For more information, see the Commission's [EV policy statement](https://docket.images.azcc.gov/0000195197.pdf) and the [Corporation Commission](https://www.azcc.gov/) website. (Reference [Docket](https://edocket.azcc.gov/Search/DocketDetailSearch?docketId=21658) RU-00000A-18-0284 decision number 77044) | G33: 2019-01-16 00:00:00 UTC | I33: FALSE | J33: 65 | K33: Laws and Regulations | M33: 2019-12-19 16:16:14 UTC | R33: ELEC|PHEV | T33: CCEINIT | U33: STATION|MAN|GOV|IND
A34: 12350 | B34: N | D34: AZ | E34: Electric Vehicle Supply Equipment (EVSE) Rebate - Tucson Electric Power (TEP) | F34: TEP provides a rebate to residential customers that covers up to 75% of the cost of EVSE installation. The maximum rebate awards are \$500 for a two-way charger and \$250 for a one-way charger. For more information, including how to apply, see the TEP [Electric Vehicle Rebates](https://www.tep.com/ev-rebates/) website. | I34: FALSE | J34: 55 | K34: Utility/Private Incentives | M34: 2019-12-19 16:24:21 UTC | Q34: Vehicle Purchase and Infrastructure Development Incentives | R34: ELEC|PHEV | S34: RBATE | U34: IND
A35: 12351 | B35: N | D35: AZ | E35: Plug-In Electric Vehicle (PEV) Charging Rates - Tuscon Electric Power (TEP) | F35: TEP offers three time-of-use (TOU) rates for residential customers with PEVs. For more information, see the TEP [Rates for EV Owners](https://www.tep.com/rates-for-ev-owners/) website. | I35: FALSE | J35: 60 | K35: Utility/Private Incentives | M35: 2019-12-19 16:46:58 UTC | R35: ELEC|PHEV | S35: OTHER | U35: IND
A36: 12402 | B36: Y | C36: Y | D36: AZ | E36: Commercial Electric Vehicle Supply Equipment (EVSE) Rebate â€“ Tucson Electric Power (TEP) | F36: TEP offers rebates and technical support to businesses, multi-family dwellings, and non-profit customers that purchase and install between two to five EVSE ports. TEP will evaluate the electrical capacity and supporting EVSE infrastructure at locations that install six or more ports on a case-by-case basis. Higher rebates are available for commercial customers located in lower-income areas. Low-income areas are defined as U.S. Census tracts where the average household income does not exceed 80% of the median Arizona household income. Rebates are available in the following amounts: <div> EVSE Type Location Rebate Low-Income Area Rebate ---------------------------------- -------------------------------------------------- ---------------------------------------------- ---------------------------------------------- Level 2 Workplace \$4,500 per port; up to 75% of project cost \$6,000 per port; up to 75% of project cost Level 2 Multi-Family Dwelling or Non-profit Organization \$6,000 per port; up to 85% of project cost \$9,000 per port; up to 85% of project cost Direct Current (DC) Fast Charger All \$24,000 per port; up to 75% of project cost \$40,000 per port; up to 75% of project cost </div> For more information, including project eligibility and how to apply, see the TEP [Smart Electric Vehicle Charging Program](https://www.tep.com/smart-ev-charging-program/) website. | I36: FALSE | J36: 65 | K36: Utility/Private Incentives | M36: 2020-05-11 18:09:06 UTC | R36: ELEC|PHEV | S36: RBATE | U36: STATION|FLEET|OTHER
A37: 12413 | B37: N | D37: AZ | E37: High Occupancy Vehicle (HOV) Lane Exemption | F37: The Arizona Department of Transportation (ADOT) allows qualified alternative fuel vehicles (AFV) with an AFV license plate to use HOV lanes, regardless of the number of occupants. Qualified AFVs are defined as vehicles powered exclusively by electricity, propane, natural gas, hydrogen, or a blend of hydrogen with propane or natural gas. Qualified AFVs must not be capable of operating on any other fuel type. This exemption expires September 20, 2025. For more information about vehicle eligibility and HOV access, visit the ADOT [AFV](https://azdot.gov/motor-vehicles/vehicle-services/vehicle-registration/alternative-fuel-vehicle) website. (Reference [Arizona Revised Statutes](https://www.azleg.gov/arstitle/) 1-215 and 28-2416) | I37: FALSE | J37: 27 | K37: State Incentives | M37: 2020-06-12 19:19:24 UTC | N37: 2025-09-30 00:00:00 UTC | R37: ELEC|HY|NG|LPG | S37: EXEM | U37: IND
A38: 12592 | B38: Y | C38: Y | D38: AZ | E38: Electric Vehicle Supply Equipment (EVSE) Pilot Program - Arizona Public Service Company (APS) | F38: APS offers free EVSE, installation, maintenance, and educational services to its workplace, fleet, and multi-unit dwelling customers through the Take Charge AZ pilot program. For more information, including eligibility, see the Reference [Take Charge AZ](https://www.aps.com/en/About/Sustainability-and-Innovation/Technology-and-Innovation/Electric-vehicles/Take-Charge-AZ) website. | I38: FALSE | J38: 43 | K38: Utility/Private Incentives | M38: 2021-06-11 21:12:05 UTC | R38: ELEC|PHEV | S38: OTHER | U38: STATION|FLEET|MUD
A39: 12593 | B39: Y | C39: Y | D39: AZ | E39: Commercial Electrification Rebates - Salt River Project (SRP) | F39: SRP offers commercial customers rebates for the purchase or lease of electric forklifts, electric truck refrigeration units (TRUs) charging infrastructure, truck charging bays, electric vehicle supply equipment (EVSE), and custom electrification projects. Equipment must be installed between May 1, 2021 and April 30, 2022. Rebate amounts for each technology type are as follows: Technology Rebate Amounts ----------------------------------------- --------------------------------------------------------------------------------------------- Class 1 or 2 Electric Forklift Up to \$2,000 per forklift Electric Forklift Charger \$150 per charger Electric TRU Charger \$1,000 per port Truck Stop and Truck Fleet Charging Bay \$1,000 per bay Level 2 EVSE \$1,500 per port; up to 50 ports Custom Electrification Project \$0.10 per annual kilowatt-hour load added by each piece of medium- or heavy-duty equipment Applicants may receive up \$50,000 in rebates through the Business Solutions Electric Technology Program. For more information, including eligibility requirements, visit the [Electrification Rebates](https://savewithsrpbiz.com/rebates/electrictechnology.aspx) website. | I39: FALSE | J39: 48 | K39: Utility/Private Incentives | M39: 2021-06-11 21:42:19 UTC | N39: 2022-07-31 00:00:00 UTC | R39: ELEC|OTHER|PHEV | S39: RBATE | U39: STATION|FLEET
A40: 12594 | B40: N | D40: AZ | E40: Commercial Electrification Assessment Incentives - Salt River Project (SRP) | F40: SRP offers funding to trained vendors who study electrification opportunities for commercial non-road equipment through the Electric Qualified Service Provider Assessment (eQSP) Program and on-road electrification opportunities for fleets under the Fleet Advisory Services (FAS) Program. Maximum funding amounts for each study through the eQSP and FAS Program are \$10,000 and \$20,000, respectively. For more information, including eligibility requirements, visit the [Electrification Rebates](https://savewithsrpbiz.com/rebates/electrictechnology.aspx) website. | I40: FALSE | J40: 49 | K40: Utility/Private Incentives | M40: 2021-06-11 22:04:01 UTC | R40: ELEC|HEV | S40: OTHER | U40: FLEET
A41: 12600 | B41: N | D41: AZ | E41: Plug-In Electric Vehicle (PEV) Rebate - Salt River Project (SRP) | F41: SRP offers residential customers a \$1,000 rebate for the purchase or lease of a PEV. For more information, including how to apply, see the [SRP Drive Electric](https://www.srpnet.com/electric/home/cars/start.aspx) website. | I41: FALSE | J41: 45 | K41: Utility/Private Incentives | M41: 2021-06-14 15:14:49 UTC | N41: 2021-12-31 00:00:00 UTC | R41: ELEC|PHEV | S41: RBATE | U41: IND
A42: 4219 | B42: N | D42: CA | E42: Employer Invested Emissions Reduction Funding - South Coast | F42: The South Coast Air Quality Management District (SCAQMD) administers the Air Quality Investment Program (AQIP). AQIP provides funding to allow employers within SCAQMD\'s jurisdiction to make annual investments into an administered fund to meet employers\' emissions reduction targets. The revenues collected are used to fund alternative mobile source emissions and trip reduction programs, including alternative fuel vehicle projects, on an on-going basis. Programs such as low emission, alternative fuel, or zero emission vehicle procurement and old vehicle scrapping may be considered for funding. For more information, including current requests for proposals and funding opportunities, see the [AQIP](http://www.aqmd.gov/home/programs/business/business-detail?title=air-quality-investment-program) website. | I42: FALSE | J42: 80 | K42: State Incentives | R42: BIOD|ETH|ELEC|HEV|HY|NG|PHEV|LPG | S42: GNT | U42: STATION|MAN|FLEET
A43: 4241 | B43: N | D43: CA | E43: Plug-In Electric Vehicle (PEV) Charging Rate Reduction - SMUD | F43: The Sacramento Municipal Utility District (SMUD) offers a discounted rate to residential customers for electricity used to charge PEVs. For more information, see the SMUD [Time-of-Day Rate](https://www.smud.org/en/Rate-Information/Time-of-Day-rates/Time-of-Day-5-8pm-Rate) website. | I43: FALSE | J43: 149 | K43: Utility/Private Incentives | M43: 2018-11-14 16:18:22 UTC | R43: ELEC|PHEV | S43: OTHER | U43: IND
A44: 4249 | B44: N | D44: CA | E44: Zero Emission Vehicle (ZEV) Production Requirements | F44: The California Air Resources Board (ARB) certifies new passenger cars, light-duty trucks, and medium-duty passenger vehicles as ZEVs if the vehicles produce zero exhaust emissions of any criteria pollutant (or precursor pollutant) under any and all possible operational modes and conditions. Manufacturers with annual sales between 4,501 and 60,000 vehicles may comply with the ZEV requirements through multiple alternative compliance options that include producing low emission vehicles and obtaining ZEV credits. Manufacturers with annual sales of 4,500 vehicles or less are not subject to this regulation. ARB\'s emissions control program for MY 2017 through 2025 combines the control of smog, soot, and greenhouse gases (GHGs) and requirements for ZEVs into a single package of standards called Advanced Clean Cars. In December 2012, ARB finalized new regulatory requirements that allow vehicle manufacturer compliance with the U.S. Environmental Protection Agency\'s GHG requirements for MY 2017-2025 to serve as compliance with California\'s adopted GHG emissions requirements for those same model years. The accounting procedures for MY 2018-2025 are based on a credit system as shown in the table below. The minimum ZEV requirement for each manufacturer includes the percentage of passenger cars and light-duty trucks produced by the manufacturer and delivered for sale in California. The regulation also includes opportunities for compliance with transitional zero emission vehicles, which must demonstrate certain exhaust emissions standards, evaporative emissions standards, on-board diagnostic requirements, and extended warranties. MY ZEV Requirement 2020 9.5% 2021 12% 2022 14.5% 2023 17% 2024 19.5% 2025 and later 22% For more information, see the [ZEV Program](http://www.arb.ca.gov/msprog/zevprog/zevprog.htm) website. (Reference [California Code of Regulations](http://www.oal.ca.gov/) Title 13, Section 1962 -1962.2) | H44: 2012-01-01 00:00:00 UTC | I44: FALSE | J44: 235 | K44: Laws and Regulations | R44: ELEC|HY|PHEV | T44: AIRQEMISSIONS|OTHER | U44: MAN | V44: http://www.oal.ca.gov/
A45: 5359 | B45: N | D45: CA | E45: High Occupancy Vehicle (HOV) and High Occupancy Toll (HOT) Lane Exemption | F45: Compressed natural gas, hydrogen, electric, and plug-in hybrid electric vehicles meeting specified California and federal emissions standards and affixed with a California Department of Motor Vehicles (DMV) Clean Air Vehicle sticker may use HOV lanes regardless of the number of occupants in the vehicle. Effective January 1, 2020, DMV issues Clean Air Vehicle stickers to first-time applicants that have a household income at or below 80% of the state median income. Stickers are valid through the following dates: - Red stickers issued on or after March 1, 2018, for a vehicle that had previously been issued a sticker between January 1, 2017, and March 1, 2018, expire January 1, 2022; - Purple stickers issued between January 1, 2019 and January 1, 2020, expire January 1, 2023; and, - Orange stickers issued on or after January 1, 2020, expire January 1, 2024. The California Department of Transportation must publish a report by June 1, 2023, detailing the number of stickers issued under this program. Vehicles originally issued white or green decals prior to 2017 are no longer eligible to participate in this program. Vehicles with stickers are also eligible for reduced rates on or exemptions from toll charges imposed on HOT lanes. For more information and restrictions, including a list of qualifying vehicles, see the California Air Resources Board [Carpool Stickers](http://www.arb.ca.gov/msprog/carpool/carpool.htm) website. (Reference [California Vehicle Code](http://www.oal.ca.gov/) 5205.5 and 21655.9) | G45: 2006-09-29 00:00:00 UTC | H45: 2018-09-13 00:00:00 UTC | I45: FALSE | J45: 25 | K45: State Incentives | M45: 2020-11-13 02:35:45 UTC | N45: 2024-01-01 00:00:00 UTC | R45: ELEC|HY|NG|PHEV | S45: EXEM | U45: FLEET|GOV|IND | V45: http://www.oal.ca.gov/|http://leginfo.legislature.ca.gov|http://leginfo.legislature.ca.gov/|http://leginfo.legislature.ca.gov/
A46: 5681 | B46: N | D46: CA | E46: Alternative Fuel and Vehicle Policy Development | F46: The California Energy Commission (CEC) must prepare and submit an Integrated Energy Policy Report (IEPR) to the governor on a biannual basis. The IEPR provides an overview of major energy trends and issues facing the state, including those related to transportation fuels, technologies, and infrastructure. The IEPR also examines potential effects of alternative fuels use, vehicle efficiency improvements, and shifts in transportation modes on public health and safety, the economy, resources, the environment, and energy security. The IEPR\'s primary purpose is to develop energy policies that conserve resources, protect the environment, ensure energy reliability, enhance the state\'s economy, and protect public health and safety. For the current IEPR, see the CEC [California\'s Energy Policy](http://www.energy.ca.gov/energypolicy/) website. As of November 1, 2015, and every four years thereafter, the CEC must also include in the IEPR strategies to maximize the benefits of natural gas in various sectors. This includes the use of natural gas as a transportation fuel. For more information, see the [2020 Integrated Energy Policy Report](https://www.energy.ca.gov/data-reports/reports/integrated-energy-policy-report/2020-integrated-energy-policy-report-update). (Reference [California Public Resources Code](http://www.oal.ca.gov/) 25302 and 25303.5) | G46: 2013-10-11 00:00:00 UTC | I46: FALSE | J46: 275 | K46: Laws and Regulations | R46: BIOD|ETH|ELEC|HEV|HY|NG|PHEV|LPG | T46: CCEINIT | U46: OTHER | V46: http://www.legislature.ca.gov/|http://www.oal.ca.gov/
A47: 5682 | B47: N | D47: CA | E47: Mobile Source Emissions Reduction Requirements | F47: Through its Mobile Sources Program, the California Air Resources Board (ARB) has developed programs and policies to reduce emissions from on-road heavy-duty diesel vehicles through the installation of verified diesel emission control strategies (VDECS) and vehicle replacements. The [on-road heavy-duty diesel vehicle rule]http://www.arb.ca.gov/msprog/onrdiesel/onrdiesel.htm) (i.e., truck and bus regulation) requires the retrofit and replacement of nearly all privately owned vehicles operated in California with a gross vehicle weight rating (GVWR) greater than 14,000 pounds (lbs.). School buses owned by private and public entities and federal government owned vehicles are also included in the scope of the rule. By January 1, 2023, nearly all vehicles must have engines certified to the 2010 engine standard or equivalent. The [drayage truck rule](http://www.arb.ca.gov/msprog/onroad/porttruck/porttruck.htm) regulates heavy-duty diesel-fueled vehicles that transport cargo to and from California\'s ports and intermodal rail facilities. The rule requires that certain drayage trucks be equipped with VDECS and that all applicable vehicles have engines certified to the 2007 emissions standards. By January 1, 2023, all applicable vehicles must have engines certified to 2010 standards. The [solid waste collection vehicle rule](http://www.arb.ca.gov/msprog/swcv/swcv.htm) regulates solid waste collection vehicles with a gross vehicle weight rating of 14,000 lbs. or more that operate on diesel fuel, have 1960 through 2006 engine models, and collect waste for a fee. The [fleet rule for public agencies and utilities](https://ww3.arb.ca.gov/msprog/publicfleets/publicfleets.htm) requires fleets to install VDECS on vehicles or purchase vehicles that run on alternative fuels or use advanced technologies to achieve emissions requirements by specified implementation dates. (Reference [California Code of Regulations](http://www.oal.ca.gov/) Title 13, 2021-2027) | H47: 2018-12-17 00:00:00 UTC | I47: FALSE | J47: 300 | K47: Laws and Regulations | M47: 2018-12-20 22:52:44 UTC | R47: BIOD|ELEC|HEV|HY|NG|PHEV|LPG | T47: REQ|AIRQEMISSIONS | U47: FLEET|GOV | V47: http://www.oal.ca.gov/
A48: 6010 | B48: N | D48: CA | E48: Fleet Vehicle Procurement Requirements | F48: When awarding a vehicle procurement contract, every city, county, and special district, including school and community college districts, may require that 75% of the passenger cars and/or light-duty trucks acquired be energy-efficient vehicles. By definition, this includes hybrid electric vehicles and alternative fuel vehicles that meet California\'s advanced technology partial zero emission vehicle standards. Vehicle procurement contract evaluations may consider fuel economy and life cycle factors for scoring purposes. (Reference [California Public Resources Code](http://www.oal.ca.gov/) 25725-25726) | I48: FALSE | J48: 265 | K48: Laws and Regulations | R48: ELEC|EFFEC|HEV|HY|NG|PHEV | T48: REQ | U48: FLEET|GOV | V48: http://www.oal.ca.gov/
A49: 6132 | B49: Y | C49: Y | D49: CA | E49: Alternative Fuel Vehicle (AFV) and Fueling Infrastructure Grants | F49: The Motor Vehicle Registration Fee Program (Program) provides funding for projects that reduce air pollution from on- and off-road vehicles. Eligible projects include purchasing AFVs and developing alternative fueling infrastructure. Contact [local air districts](https://ww2.arb.ca.gov/air-pollution-control-districts) and see the [Program](https://ww2.arb.ca.gov/resources/fact-sheets/motor-vehicle-registration-fee-program) website for more information about available grant funding and distribution from the Program. (Reference [California Health and Safety Code](http://www.oal.ca.gov/) 44220 (b)) | G49: 2009-06-04 00:00:00 UTC | I49: FALSE | J49: 35 | K49: Laws and Regulations | R49: ELEC|HY|NG|PHEV|LPG | T49: OTHER | U49: STATION|FLEET|GOV | V49: http://www.oal.ca.gov/
A50: 6135 | B50: Y | C50: Y | D50: CA | E50: Technology Advancement Funding - South Coast | F50: The South Coast Air Quality Management District\'s (SCAQMD) Clean Fuels Program provides funding for research, development, demonstration, and deployment projects that are expected to help accelerate the commercialization of advanced low-emission transportation technologies. Eligible projects include powertrains and energy storage or conversion devices, including fuel cells and batteries, and implementation of clean fuels, including the necessary infrastructure. Qualified clean fuels include, but are not limited to, natural gas, propane, and hydrogen. Projects are selected via specific requests for proposals on an as-needed basis or through unsolicited proposals. For more information, see the SCAQMD [Research, Development, Demonstration, and Deployment](https://www.aqmd.gov/home/technology/research-development-and-demontration) website. | I50: FALSE | J50: 82 | K50: State Incentives | R50: ELEC|HY|NG|PHEV|LPG | S50: GNT | U50: STATION|MAN|OTHER
A51: 6142 | B51: N | D51: CA | E51: Plug-In Electric Vehicle (PEV) Charging Rate Reduction - LADWP | F51: The Los Angeles Department of Water and Power (LADWP) offers a \$0.025 per kilowatt-hour discount for electricity used to charge PEVs during off-peak times. Residential customers who install a separate time-of-use meter panel will also receive a \$250 credit. For more information, see the LADWP [Electric Vehicle Incentives](https://www.ladwp.com/ladwp/faces/wcnav_externalId/r-gg-EVincentives?_adf.ctrl-state=il6iu2y7z_34&_afrLoop=203033140060675&_afrWindowMode=0&_afrWindowId=kfolzdw9d_1#%40%3F_afrWindowId%3Dkfolzdw9d_1%26_afrLoop%3D203033140060675%26_afrWindowMode%3D0%26_adf.ctrl-state%3Dkfolzdw9d_25) website. | I51: FALSE | J51: 140 | K51: Utility/Private Incentives | R51: ELEC|PHEV | S51: OTHER | U51: STATION|PURCH|IND
A52: 6143 | B52: N | D52: CA | E52: Plug-In Electric Vehicle (PEV) Charging Rate Reduction - SCE | F52: Southern California Edison (SCE) offers a discounted rate to customers for electricity used to charge PEVs. Two rate schedules are available for PEV charging during on- and off-peak hours. For more information, see the SCE [Electric Vehicle Plans](https://www.sce.com/residential/rates/electric-vehicle-plans) website. | I52: FALSE | J52: 145 | K52: Utility/Private Incentives | R52: ELEC|PHEV | S52: OTHER | U52: IND
A53: 6307 | B53: Y | C53: Y | D53: CA | E53: Alternative Fuel and Vehicle Incentives | F53: The California Energy Commission (CEC) administers the Clean Transportation Program (Program) to provide financial incentives for businesses, vehicle and technology manufacturers, workforce training partners, fleet owners, consumers, and academic institutions with the goal of developing and deploying alternative and renewable fuels and advanced transportation technologies. Funding areas include: - Electric vehicles and charging infrastructure; - Hydrogen vehicles and refueling infrastructure; - Medium- and heavy-duty zero emission vehicles; - Natural gas vehicles and refueling infrastructure; - Biofuels; and, - Workforce development. The CEC must prepare and adopt an annual [Investment Plan](https://www.energy.ca.gov/transportation/arfvtp/investmentplans.html) for the Program to establish funding priorities and opportunities that reflect program goals and to describe how program funding will complement other public and private investments. For more information, see the [Program](https://www.energy.ca.gov/programs-and-topics/programs/clean-transportation-program) website. (Reference [California Health and Safety Code](http://www.oal.ca.gov/) 44270-44274.7 and [California Code of Regulations](http://www.oal.ca.gov/), Title 13, Chapter 8.1) | G53: 2007-10-14 00:00:00 UTC | H53: 2012-10-05 00:00:00 UTC | I53: FALSE | J53: 20 | K53: State Incentives | R53: AFTMKTCONV|BIOD|ETH|ELEC|HY|NG|PHEV|LPG | S53: GNT|LOANS | U53: STATION|FLEET|GOV|OTHER|IND | V53: http://www.oal.ca.gov/
A54: 6489 | B54: N | D54: CA | E54: Plug-In Electric Vehicle (PEV) and Compressed Natural Gas (CNG) Rate Reduction - PG&E | F54: Pacific Gas & Electric (PG&E) offers discounted residential time-of-use rates for electricity used for PEV charging during off-peak hours. Discounted rates are also available for CNG or uncompressed natural gas used in vehicle home fueling appliances. For more information, see the PG&E [Electric Vehicle Rate Plans](https://www.pge.com/en_US/residential/rate-plans/rate-plan-options/electric-vehicle-base-plan/electric-vehicle-base-plan.page?) and [CNG for Vehicles](http://www.pge.com/myhome/environment/pge/cleanair/naturalgasvehicles/rates/) websites. | I54: FALSE | J54: 152 | K54: Utility/Private Incentives | R54: ELEC|NG|PHEV | S54: OTHER | U54: IND
A55: 6490 | B55: N | D55: CA | E55: Alternative Fuel and Hybrid Electric Vehicle Retrofit Regulations | F55: Converting a vehicle to operate on an alternative fuel in lieu of the original gasoline or diesel fuel is prohibited unless the California Air Resources Board (ARB) has evaluated and certified the retrofit system. ARB will issue certification to the manufacturer of the system in the form of an Executive Order once the manufacturer demonstrates compliance with the emissions, warranty, and durability requirements. A manufacturer is defined as a person or company who manufactures or assembles an alternative fuel retrofit system for sale in California; this definition does not include individuals wishing to convert vehicles for personal use. Individuals interested in converting their vehicles to operate on an alternative fuel must ensure that the alternative fuel retrofit systems used for their vehicles have been ARB certified. For more information, see the ARB [Alternative Fuel Retrofit Systems](https://ww3.arb.ca.gov/msprog/aftermkt/altfuel/altfuel.htm) website. A hybrid electric vehicle that is Model Year 2000 or newer and is a passenger car, light-duty truck, or medium-duty vehicle may be converted to incorporate off-vehicle charging capability if the manufacturer demonstrates compliance with emissions, warranty, and durability requirements. ARB issues certification to the manufacturer and the vehicle must meet California emissions standards for the model year of the original vehicle. (Reference [California Code of Regulations](http://www.oal.ca.gov/) Title 13, Section 2030-2032, and [California Vehicle Code](http://www.oal.ca.gov/) 27156) | I55: FALSE | J55: 240 | K55: Laws and Regulations | R55: AFTMKTCONV|BIOD|ETH|ELEC|HEV|HY|NG|PHEV|LPG | T55: AIRQEMISSIONS | U55: MAN|FLEET|GOV|IND | V55: http://www.oal.ca.gov/
A56: 6492 | B56: N | D56: CA | E56: Vehicle Acquisition and Petroleum Reduction Requirements | F56: The California Department of General Services (DGS) is responsible for maintaining specifications and standards for passenger cars and light-duty trucks that are purchased or leased for state office, agency, and department use. These specifications include minimum vehicle emissions standards and encourage the purchase or lease of fuel-efficient and alternative fuel vehicles (AFVs). Specifically, DGS must reduce or displace the fleet\'s consumption of petroleum products by 20% by January 1, 2020, as compared to the 2003 consumption level. Beginning in fiscal year 2024, DGS must also ensure that at least 50% of the light-duty vehicles purchased by the state are zero emission vehicles (ZEVs). Further, at least 15% of DGS\' fleet of new vehicles with a gross vehicle weight rating of 19,000 pounds or more must be ZEVs by 2025, and at least 30% by 2030. On an annual basis, DGS must compile information including, but not limited to, the number of AFVs and hybrid electric vehicles acquired, the locations of the alternative fuel pumps available for those vehicles, and the total amount of alternative fuels used. Vehicles the state owns or leases that are capable of operating on alternative fuel must operate on that fuel unless the alternative fuel is not available. DGS is also required to: - Take steps to transfer vehicles between agencies and departments to ensure that the most fuel-efficient vehicles are used and to eliminate the least fuel-efficient vehicles from the state\'s motor vehicle fleet; - Submit annual progress reports to the California Department of Finance, related legislative committees, and the general public via the DGS website; - Encourage other agencies to operate AFVs on the alternative fuel for which they are designed, to the extent feasible; - Encourage the development of commercial fueling infrastructure at or near state vehicle fueling or parking sites; - Work with other agencies to incentivize and promote state employee use of AFVs through preferential or reduced-cost parking, access to electric vehicle charging, or other means, to the extent feasible; and - Establish a more stringent fuel economy standard than the 2007 standard. (Reference [California Public Resources Code](http://www.oal.ca.gov/) 25722.5-25722.11 and 25724) | G56: 2012-09-27 00:00:00 UTC | H56: 2017-10-10 00:00:00 UTC | I56: FALSE | J56: 270 | K56: Laws and Regulations | M56: 2017-11-08 19:11:57 UTC | R56: BIOD|ETH|ELEC|EFFEC|HEV|HY|NG|PHEV|LPG | T56: REQ | U56: GOV | V56: http://www.documents.dgs.ca.gov/ofa/eos-14-09.pdf|http://www.oal.ca.gov/|http://leginfo.legislature.ca.gov|http://leginfo.legislature.ca.gov
A57: 6493 | B57: N | D57: CA | E57: Low Emission Vehicle (LEV) Standards | F57: California\'s LEV II exhaust emissions standards apply to Model Year (MY) 2004 and subsequent model year passenger cars, light-duty trucks, and medium-duty passenger vehicles meeting specified exhaust standards. The LEV II standards represent the maximum exhaust emissions for LEVs, Ultra LEVs, and Super Ultra LEVs, including flexible fuel, bi-fuel, and dual-fuel vehicles when operating on an alternative fuel. MY 2009 and subsequent model year passenger cars, light-duty trucks, and medium-duty passenger vehicles must meet specified fleet average greenhouse gas (GHG) exhaust emissions requirements. Each manufacturer must comply with these fleet average GHG requirements, which are based on California Air Resources Board (ARB) calculations. Bi-fuel, flexible fuel, dual-fuel, and grid-connected hybrid electric vehicles may be eligible for an alternative compliance method. In December 2012, ARB finalized regulatory requirements, referred to as LEV III, which allow vehicle manufacturer compliance with the U.S. Environmental Protection Agency\'s GHG requirements for MY 2017-2025 to serve as compliance with California\'s adopted GHG emissions requirements for those same model years. For more information, see the ARB [LEVII](http://www.arb.ca.gov/msprog/levprog/levii/levii.htm) and [LEV III](https://www.arb.ca.gov/msprog/levprog/leviii/leviii.htm) Program websites for more information. (Reference [California Code of Regulations](http://www.oal.ca.gov/) Title 13, Section 1961-1961.3) | H57: 2012-08-01 00:00:00 UTC | I57: FALSE | J57: 233 | K57: Laws and Regulations | R57: BIOD|ETH|ELEC|HEV|HY|NG|PHEV|LPG | T57: AIRQEMISSIONS | U57: MAN | V57: http://www.oal.ca.gov/
A58: 6614 | B58: N | D58: CA | E58: Plug-In Electric Vehicle (PEV) and Natural Gas Infrastructure Charging Rate Reduction - SDG&E | F58: San Diego Gas & Electric (SDG&E) offers three PEV Time-of-Use (TOU) rates to customers, using a single meter or requiring the installation of a second meter. Lower natural gas rates are available to customers who own a natural gas vehicle (NGV) and use a qualified compressed natural gas fueling appliance at home. For more information about rates, see the SDG&E [EV Plans](https://www.sdge.com/residential/pricing-plans/about-our-pricing-plans/electric-vehicle-plans) and [NGV Rates](http://regarchive.sdge.com/tm2/pdf/GAS_GAS-SCHEDS_G-NGV.pdf) websites. | I58: FALSE | J58: 153 | K58: Utility/Private Incentives | R58: ELEC|NG|PHEV | S58: OTHER | U58: STATION|IND
A59: 6615 | B59: N | D59: CA | E59: Plug-In Electric Vehicle (PEV) Charging Requirements | F59: New PEVs must be equipped with a conductive charger inlet port that meets the specifications contained in Society of Automotive Engineers (SAE) standard J1772. PEVs must be equipped with an on-board charger with a minimum output of 3.3 kilowatts (kW). These requirements do not apply to PEVs that are only capable of Level 1 charging, which has a maximum power of 12 amperes (amps), a branch circuit rating of 15 amps, and continuous power of 1.44 kW. (Reference [California Code of Regulations](http://www.oal.ca.gov/) Title 13, Section 1962.3) | G59: 2009-10-11 00:00:00 UTC | I59: FALSE | J59: 220 | K59: Laws and Regulations | R59: ELEC|PHEV | T59: OTHER | U59: MAN | V59: http://www.oal.ca.gov/
A60: 6619 | B60: N | D60: CA | E60: State Transportation Plan | F60: The California Department of Transportation (Caltrans) must update the California Transportation Plan (Plan) by December 31, 2020, and every five years thereafter. The Plan must address how the state will achieve maximum feasible emissions reductions, taking into consideration the use of alternative fuels, new vehicle technology, and tailpipe emissions reductions. Caltrans must consult and coordinate with related state agencies, air quality management districts, public transit operators, and regional transportation planning agencies. Caltrans must also provide an opportunity for general public input. Caltrans must submit a final draft of the Plan to the legislature and governor. A copy of the 2016 report is available on the [Caltrans](http://www.dot.ca.gov/hq/tpp/californiatransportationplan2040/) website. Caltrans must also review the Plan and prepare a report for the legislature and governor that includes actionable, programmatic transportation system improvement recommendations every five years. (Reference [California Government Code](http://www.oal.ca.gov/) 65070-65073) | G60: 2009-10-11 00:00:00 UTC | I60: FALSE | J60: 231 | K60: Laws and Regulations | R60: BIOD|ETH|ELEC|HY|NG|PHEV|LPG | T60: REQ | U60: OTHER | V60: http://www.oal.ca.gov/
A61: 8160 | B61: Y | C61: Y | D61: CA | E61: Low Emission Truck and Bus Purchase Vouchers | F61: Through the Hybrid and Zero Emission Truck and Bus Voucher Incentive Project (HVIP) and Low NOx Engine Incentives, the California Air Resources Board provides vouchers to eligible fleets to reduce the incremental cost of qualified electric, hybrid, or natural gas trucks and buses at the time of purchase. Vouchers are available on a first-come, first-served basis. Only fleets that operate vehicles in California are eligible. Voucher amounts vary depending on whether the vehicles are located in a disadvantaged community. For more information, including a list of qualified vehicles and other requirements, see the [HVIP](http://www.californiahvip.org/) website. | G61: 2010-02-01 00:00:00 UTC | I61: FALSE | J61: 10 | K61: State Incentives | M61: 2018-08-23 20:32:57 UTC | R61: ELEC|HEV|NG|PHEV | S61: OTHER|RBATE | U61: FLEET
A62: 8161 | B62: N | D62: CA | E62: Plug-In Hybrid and Zero Emission Light-Duty Vehicle Rebates | F62: The Clean Vehicle Rebate Project (CVRP) offers rebates for the purchase or lease of qualified vehicles. Qualified vehicles are light-duty electric vehicles (EVs), fuel cell electric vehicles (FCEVs), and plug-in hybrid electric vehicles (PHEVs) the California Air Resources Board (ARB) has approved or certified. The rebates are for up to \$4,500 for FCEVs, \$2,000 for EVs, \$1,000 for PHEVs, and \$750 for zero emission motorcycles. Rebates are available on a first-come, first-served basis to individuals, business owners, and government entities in California that purchase or lease new eligible vehicles. Residents of San Diego County may be eligible for a preapproved rebate through the CVRP [Rebate Now](https://cleanvehiclerebate.org/eng/rebatenow) pilot. Manufacturers must apply to ARB to have their vehicles included in the CVRP. Individuals are eligible for the rebate based on gross annual income, as stated on the individual\'s federal tax return. Individuals with a gross annual income above the following thresholds are eligible for all rebates except those that apply to FCEVs: - \$150,000 for single filers - \$204,000 for head-of-household filers - \$300,000 for joint filers For individuals with low and moderate household incomes of less than or equal to 300% of the federal poverty level, rebates are increased by \$2,500. Increased rebates are available for ARB-approved FCEVs, PHEVs, and PEVs. ARB must provide outreach to low income households and communities to raise awareness about CVRP. Through January 1, 2022, ARB must prioritize rebate payments for low income applicants. ARB determines annual funding amounts for the CVRP, which is expected to be effective through 2023. For more information, including information on income verification, a list of eligible vehicles, and instructions on how to apply, see the [CVRP](https://cleanvehiclerebate.org/eng) website. (Reference [California Health and Safety Code](https://oal.ca.gov/) 44274 and 44258) | G62: 2010-03-15 00:00:00 UTC | H62: 2018-09-13 00:00:00 UTC | I62: FALSE | J62: 12 | K62: State Incentives | M62: 2019-12-10 14:35:57 UTC | R62: ELEC|HY|NEVS|PHEV | S62: RBATE | U62: FLEET|GOV|IND | V62: http://www.oal.ca.gov/|http://www.oal.ca.gov/|http://leginfo.legislature.ca.gov/faces/home.xhtml
A63: 8821 | B63: Y | C63: Y | D63: CA | E63: Advanced Transportation Tax Exclusion | F63: The California Alternative Energy and Advanced Transportation Financing Authority (CAEATFA) provides a sales and use tax exclusion for qualified manufacturers of advanced transportation products, components, or systems that reduce pollution and energy use and promote economic development. Incentives are available until December 31, 2025. For more information, including application materials, see the CAEATFA [Sales and Use Tax Exclusion Program](http://www.treasurer.ca.gov/caeatfa/ste/index.asp) website. (Reference [California Public Resources Code](http://www.oal.ca.gov/) 26000-26017) | G63: 2010-03-24 00:00:00 UTC | H63: 2015-10-12 00:00:00 UTC | I63: FALSE | J63: 55 | K63: State Incentives | M63: 2015-11-09 22:13:31 UTC | R63: ELEC|HY|OTHER|PHEV | S63: EXEM|TAX | U63: MAN|OTHER | V63: http://www.oal.ca.gov/
A64: 8842 | B64: N | D64: CA | E64: Plug-In Electric Vehicle (PEV) Infrastructure Information Resource | F64: The California Energy Commission, in consultation with the Public Utilities Commission, must develop and maintain a website containing specific links to electrical corporations, local publicly owned electric utilities, and other websites that contain information specific to PEVs, including the following: - Resources to help consumers determine if their residences will require utility service upgrades to accommodate PEVs; - Basic charging circuit requirements; - Utility rate options; and - Load management techniques. (Reference [California Public Resources Code](http://www.oal.ca.gov/) 25227) | G64: 2010-09-27 00:00:00 UTC | I64: FALSE | J64: 197 | K64: Laws and Regulations | R64: ELEC|PHEV | T64: OTHER | U64: OTHER | V64: http://www.oal.ca.gov/
A65: 9232 | B65: Y | C65: Y | D65: CA | E65: Electric Vehicle Supply Equipment (EVSE) Rebate - LADWP | F65: The Los Angeles Department of Water and Power (LADWP) provides rebates to commercial customers toward the purchase of Level 2 or direct current (DC) fast EVSE. Commercial customers who purchase and install EVSE for employee and public use can receive up to \$5,000 for each Level 2 EVSE with up to \$500 in additional rebate funds per extra charge port. Commercial customers may also receive up to \$75,000 per DC fast EVSE, and up to \$125,000 per DC fast EVSE for medium- and heavy-duty vehicle use. Eligible customers may qualify for up to 40 rebate awards depending on the number of parking spaces at the installation site. EVSE must be installed within the LADWP service area. Rebates are available on a first-come, first-served basis. For program guidelines and application materials, see the [Charge Up L.A.!](https://www.ladwp.com/ladwp/faces/ladwp/residential/r-gogreen/r-gg-driveelectric?_adf.ctrl-state=1d4357epvd_4&_afrLoop=472125629767806) website. | G65: 2010-05-01 00:00:00 UTC | H65: 2015-10-01 00:00:00 UTC | I65: FALSE | J65: 137 | K65: Utility/Private Incentives | M65: 2020-11-13 15:48:37 UTC | R65: ELEC|PHEV | S65: RBATE | U65: STATION|FLEET|GOV|IND
A66: 9573 | B66: Y | C66: Y | D66: CA | E66: Alternative Fuel Vehicle (AFV) Incentives - San Joaquin Valley | F66: The San Joaquin Valley Air Pollution Control District administers the Public Benefit Grant Program, which provides funding to cities, counties, special districts (such as water districts and irrigation districts), and public educational institutions for the purchase of new AFVs, including electric, hybrid electric, natural gas, and propane vehicles. The maximum grant amount allowed per vehicle is \$20,000, with a limit of \$100,000 per agency per year. Projects are considered on a first-come, first-serve basis. For more information, see the [Public Benefit Grant Program](http://valleyair.org/grants/content/publicbenefit.html) website. | I66: FALSE | J66: 95 | K66: State Incentives | R66: ELEC|NG|PHEV|LPG | S66: GNT | U66: STATION|FLEET|GOV
A67: 9578 | B67: N | D67: CA | E67: Public Utility Definition | F67: A corporation or individual that owns, controls, operates, or manages a facility that supplies electricity to the public exclusively to charge light-, medium-, and heavy-duty all-electric and plug-in hybrid electric vehicles, compressed natural gas to fuel natural gas vehicles, or hydrogen as a motor vehicle fuel is not defined as a public utility. (Reference [California Public Utilities](http://www.oal.ca.gov/) Decision 20-09-025, 2020 and [California Public Utilities Code](http://www.oal.ca.gov/) 216) | G67: 2011-10-06 00:00:00 UTC | H67: 2015-09-15 00:00:00 UTC | I67: FALSE | J67: 184 | K67: Laws and Regulations | M67: 2015-11-09 23:23:05 UTC | R67: ELEC|HY|NG|PHEV | T67: UTILITY | U67: STATION | V67: http://www.oal.ca.gov/
A68: 9579 | B68: N | D68: CA | E68: Electric Vehicle Supply Equipment (EVSE) Policies for Multi-Unit Dwellings | F68: A common interest development, including a community apartment, condominium, and cooperative development, may not prohibit or restrict the installation or use of EVSE or a plug-in electric vehicle (PEV)-dedicated time-of-use (TOU) meter in a homeowner\'s designated parking space or unit. These entities may put reasonable restrictions on EVSE, but the policies may not significantly increase the cost of the EVSE or significantly decrease its efficiency or performance. Restrictions may be placed on TOU meter installations if they are based on the structure of or available space in the building. If installation in the homeowner\'s designated parking space or unit is not possible, with authorization, the homeowner may add EVSE or a PEV-dedicated TOU meter in a common area. The homeowner must obtain appropriate approvals from the common interest development association and agree in writing to comply with applicable architectural standards, engage a licensed installation contractor, provide a certificate of insurance, and pay for the electricity usage, maintenance, and other costs associated with the EVSE or TOU meter. Any application for approval should be processed by the common interest development association without willful avoidance or delay. The homeowner and each successive homeowner of the parking space or unit equipped with EVSE or a TOU meter is responsible for the cost of the installation, maintenance, repair, removal, or replacement of the equipment, as well as any resulting damage to the EVSE, TOU meter, or surrounding area. The homeowner must also maintain a \$1 million umbrella liability coverage policy and name the common interest development as an additional insured entity under the policy. If EVSE or a PEV-dedicated TOU meter is installed in a common area for use by all members of the association, the common interest development must develop terms for use of the EVSE or TOU meter. (Reference [California Civil Code](http://www.oal.ca.gov/) 4745 and 6713) | G68: 2011-07-25 00:00:00 UTC | H68: 2018-09-13 00:00:00 UTC | I68: FALSE | J68: 192 | K68: Laws and Regulations | M68: 2018-11-13 18:16:25 UTC | R68: ELEC|PHEV | T68: OTHER | U68: MUD|IND | V68: http://www.legislature.ca.gov/|http://www.oal.ca.gov/|http://www.legislature.ca.gov/
A69: 9580 | B69: N | D69: CA | E69: Access to Plug-In Electric Vehicle (PEV) Registration Records | F69: The California Department of Motor Vehicles may disclose to an electrical corporation or local publicly owned utility a PEV owner's address and vehicle type if the information is used exclusively to identify where the PEV is registered. (Reference [California Vehicle Code](http://www.oal.ca.gov/) 1808.23) | G69: 2011-09-27 00:00:00 UTC | I69: FALSE | J69: 195 | K69: Laws and Regulations | R69: ELEC|PHEV | T69: OTHER | U69: OTHER | V69: http://www.oal.ca.gov/
A70: 9892 | B70: N | D70: CA | E70: Alternative Fuel and Advanced Vehicle Rebate - San Joaquin Valley | F70: The San Joaquin Valley Air Pollution Control District (SJVAPCD) administers the Drive Clean! Rebate Program, which provides rebates for the purchase or lease of eligible new vehicles, including qualified natural gas, hydrogen fuel cell, propane, all-electric, plug-in electric vehicles, and zero emission motorcycles. The program offers rebates of up to \$3,000, which are available on a first-come, first-served basis for residents and businesses located in the SJVAPCD. For more information, including a list of eligible vehicles and other requirements, see the SJVAPCD [Drive Clean! Rebate Program](http://valleyair.org/drivecleaninthesanjoaquin/rebate/) website. | I70: FALSE | J70: 90 | K70: State Incentives | R70: ELEC|HY|NG|PHEV | S70: RBATE | U70: FLEET|IND
A71: 10212 | B71: N | D71: CA | E71: Zero Emission Vehicle (ZEV) Promotion Plan | F71: All California state agencies must support and facilitate the rapid commercialization of ZEVs in California. In particular, the Air Resources Board, Energy Commission (CEC), Public Utilities Commission, and other relevant state agencies must work with the private sector to establish benchmarks to achieve targets for ZEV commercialization and deployment. These targets include: - By 2020, the state will have established adequate infrastructure to support one million ZEVs; - By 2025, there will be 1.5 million ZEVs on the road in California and clean, efficient vehicles will displace 1.5 billion gallons of petroleum fuels annually; - By 2025, there will be 200 hydrogen fueling stations and 250,000 plug-in electric vehicle (PEV) chargers, including 10,000 direct current fast chargers, in California; - By 2030, there will be 5 million ZEVs on the road in California; and - By 2050, greenhouse gas emissions from the transportation sector will be 80% less than 1990 levels. State agencies must also work with their stakeholders to accomplish the following: - Develop new criteria for clean vehicle incentive programs to encourage manufacturers to produce clean, affordable cars; - Update the 2016 ZEV Action plan, with a focus on low income and disadvantaged communities; - Recommend actions to increase the deployment of ZEV infrastructure through the Low Carbon Fuel Standard; - Support and recommend policies that will facilitate the installation of PEV infrastructure in homes and businesses; and - Ensure PEV charging and hydrogen fueling are affordable and accessible to all drivers. The ZEV promotion plan additionally directs the state fleet to increase the number of ZEVs in the fleet through gradual vehicle replacement. By 2020, ZEVs should make up at least 25% of the fleet\'s light-duty vehicles. Vehicles with special performance requirements necessary for public safety and welfare are exempt from this requirement. For more information about the plan, see CEC\'s [ZEVs and Infrastructure Update](https://static.business.ca.gov/wp-content/uploads/2019/12/2018-ZEV-Action-Plan-Priorities-Update.pdf). (Reference [Executive Orders](https://www.gov.ca.gov/category/executive-orders/) N-19-19, 2019, B-48, 2018, and B-16, 2012) | G71: 2012-03-23 00:00:00 UTC | H71: 2018-01-26 00:00:00 UTC | I71: FALSE | J71: 215 | K71: Laws and Regulations | M71: 2019-11-11 21:49:02 UTC | R71: ELEC|HY|PHEV | T71: REQ|AIRQEMISSIONS | U71: GOV | V71: http://gov.ca.gov/s_executiveorders.php|http://gov.ca.gov/s_executiveorders.php|http://gov.ca.gov/s_executiveorders.php
A72: 10393 | B72: N | D72: CA | E72: Alternative Fuel Vehicle (AFV) Parking Incentive Programs | F72: The California Department of General Services (DGS) and California Department of Transportation (DOT) must develop and implement AFV parking incentive programs in public parking facilities operated by DGS with 50 or more parking spaces and park-and-ride lots owned and operated by DOT. The incentives must provide meaningful and tangible benefits to drivers, such as preferential spaces, reduced fees, and fueling infrastructure. Fueling infrastructure built at park-and-ride lots is not subject to restricted use by those using bicycles, public transit, or ridesharing. (Reference [California Public Resources Code](http://www.oal.ca.gov/) 25722.9) | G72: 2012-09-27 00:00:00 UTC | I72: FALSE | J72: 180 | K72: Laws and Regulations | R72: BIOD|ETH|ELEC|HEV|HY|NG|PHEV|LPG | T72: OTHER | U72: STATION|FLEET|IND | V72: http://www.oal.ca.gov/
A73: 11067 | B73: N | D73: CA | E73: Electric Vehicle Supply Equipment (EVSE) Open Access Requirements | F73: EVSE service providers may not charge a subscription fee or require membership for use of their public charging stations. In addition, providers must disclose the actual charges for using public EVSE at the point of sale; allow at least two options for payment; install the Open Charge Point interoperability billing standard on each EVSE; and disclose the EVSE geographic location, schedule of fees, accepted methods of payment, and network roaming charges to the National Renewable Energy Laboratory. Exceptions apply. For more information, see the [ARB EVSE Standards](http://www.oal.ca.gov/) website. (Reference [California Health and Safety Code](http://www.oal.ca.gov/) 44268 and 44268.2) | G73: 2013-09-28 00:00:00 UTC | I73: FALSE | J73: 175 | K73: Laws and Regulations | R73: ELEC|PHEV | T73: OTHER | U73: STATION|FLEET | V73: http://www.oal.ca.gov/
A74: 11068 | B74: N | D74: CA | E74: Mandatory Electric Vehicle Supply Equipment (EVSE) Building Standards | F74: The California Building Standards Commission (Commission) published mandatory building standards for EVSE installation in parking spaces at one- and two-family dwellings with attached private garages, multi-family dwellings, and non-residential developments in the California Green Building Standards Code within the California Building Standards Code. For more information, see the [California Building Codes Standards Commission](http://www.bsc.ca.gov/Codes.aspx) website. (Reference [California Health and Safety Code](http://www.oal.ca.gov/) 18941.10) | G74: 2013-09-28 00:00:00 UTC | I74: FALSE | J74: 173 | K74: Laws and Regulations | R74: ELEC|PHEV | T74: OTHER | U74: STATION|IND | V74: http://www.oal.ca.gov/
A75: 11484 | B75: N | D75: CA | E75: Zero Emission Vehicle (ZEV) Deployment Support | F75: California joined Connecticut, Maine, Maryland, Massachusetts, New Jersey, New York, Oregon, Rhode Island, and Vermont in signing a [memorandum of understanding](https://www.nescaum.org/documents/zev-mou-10-governors-signed-20191120.pdf/%20) (MOU) to support the deployment of ZEVs through involvement in a ZEV Program Implementation Task Force (Task Force). In May 2014, the Task Force published a [ZEV Action Plan](https://www.nescaum.org/documents/multi-state-zev-action-plan.pdf) (Plan) identifying 11 priority actions to accomplish the goals of the MOU, including deploying at least 3.3 million ZEVs and adequate fueling infrastructure within the signatory states by 2025. The Plan also includes a research agenda to inform future actions. On an annual basis, each state must report on the number of registered ZEVs, the number of public electric vehicle supply equipment (EVSE) and hydrogen fueling stations, and available information regarding workplace fueling for ZEVs. In June 2018, the Task Force published a new [ZEV Action Plan](https://www.nescaum.org/documents/2018-zev-action-plan.pdf) for 2018-2021. Building on the 2014 Action Plan, the 2018 Action Plan makes recommendations for states and other key partners in five priority areas: - Raising consumer awareness and interest in electric vehicle technology; - Building out a reliable and convenient residential, workplace and public charging/fueling infrastructure network; - Continuing and improving access to consumer purchase and non-financial incentives; - Expanding public and private sector fleet adoption; and - Supporting dealership efforts to increase ZEV sales. For more information, see the [Multi-State ZEV Task Force](https://www.nescaum.org/topics/zero-emission-vehicles) website. | G75: 2013-10-24 00:00:00 UTC | H75: 2014-05-31 00:00:00 UTC | I75: FALSE | J75: 216 | K75: Laws and Regulations | M75: 2018-06-25 19:45:05 UTC | R75: ELEC|HY|PHEV | T75: AIRQEMISSIONS | U75: OTHER
A76: 11528 | B76: Y | C76: Y | D76: CA | E76: Establishment of a Zero Emission Medium- and Heavy-Duty Vehicle Program | F76: The California Clean Truck, Bus, and Off-Road Vehicle and Equipment Technology Program (Program) will provide funding for development, demonstration, pre-commercial pilot, and early commercial implementation projects for zero and near-zero emission trucks, buses, and off-road vehicles and equipment. Eligible projects include, but are not limited to, the following: - Technology development, demonstration, pre-commercial pilots, and early commercial implementation projects for zero and near-zero emission truck technology; - Zero and near-zero emission bus technology development, demonstration, pre-commercial pilots, and early commercial deployments, including pilots of multiple vehicles at one site or region; - Purchase incentives for commercially available zero and near-zero emission truck, bus, and off-road vehicle and equipment technologies and fueling infrastructure; and - Projects that support greater commercial motor vehicle and equipment freight efficiency and greenhouse gas emissions reductions, including autonomous vehicles, grid integration technology, and charge management solutions. Remanufactured and retrofitted vehicles meeting warranty and emissions requirements may also qualify for funding. The Program is expected to provide \$12 million to \$20 million in funding annually through December 31, 2021. At least 20% of allocated funds must go towards early commercial deployment of eligible vehicles and equipment. The California Air Resources Board and the State Energy Resources Conservation and Development Commission will develop and administer the Program. (Reference [California Health and Safety Code](http://www.oal.ca.gov/) 39719.2) | G76: 2014-09-21 00:00:00 UTC | H76: 2018-09-22 00:00:00 UTC | I76: FALSE | J76: 166 | K76: Laws and Regulations | M76: 2018-11-13 17:25:10 UTC | R76: AUTONOMOUS|ELEC|HY|PHEV | T76: OTHER | U76: FLEET|GOV|IND | V76: http://www.oal.ca.gov/|http://leginfo.legislature.ca.gov/faces/home.xhtml
A77: 11529 | B77: Y | D77: CA | E77: Zero Emission Vehicle (ZEV) Initiative | F77: The California Air Resources Board\'s (ARB) Charge Ahead California Initiative was established to help place into service at least 1 million ZEVs and near-zero emission vehicles in California by January 1, 2023. In consultation with the State Energy Resources Conservation and Development Commission, ARB prepared a [funding plan](https://ww2.arb.ca.gov/sites/default/files/2019-09/fy1920fundingplan.pdf) that includes a market and technology assessment, assessments of existing zero and near-zero emission funding programs, and programs that increase access to disadvantaged, low-income, and moderate-income communities and consumers. Potential programs under the initiative include those involving innovative financing, car sharing, charging infrastructure in multi-unit dwellings located in disadvantaged communities, public transit, and agricultural vanpool programs. The funding plan must be updated at least every three years through January 1, 2023. (Reference [California Health and Safety Code](http://www.oal.ca.gov/) 44258.4) | G77: 2014-09-21 00:00:00 UTC | H77: 2018-09-13 00:00:00 UTC | I77: FALSE | J77: 168 | K77: Laws and Regulations | M77: 2018-11-13 17:29:47 UTC | R77: ELEC|HY|OTHER|PHEV | T77: AIRQEMISSIONS | U77: OTHER | V77: http://www.oal.ca.gov/|http://leginfo.legislature.ca.gov/faces/home.xhtml
